Workbook
Name BillingsThreshold_North: 'KPI Dashboard North'!$Q$17:$U$20
Name BillingsThreshold_OT: 'KPI Dashboard OT'!$Q$15:$U$18
Name BillingsThreshold_South: 'KPI Dashboard South'!$Q$15:$U$18
Name CeasedThreshold_North: 'KPI Dashboard North'!$Q$26:$U$28
Name CeasedThreshold_South: 'KPI Dashboard South'!$Q$24:$U$26
Name MMP_KPI: 'MMP Dashboard'!$C$32:$H$36
Name TeamKPI_North: 'KPI Dashboard North'!$Q$7:$W$12
Name TeamKPI_OT: 'KPI Dashboard OT'!$Q$7:$W$10
Name TeamKPI_South: 'KPI Dashboard South'!$Q$7:$W$10

Sheet MMP Dashboard
A2: #VALUE! | C2: Melbourne Mobile Physio
A10: South | C10: Team Average | D10: Jan | E10: Feb | F10: Mar | G10: Apr | H10: May | I10: June | J10: July | K10: Aug | L10: Sept | M10: Oct | N10: Nov | O10: Dec | P10: Average
C11: Billings | D11: =IF(SUMIFS(FTETable[Jan], FTETable[Team], "Physio_South")=0, "", SUMIFS(FTETable[Jan], FTETable[Team], "Physio_South") / SUMIFS(FTETable[FTE], FTETable[Team], "Physio_South", FTETable[Jan], ">0")) | E11: =IF(SUMIFS(FTETable[Feb], FTETable[Team], "Physio_South")=0, "", SUMIFS(FTETable[Feb], FTETable[Team], "Physio_South") / SUMIFS(FTETable[FTE], FTETable[Team], "Physio_South", FTETable[Feb], ">0")) | F11: =IF(SUMIFS(FTETable[Mar], FTETable[Team], "Physio_South")=0, "", SUMIFS(FTETable[Mar], FTETable[Team], "Physio_South") / SUMIFS(FTETable[FTE], FTETable[Team], "Physio_South", FTETable[Mar], ">0")) | G11: =IF(SUMIFS(FTETable[Apr], FTETable[Team], "Physio_South")=0, "", SUMIFS(FTETable[Apr], FTETable[Team], "Physio_South") / SUMIFS(FTETable[FTE], FTETable[Team], "Physio_South", FTETable[Apr], ">0")) | H11: =IF(SUMIFS(FTETable[May], FTETable[Team], "Physio_South")=0, "", SUMIFS(FTETable[May], FTETable[Team], "Physio_South") / SUMIFS(FTETable[FTE], FTETable[Team], "Physio_South", FTETable[May], ">0")) | I11: =IF(SUMIFS(FTETable[June], FTETable[Team], "Physio_South")=0, "", SUMIFS(FTETable[June], FTETable[Team], "Physio_South") / SUMIFS(FTETable[FTE], FTETable[Team], "Physio_South", FTETable[June], ">0")) | J11: =IF(SUMIFS(FTETable[July], FTETable[Team], "Physio_South")=0, "", SUMIFS(FTETable[July], FTETable[Team], "Physio_South") / SUMIFS(FTETable[FTE], FTETable[Team], "Physio_South", FTETable[July], ">0")) | K11: =IF(SUMIFS(FTETable[Aug], FTETable[Team], "Physio_South")=0, "", SUMIFS(FTETable[Aug], FTETable[Team], "Physio_South") / SUMIFS(FTETable[FTE], FTETable[Team], "Physio_South", FTETable[Aug], ">0")) | L11: =IF(SUMIFS(FTETable[Sept], FTETable[Team], "Physio_South")=0, "", SUMIFS(FTETable[Sept], FTETable[Team], "Physio_South") / SUMIFS(FTETable[FTE], FTETable[Team], "Physio_South", FTETable[Sept], ">0")) | M11: =IF(SUMIFS(FTETable[Oct], FTETable[Team], "Physio_South")=0, "", SUMIFS(FTETable[Oct], FTETable[Team], "Physio_South") / SUMIFS(FTETable[FTE], FTETable[Team], "Physio_South", FTETable[Oct], ">0")) | N11: =IF(SUMIFS(FTETable[Nov], FTETable[Team], "Physio_South")=0, "", SUMIFS(FTETable[Nov], FTETable[Team], "Physio_South") / SUMIFS(FTETable[FTE], FTETable[Team], "Physio_South", FTETable[Nov], ">0")) | O11: =IF(SUMIFS(FTETable[Dec], FTETable[Team], "Physio_South")=0, "", SUMIFS(FTETable[Dec], FTETable[Team], "Physio_South") / SUMIFS(FTETable[FTE], FTETable[Team], "Physio_South", FTETable[Dec], ">0")) | P11: =IFERROR(AVERAGEIF(D11:O11, ">0"),"")
C12: Ceased Services | D12: =IFERROR(AVERAGE(Ceased_South[Jan]),"") | E12: =IFERROR(AVERAGE(Ceased_South[Feb]),"") | F12: =IFERROR(AVERAGE(Ceased_South[Mar]),"") | G12: =IFERROR(AVERAGE(Ceased_South[Apr]),"") | H12: =IFERROR(AVERAGE(Ceased_South[May]),"") | I12: =IFERROR(AVERAGE(Ceased_South[June]),"") | J12: =IFERROR(AVERAGE(Ceased_South[July]),"") | K12: =IFERROR(AVERAGE(Ceased_South[Aug]),"") | L12: =IFERROR(AVERAGE(Ceased_South[Sept]),"") | M12: =IFERROR(AVERAGE(Ceased_South[Oct]),"") | N12: =IFERROR(AVERAGE(Ceased_South[Nov]),"") | O12: =IFERROR(AVERAGE(Ceased_South[Dec]),"") | P12: =IFERROR(AVERAGEIF(D12:O12, ">0"),"")
C13: Documentation | D13: =IFERROR(AVERAGE(Documentation_South[Jan]),"") | E13: =IFERROR(AVERAGE(Documentation_South[Feb]),"") | F13: =IFERROR(AVERAGE(Documentation_South[Mar]),"") | G13: =IFERROR(AVERAGE(Documentation_South[Apr]),"") | H13: =IFERROR(AVERAGE(Documentation_South[May]),"") | I13: =IFERROR(AVERAGE(Documentation_South[June]),"") | J13: =IFERROR(AVERAGE(Documentation_South[July]),"") | K13: =IFERROR(AVERAGE(Documentation_South[Aug]),"") | L13: =IFERROR(AVERAGE(Documentation_South[Sept]),"") | M13: =IFERROR(AVERAGE(Documentation_South[Oct]),"") | N13: =IFERROR(AVERAGE(Documentation_South[Nov]),"") | O13: =IFERROR(AVERAGE(Documentation_South[Dec]),"") | P13: =IFERROR(AVERAGEIF(D13:O13, ">0"),"")
C14: Admin & Operational Efficiency | D14: =IFERROR(AVERAGE(Admin_South[Jan]),"") | E14: =IFERROR(AVERAGE(Admin_South[Feb]),"") | F14: =IFERROR(AVERAGE(Admin_South[Mar]),"") | G14: =IFERROR(AVERAGE(Admin_South[Apr]),"") | H14: =IFERROR(AVERAGE(Admin_South[May]),"") | I14: =IFERROR(AVERAGE(Admin_South[June]),"") | J14: =IFERROR(AVERAGE(Admin_South[July]),"") | K14: =IFERROR(AVERAGE(Admin_South[Aug]),"") | L14: =IFERROR(AVERAGE(Admin_South[Sept]),"") | M14: =IFERROR(AVERAGE(Admin_South[Oct]),"") | N14: =IFERROR(AVERAGE(Admin_South[Nov]),"") | O14: =IFERROR(AVERAGE(Admin_South[Dec]),"") | P14: =IFERROR(AVERAGEIF(D14:O14, ">0"),"")
C15: Attitude, Learning, Collaboration & Client Impact | D15: =IFERROR(AVERAGE(Attitude_South[Jan]),"") | E15: =IFERROR(AVERAGE(Attitude_South[Feb]),"") | F15: =IFERROR(AVERAGE(Attitude_South[Mar]),"") | G15: =IFERROR(AVERAGE(Attitude_South[Apr]),"") | H15: =IFERROR(AVERAGE(Attitude_South[May]),"") | I15: =IFERROR(AVERAGE(Attitude_South[June]),"") | J15: =IFERROR(AVERAGE(Attitude_South[July]),"") | K15: =IFERROR(AVERAGE(Attitude_South[Aug]),"") | L15: =IFERROR(AVERAGE(Attitude_South[Sept]),"") | M15: =IFERROR(AVERAGE(Attitude_South[Oct]),"") | N15: =IFERROR(AVERAGE(Attitude_South[Nov]),"") | O15: =IFERROR(AVERAGE(Attitude_South[Dec]),"") | P15: =IFERROR(AVERAGEIF(D15:O15, ">0"),"")
A17: North | C17: Team Average | D17: Jan | E17: Feb | F17: Mar | G17: Apr | H17: May | I17: June | J17: July | K17: Aug | L17: Sept | M17: Oct | N17: Nov | O17: Dec | P17: Average
C18: Billings | D18: =IF(SUMIFS(FTETable[Jan], FTETable[Team], "Physio_North")=0, "", SUMIFS(FTETable[Jan], FTETable[Team], "Physio_North") / SUMIFS(FTETable[FTE], FTETable[Team], "Physio_North", FTETable[Jan], ">0")) | E18: =IF(SUMIFS(FTETable[Feb], FTETable[Team], "Physio_North")=0, "", SUMIFS(FTETable[Feb], FTETable[Team], "Physio_North") / SUMIFS(FTETable[FTE], FTETable[Team], "Physio_North", FTETable[Feb], ">0")) | F18: =IF(SUMIFS(FTETable[Mar], FTETable[Team], "Physio_North")=0, "", SUMIFS(FTETable[Mar], FTETable[Team], "Physio_North") / SUMIFS(FTETable[FTE], FTETable[Team], "Physio_North", FTETable[Mar], ">0")) | G18: =IF(SUMIFS(FTETable[Apr], FTETable[Team], "Physio_North")=0, "", SUMIFS(FTETable[Apr], FTETable[Team], "Physio_North") / SUMIFS(FTETable[FTE], FTETable[Team], "Physio_North", FTETable[Apr], ">0")) | H18: =IF(SUMIFS(FTETable[May], FTETable[Team], "Physio_North")=0, "", SUMIFS(FTETable[May], FTETable[Team], "Physio_North") / SUMIFS(FTETable[FTE], FTETable[Team], "Physio_North", FTETable[May], ">0")) | I18: =IF(SUMIFS(FTETable[June], FTETable[Team], "Physio_North")=0, "", SUMIFS(FTETable[June], FTETable[Team], "Physio_North") / SUMIFS(FTETable[FTE], FTETable[Team], "Physio_North", FTETable[June], ">0")) | J18: =IF(SUMIFS(FTETable[July], FTETable[Team], "Physio_North")=0, "", SUMIFS(FTETable[July], FTETable[Team], "Physio_North") / SUMIFS(FTETable[FTE], FTETable[Team], "Physio_North", FTETable[July], ">0")) | K18: =IF(SUMIFS(FTETable[Aug], FTETable[Team], "Physio_North")=0, "", SUMIFS(FTETable[Aug], FTETable[Team], "Physio_North") / SUMIFS(FTETable[FTE], FTETable[Team], "Physio_North", FTETable[Aug], ">0")) | L18: =IF(SUMIFS(FTETable[Sept], FTETable[Team], "Physio_North")=0, "", SUMIFS(FTETable[Sept], FTETable[Team], "Physio_North") / SUMIFS(FTETable[FTE], FTETable[Team], "Physio_North", FTETable[Sept], ">0")) | M18: =IF(SUMIFS(FTETable[Oct], FTETable[Team], "Physio_North")=0, "", SUMIFS(FTETable[Oct], FTETable[Team], "Physio_North") / SUMIFS(FTETable[FTE], FTETable[Team], "Physio_North", FTETable[Oct], ">0")) | N18: =IF(SUMIFS(FTETable[Nov], FTETable[Team], "Physio_North")=0, "", SUMIFS(FTETable[Nov], FTETable[Team], "Physio_North") / SUMIFS(FTETable[FTE], FTETable[Team], "Physio_North", FTETable[Nov], ">0")) | O18: =IF(SUMIFS(FTETable[Dec], FTETable[Team], "Physio_North")=0, "", SUMIFS(FTETable[Dec], FTETable[Team], "Physio_North") / SUMIFS(FTETable[FTE], FTETable[Team], "Physio_North", FTETable[Dec], ">0")) | P18: =IFERROR(AVERAGEIF(D18:O18, ">0"),"")
C19: Ceased Services | D19: =IFERROR(AVERAGE(Ceased_North[Jan]),"") | E19: =IFERROR(AVERAGE(Ceased_North[Feb]),"") | F19: =IFERROR(AVERAGE(Ceased_North[Mar]),"") | G19: =IFERROR(AVERAGE(Ceased_North[Apr]),"") | H19: =IFERROR(AVERAGE(Ceased_North[May]),"") | I19: =IFERROR(AVERAGE(Ceased_North[June]),"") | J19: =IFERROR(AVERAGE(Ceased_North[July]),"") | K19: =IFERROR(AVERAGE(Ceased_North[Aug]),"") | L19: =IFERROR(AVERAGE(Ceased_North[Sept]),"") | M19: =IFERROR(AVERAGE(Ceased_North[Oct]),"") | N19: =IFERROR(AVERAGE(Ceased_North[Nov]),"") | O19: =IFERROR(AVERAGE(Ceased_North[Dec]),"") | P19: =IFERROR(AVERAGEIF(D19:O19, ">0"),"")
C20: Documentation | D20: =IFERROR(AVERAGE(Documentation_North[Jan]),"") | E20: =IFERROR(AVERAGE(Documentation_North[Feb]),"") | F20: =IFERROR(AVERAGE(Documentation_North[Mar]),"") | G20: =IFERROR(AVERAGE(Documentation_North[Apr]),"") | H20: =IFERROR(AVERAGE(Documentation_North[May]),"") | I20: =IFERROR(AVERAGE(Documentation_North[June]),"") | J20: =IFERROR(AVERAGE(Documentation_North[July]),"") | K20: =IFERROR(AVERAGE(Documentation_North[Aug]),"") | L20: =IFERROR(AVERAGE(Documentation_North[Sept]),"") | M20: =IFERROR(AVERAGE(Documentation_North[Oct]),"") | N20: =IFERROR(AVERAGE(Documentation_North[Nov]),"") | O20: =IFERROR(AVERAGE(Documentation_North[Dec]),"") | P20: =IFERROR(AVERAGEIF(D20:O20, ">0"),"")
C21: Admin & Operational Efficiency | D21: =IFERROR(AVERAGE(Admin_North[Jan]),"") | E21: =IFERROR(AVERAGE(Admin_North[Feb]),"") | F21: =IFERROR(AVERAGE(Admin_North[Mar]),"") | G21: =IFERROR(AVERAGE(Admin_North[Apr]),"") | H21: =IFERROR(AVERAGE(Admin_North[May]),"") | I21: =IFERROR(AVERAGE(Admin_North[June]),"") | J21: =IFERROR(AVERAGE(Admin_North[July]),"") | K21: =IFERROR(AVERAGE(Admin_North[Aug]),"") | L21: =IFERROR(AVERAGE(Admin_North[Sept]),"") | M21: =IFERROR(AVERAGE(Admin_North[Oct]),"") | N21: =IFERROR(AVERAGE(Admin_North[Nov]),"") | O21: =IFERROR(AVERAGE(Admin_North[Dec]),"") | P21: =IFERROR(AVERAGEIF(D21:O21, ">0"),"")
C22: Attitude, Learning, Collaboration & Client Impact | D22: =IFERROR(AVERAGE(Attitude_North[Jan]),"") | E22: =IFERROR(AVERAGE(Attitude_North[Feb]),"") | F22: =IFERROR(AVERAGE(Attitude_North[Mar]),"") | G22: =IFERROR(AVERAGE(Attitude_North[Apr]),"") | H22: =IFERROR(AVERAGE(Attitude_North[May]),"") | I22: =IFERROR(AVERAGE(Attitude_North[June]),"") | J22: =IFERROR(AVERAGE(Attitude_North[July]),"") | K22: =IFERROR(AVERAGE(Attitude_North[Aug]),"") | L22: =IFERROR(AVERAGE(Attitude_North[Sept]),"") | M22: =IFERROR(AVERAGE(Attitude_North[Oct]),"") | N22: =IFERROR(AVERAGE(Attitude_North[Nov]),"") | O22: =IFERROR(AVERAGE(Attitude_North[Dec]),"") | P22: =IFERROR(AVERAGEIF(D22:O22, ">0"),"")
A24: OT | C24: Team Average | D24: Jan | E24: Feb | F24: Mar | G24: Apr | H24: May | I24: June | J24: July | K24: Aug | L24: Sept | M24: Oct | N24: Nov | O24: Dec | P24: Average
C25: Billings | D25: =IF(SUMIFS(FTETable[Jan], FTETable[Team], "OT")=0, "", SUMIFS(FTETable[Jan], FTETable[Team], "OT") / SUMIFS(FTETable[FTE], FTETable[Team], "OT", FTETable[Jan], ">0")) | E25: =IF(SUMIFS(FTETable[Feb], FTETable[Team], "OT")=0, "", SUMIFS(FTETable[Feb], FTETable[Team], "OT") / SUMIFS(FTETable[FTE], FTETable[Team], "OT", FTETable[Feb], ">0")) | F25: =IF(SUMIFS(FTETable[Mar], FTETable[Team], "OT")=0, "", SUMIFS(FTETable[Mar], FTETable[Team], "OT") / SUMIFS(FTETable[FTE], FTETable[Team], "OT", FTETable[Mar], ">0")) | G25: =IF(SUMIFS(FTETable[Apr], FTETable[Team], "OT")=0, "", SUMIFS(FTETable[Apr], FTETable[Team], "OT") / SUMIFS(FTETable[FTE], FTETable[Team], "OT", FTETable[Apr], ">0")) | H25: =IF(SUMIFS(FTETable[May], FTETable[Team], "OT")=0, "", SUMIFS(FTETable[May], FTETable[Team], "OT") / SUMIFS(FTETable[FTE], FTETable[Team], "OT", FTETable[May], ">0")) | I25: =IF(SUMIFS(FTETable[June], FTETable[Team], "OT")=0, "", SUMIFS(FTETable[June], FTETable[Team], "OT") / SUMIFS(FTETable[FTE], FTETable[Team], "OT", FTETable[June], ">0")) | J25: =IF(SUMIFS(FTETable[July], FTETable[Team], "OT")=0, "", SUMIFS(FTETable[July], FTETable[Team], "OT") / SUMIFS(FTETable[FTE], FTETable[Team], "OT", FTETable[July], ">0")) | K25: =IF(SUMIFS(FTETable[Aug], FTETable[Team], "OT")=0, "", SUMIFS(FTETable[Aug], FTETable[Team], "OT") / SUMIFS(FTETable[FTE], FTETable[Team], "OT", FTETable[Aug], ">0")) | L25: =IF(SUMIFS(FTETable[Sept], FTETable[Team], "OT")=0, "", SUMIFS(FTETable[Sept], FTETable[Team], "OT") / SUMIFS(FTETable[FTE], FTETable[Team], "OT", FTETable[Sept], ">0")) | M25: =IF(SUMIFS(FTETable[Oct], FTETable[Team], "OT")=0, "", SUMIFS(FTETable[Oct], FTETable[Team], "OT") / SUMIFS(FTETable[FTE], FTETable[Team], "OT", FTETable[Oct], ">0")) | N25: =IF(SUMIFS(FTETable[Nov], FTETable[Team], "OT")=0, "", SUMIFS(FTETable[Nov], FTETable[Team], "OT") / SUMIFS(FTETable[FTE], FTETable[Team], "OT", FTETable[Nov], ">0")) | O25: =IF(SUMIFS(FTETable[Dec], FTETable[Team], "OT")=0, "", SUMIFS(FTETable[Dec], FTETable[Team], "OT") / SUMIFS(FTETable[FTE], FTETable[Team], "OT", FTETable[Dec], ">0")) | P25: =IFERROR(AVERAGEIF(D25:O25, ">0"),"")
C26: Operational Efficiency, Compliance & Admin Responsiveness | D26: =IFERROR(AVERAGE(Compliance_OT[Jan]),"") | E26: =IFERROR(AVERAGE(Compliance_OT[Feb]),"") | F26: =IFERROR(AVERAGE(Compliance_OT[Mar]),"") | G26: =IFERROR(AVERAGE(Compliance_OT[Apr]),"") | H26: =IFERROR(AVERAGE(Compliance_OT[May]),"") | I26: =IFERROR(AVERAGE(Compliance_OT[June]),"") | J26: =IFERROR(AVERAGE(Compliance_OT[July]),"") | K26: =IFERROR(AVERAGE(Compliance_OT[Aug]),"") | L26: =IFERROR(AVERAGE(Compliance_OT[Sept]),"") | M26: =IFERROR(AVERAGE(Compliance_OT[Oct]),"") | N26: =IFERROR(AVERAGE(Compliance_OT[Nov]),"") | O26: =IFERROR(AVERAGE(Compliance_OT[Dec]),"") | P26: =IFERROR(AVERAGEIF(D26:O26, ">0"),"")
C27: Client & Referrer Satisfaction | D27: =IFERROR(AVERAGE(ReferrerEng_OT[Jan]),"") | E27: =IFERROR(AVERAGE(ReferrerEng_OT[Feb]),"") | F27: =IFERROR(AVERAGE(ReferrerEng_OT[Mar]),"") | G27: =IFERROR(AVERAGE(ReferrerEng_OT[Apr]),"") | H27: =IFERROR(AVERAGE(ReferrerEng_OT[May]),"") | I27: =IFERROR(AVERAGE(ReferrerEng_OT[June]),"") | J27: =IFERROR(AVERAGE(ReferrerEng_OT[July]),"") | K27: =IFERROR(AVERAGE(ReferrerEng_OT[Aug]),"") | L27: =IFERROR(AVERAGE(ReferrerEng_OT[Sept]),"") | M27: =IFERROR(AVERAGE(ReferrerEng_OT[Oct]),"") | N27: =IFERROR(AVERAGE(ReferrerEng_OT[Nov]),"") | O27: =IFERROR(AVERAGE(ReferrerEng_OT[Dec]),"") | P27: =IFERROR(AVERAGEIF(D27:O27, ">0"),"")
C28: Capacity Building & Use of NDIS Funding | D28: =IFERROR(AVERAGE(Capacity_OT[Jan]),"") | E28: =IFERROR(AVERAGE(Capacity_OT[Feb]),"") | F28: =IFERROR(AVERAGE(Capacity_OT[Mar]),"") | G28: =IFERROR(AVERAGE(Capacity_OT[Apr]),"") | H28: =IFERROR(AVERAGE(Capacity_OT[May]),"") | I28: =IFERROR(AVERAGE(Capacity_OT[June]),"") | J28: =IFERROR(AVERAGE(Capacity_OT[July]),"") | K28: =IFERROR(AVERAGE(Capacity_OT[Aug]),"") | L28: =IFERROR(AVERAGE(Capacity_OT[Sept]),"") | M28: =IFERROR(AVERAGE(Capacity_OT[Oct]),"") | N28: =IFERROR(AVERAGE(Capacity_OT[Nov]),"") | O28: =IFERROR(AVERAGE(Capacity_OT[Dec]),"") | P28: =IFERROR(AVERAGEIF(D28:O28, ">0"),"")
C29: Team Contribution, Attitude & Clinical Growth | D29: =IFERROR(AVERAGE(Attitude_OT[Jan]),"") | E29: =IFERROR(AVERAGE(Attitude_OT[Feb]),"") | F29: =IFERROR(AVERAGE(Attitude_OT[Mar]),"") | G29: =IFERROR(AVERAGE(Attitude_OT[Apr]),"") | H29: =IFERROR(AVERAGE(Attitude_OT[May]),"") | I29: =IFERROR(AVERAGE(Attitude_OT[June]),"") | J29: =IFERROR(AVERAGE(Attitude_OT[July]),"") | K29: =IFERROR(AVERAGE(Attitude_OT[Aug]),"") | L29: =IFERROR(AVERAGE(Attitude_OT[Sept]),"") | M29: =IFERROR(AVERAGE(Attitude_OT[Oct]),"") | N29: =IFERROR(AVERAGE(Attitude_OT[Nov]),"") | O29: =IFERROR(AVERAGE(Attitude_OT[Dec]),"") | P29: =IFERROR(AVERAGEIF(D29:O29, ">0"),"")
D31: TEAM KPI'S
C32: Role | D32: Below | E32: Good | F32: Excellent
C33: Physiotherapists | D33: <5 | E33: 5-5.4 | F33: >5.4
C34: Occupational Therapists | D34: <4.3 | E34: 4.3-4.9 | F34: >4.9
C35: Other KPI's | D35: Unsatisfactory | E35: Needs improvement | F35: In progress | G35: Very Good | H35: Excellent
D36: <1.5 | E36: 1.5-2.5 | F36: 2.5-3.5 | G36: 3.5-4.5 | H36: 4.5-5

Sheet KPI Dashboard South
B2: Team South | C2: Beth | Y2: 5
Y3: 4
Y4: 3
Y5: 2
B6: Team Average | C6: Jan | D6: Feb | E6: Mar | F6: Apr | G6: May | H6: June | I6: July | J6: Aug | K6: Sept | L6: Oct | M6: Nov | N6: Dec | O6: Average | Q6: TEAM KPI'S | Y6: 1
B7: Billings | C7: =IF(SUMIFS(FTETable[Jan], FTETable[Team], "Physio_South")=0, "", SUMIFS(FTETable[Jan], FTETable[Team], "Physio_South") / SUMIFS(FTETable[FTE], FTETable[Team], "Physio_South", FTETable[Jan], ">0")) | D7: =IF(SUMIFS(FTETable[Feb], FTETable[Team], "Physio_South")=0, "", SUMIFS(FTETable[Feb], FTETable[Team], "Physio_South") / SUMIFS(FTETable[FTE], FTETable[Team], "Physio_South", FTETable[Feb], ">0")) | E7: =IF(SUMIFS(FTETable[Mar], FTETable[Team], "Physio_South")=0, "", SUMIFS(FTETable[Mar], FTETable[Team], "Physio_South") / SUMIFS(FTETable[FTE], FTETable[Team], "Physio_South", FTETable[Mar], ">0")) | F7: =IF(SUMIFS(FTETable[Apr], FTETable[Team], "Physio_South")=0, "", SUMIFS(FTETable[Apr], FTETable[Team], "Physio_South") / SUMIFS(FTETable[FTE], FTETable[Team], "Physio_South", FTETable[Apr], ">0")) | G7: =IF(SUMIFS(FTETable[May], FTETable[Team], "Physio_South")=0, "", SUMIFS(FTETable[May], FTETable[Team], "Physio_South") / SUMIFS(FTETable[FTE], FTETable[Team], "Physio_South", FTETable[May], ">0")) | H7: =IF(SUMIFS(FTETable[June], FTETable[Team], "Physio_South")=0, "", SUMIFS(FTETable[June], FTETable[Team], "Physio_South") / SUMIFS(FTETable[FTE], FTETable[Team], "Physio_South", FTETable[June], ">0")) | I7: =IF(SUMIFS(FTETable[July], FTETable[Team], "Physio_South")=0, "", SUMIFS(FTETable[July], FTETable[Team], "Physio_South") / SUMIFS(FTETable[FTE], FTETable[Team], "Physio_South", FTETable[July], ">0")) | J7: =IF(SUMIFS(FTETable[Aug], FTETable[Team], "Physio_South")=0, "", SUMIFS(FTETable[Aug], FTETable[Team], "Physio_South") / SUMIFS(FTETable[FTE], FTETable[Team], "Physio_South", FTETable[Aug], ">0")) | K7: =IF(SUMIFS(FTETable[Sept], FTETable[Team], "Physio_South")=0, "", SUMIFS(FTETable[Sept], FTETable[Team], "Physio_South") / SUMIFS(FTETable[FTE], FTETable[Team], "Physio_South", FTETable[Sept], ">0")) | L7: =IF(SUMIFS(FTETable[Oct], FTETable[Team], "Physio_South")=0, "", SUMIFS(FTETable[Oct], FTETable[Team], "Physio_South") / SUMIFS(FTETable[FTE], FTETable[Team], "Physio_South", FTETable[Oct], ">0")) | M7: =IF(SUMIFS(FTETable[Nov], FTETable[Team], "Physio_South")=0, "", SUMIFS(FTETable[Nov], FTETable[Team], "Physio_South") / SUMIFS(FTETable[FTE], FTETable[Team], "Physio_South", FTETable[Nov], ">0")) | N7: =IF(SUMIFS(FTETable[Dec], FTETable[Team], "Physio_South")=0, "", SUMIFS(FTETable[Dec], FTETable[Team], "Physio_South") / SUMIFS(FTETable[FTE], FTETable[Team], "Physio_South", FTETable[Dec], ">0")) | O7: =IFERROR(AVERAGEIF(C7:N7, ">0"),"") | Q7: Team Billings | S7: Below | T7: Good | U7: Excellent
B8: Ceased Services | C8: =IFERROR(AVERAGE(Ceased_South[Jan]),"") | D8: =IFERROR(AVERAGE(Ceased_South[Feb]),"") | E8: =IFERROR(AVERAGE(Ceased_South[Mar]),"") | F8: =IFERROR(AVERAGE(Ceased_South[Apr]),"") | G8: =IFERROR(AVERAGE(Ceased_South[May]),"") | H8: =IFERROR(AVERAGE(Ceased_South[June]),"") | I8: =IFERROR(AVERAGE(Ceased_South[July]),"") | J8: =IFERROR(AVERAGE(Ceased_South[Aug]),"") | K8: =IFERROR(AVERAGE(Ceased_South[Sept]),"") | L8: =IFERROR(AVERAGE(Ceased_South[Oct]),"") | M8: =IFERROR(AVERAGE(Ceased_South[Nov]),"") | N8: =IFERROR(AVERAGE(Ceased_South[Dec]),"") | O8: =IFERROR(AVERAGEIF(C8:N8, ">0"),"") | S8: <5 | T8: 5-5.4 | U8: >5.4
B9: Documentation | C9: =IFERROR(AVERAGE(Documentation_South[Jan]),"") | D9: =IFERROR(AVERAGE(Documentation_South[Feb]),"") | E9: =IFERROR(AVERAGE(Documentation_South[Mar]),"") | F9: =IFERROR(AVERAGE(Documentation_South[Apr]),"") | G9: =IFERROR(AVERAGE(Documentation_South[May]),"") | H9: =IFERROR(AVERAGE(Documentation_South[June]),"") | I9: =IFERROR(AVERAGE(Documentation_South[July]),"") | J9: =IFERROR(AVERAGE(Documentation_South[Aug]),"") | K9: =IFERROR(AVERAGE(Documentation_South[Sept]),"") | L9: =IFERROR(AVERAGE(Documentation_South[Oct]),"") | M9: =IFERROR(AVERAGE(Documentation_South[Nov]),"") | N9: =IFERROR(AVERAGE(Documentation_South[Dec]),"") | O9: =IFERROR(AVERAGEIF(C9:N9, ">0"),"") | Q9: Other KPI's | S9: Unsatisfactory | T9: Needs improvement | U9: In progress | V9: Very Good | W9: Excellent
B10: Admin & Operational Efficiency | C10: =IFERROR(AVERAGE(Admin_South[Jan]),"") | D10: =IFERROR(AVERAGE(Admin_South[Feb]),"") | E10: =IFERROR(AVERAGE(Admin_South[Mar]),"") | F10: =IFERROR(AVERAGE(Admin_South[Apr]),"") | G10: =IFERROR(AVERAGE(Admin_South[May]),"") | H10: =IFERROR(AVERAGE(Admin_South[June]),"") | I10: =IFERROR(AVERAGE(Admin_South[July]),"") | J10: =IFERROR(AVERAGE(Admin_South[Aug]),"") | K10: =IFERROR(AVERAGE(Admin_South[Sept]),"") | L10: =IFERROR(AVERAGE(Admin_South[Oct]),"") | M10: =IFERROR(AVERAGE(Admin_South[Nov]),"") | N10: =IFERROR(AVERAGE(Admin_South[Dec]),"") | O10: =IFERROR(AVERAGEIF(C10:N10, ">0"),"") | S10: <1.5 | T10: 1.5-2.5 | U10: 2.5-3.5 | V10: 3.5-4.5 | W10: 4.5-5
B11: Attitude, Learning, Collaboration & Client Impact | C11: =IFERROR(AVERAGE(Attitude_South[Jan]),"") | D11: =IFERROR(AVERAGE(Attitude_South[Feb]),"") | E11: =IFERROR(AVERAGE(Attitude_South[Mar]),"") | F11: =IFERROR(AVERAGE(Attitude_South[Apr]),"") | G11: =IFERROR(AVERAGE(Attitude_South[May]),"") | H11: =IFERROR(AVERAGE(Attitude_South[June]),"") | I11: =IFERROR(AVERAGE(Attitude_South[July]),"") | J11: =IFERROR(AVERAGE(Attitude_South[Aug]),"") | K11: =IFERROR(AVERAGE(Attitude_South[Sept]),"") | L11: =IFERROR(AVERAGE(Attitude_South[Oct]),"") | M11: =IFERROR(AVERAGE(Attitude_South[Nov]),"") | N11: =IFERROR(AVERAGE(Attitude_South[Dec]),"") | O11: =IFERROR(AVERAGEIF(C11:N11, ">0"),"")
B13: Billings | C13: Jan | D13: Feb | E13: Mar | F13: Apr | G13: May | H13: June | I13: July | J13: Aug | K13: Sept | L13: Oct | M13: Nov | N13: Dec | O13: Average | Q13: Billings
B14: Tom | O14: =IFERROR(AVERAGE(Billings_South[[#This Row],[Jan]:[Dec]]),"")
B15: Maddie | O15: =IFERROR(AVERAGE(Billings_South[[#This Row],[Jan]:[Dec]]),"") | S15: Below | T15: Good | U15: Excellent
B16: Andy | O16: =IFERROR(AVERAGE(Billings_South[[#This Row],[Jan]:[Dec]]),"") | Q16: Grad | S16: <4.5 | T16: 4.5-5 | U16: >5
B17: Beth | O17: =IFERROR(AVERAGE(Billings_South[[#This Row],[Jan]:[Dec]]),"") | Q17: Clinical Associate | S17: <5 | T17: 5-5.4 | U17: >5.4
B18: Felina | O18: =IFERROR(AVERAGE(Billings_South[[#This Row],[Jan]:[Dec]]),"") | Q18: Senior | S18: <5.4 | T18: 5.4-5.7 | U18: >5.7
B19: Janice | O19: =IFERROR(AVERAGE(Billings_South[[#This Row],[Jan]:[Dec]]),"")
B20: Raj | O20: =IFERROR(AVERAGE(Billings_South[[#This Row],[Jan]:[Dec]]),"")
B21: Steph | O21: =IFERROR(AVERAGE(Billings_South[[#This Row],[Jan]:[Dec]]),"") | Q21: Ceased Services
B22: Vincent | O22: =IFERROR(AVERAGE(Billings_South[[#This Row],[Jan]:[Dec]]),"") | Q22: Ceased Clients ÷ Active Clients (excluding respite & deceased)
B23: Kate | O23: =IFERROR(AVERAGE(Billings_South[[#This Row],[Jan]:[Dec]]),"")
B24: Shirley | O24: =IFERROR(AVERAGE(Billings_South[[#This Row],[Jan]:[Dec]]),"") | Q24: <2.5 | S24: Excellent
Q25: 2.5-4 | S25: Good
B26: Ceased Services | C26: Jan | D26: Feb | E26: Mar | F26: Apr | G26: May | H26: June | I26: July | J26: Aug | K26: Sept | L26: Oct | M26: Nov | N26: Dec | O26: Average | Q26: >4 | S26: Below
B27: Tom | O27: =IFERROR(AVERAGE(Ceased_South[[#This Row],[Jan]:[Dec]]),"")
B28: Maddie | O28: =IFERROR(AVERAGE(Ceased_South[[#This Row],[Jan]:[Dec]]),"")
B29: Andy | O29: =IFERROR(AVERAGE(Ceased_South[[#This Row],[Jan]:[Dec]]),"") | Q29: Documentation
B30: Beth | O30: =IFERROR(AVERAGE(Ceased_South[[#This Row],[Jan]:[Dec]]),"") | Q30: Clinical notes, service agreements, and reports.
B31: Felina | O31: =IFERROR(AVERAGE(Ceased_South[[#This Row],[Jan]:[Dec]]),"") | Q31: 5 | S31: Excellent | V31: Notes/reports completed on time, accurate, clinically sound, and advocate for client. Service agreements up to date.
B32: Janice | O32: =IFERROR(AVERAGE(Ceased_South[[#This Row],[Jan]:[Dec]]),"") | Q32: 4 | S32: Very Good | V32: Notes/reports generally completed on time and of good quality. Service agreements mostly up to date.
B33: Raj | O33: =IFERROR(AVERAGE(Ceased_South[[#This Row],[Jan]:[Dec]]),"") | Q33: 3 | S33: In Progress | V33: Notes/reports mostly on time. Clinical quality is developing, occasional revisions. Some service agreements need follow-up.
B34: Steph | O34: =IFERROR(AVERAGE(Ceased_South[[#This Row],[Jan]:[Dec]]),"") | Q34: 2 | S34: Needs Improvement | V34: Frequent delays in documentation. Clinical quality inconsistent, most service agreements not up to date.
B35: Vincent | O35: =IFERROR(AVERAGE(Ceased_South[[#This Row],[Jan]:[Dec]]),"") | Q35: 1 | S35: Unsatisfactory | V35: Notes and reports regularly late or missing. Clinical quality below standard. Service agreements not maintained.
B36: Kate | O36: =IFERROR(AVERAGE(Ceased_South[[#This Row],[Jan]:[Dec]]),"")
B37: Shirley | O37: =IFERROR(AVERAGE(Ceased_South[[#This Row],[Jan]:[Dec]]),"")
Q38: Admin & Operational Efficiency
B39: Documentation | C39: Jan | D39: Feb | E39: Mar | F39: Apr | G39: May | H39: June | I39: July | J39: Aug | K39: Sept | L39: Oct | M39: Nov | N39: Dec | O39: Average | Q39: Admin responsiveness, scheduling and bookings, service in Zanda, travel efficiency.
B40: Tom | O40: =IFERROR(AVERAGE(Documentation_South[[#This Row],[Jan]:[Dec]]),"") | Q40: 5 | S40: Excellent | V40: Responsive to admin. Appointments scheduled, confirmed & services in Zanda accurate/timely. Efficient travel.
B41: Maddie | O41: =IFERROR(AVERAGE(Documentation_South[[#This Row],[Jan]:[Dec]]),"") | Q41: 4 | S41: Very Good | V41: Generally responsive to admin. Most appointments scheduled and confirmed in a timely manner. Services entered in Zanda with occasional delays/minor errors. Travel mostly efficient.
B42: Andy | O42: =IFERROR(AVERAGE(Documentation_South[[#This Row],[Jan]:[Dec]]),"") | Q42: 3 | S42: In Progress | V42: Moderately responsive to admin. Some delays/inconsistencies in appointment scheduling or confirmation. Zanda services entry late or incomplete. Travel planning can be improved.
B43: Beth | O43: =IFERROR(AVERAGE(Documentation_South[[#This Row],[Jan]:[Dec]]),"") | Q43: 2 | S43: Needs Improvement | V43: Slow response to admin. Appointments are frequently unconfirmed or poorly scheduled. Zanda service entry is inconsistent or late. Travel mostly inefficient.
B44: Felina | O44: =IFERROR(AVERAGE(Documentation_South[[#This Row],[Jan]:[Dec]]),"") | Q44: 1 | S44: Unsatisfactory | V44: Rarely responds to admin. Appointments often missed, unconfirmed, or disorganised. Services not entered in Zanda. Travel inefficient.
B45: Janice | O45: =IFERROR(AVERAGE(Documentation_South[[#This Row],[Jan]:[Dec]]),"")
B46: Raj | O46: =IFERROR(AVERAGE(Documentation_South[[#This Row],[Jan]:[Dec]]),"")
B47: Steph | O47: =IFERROR(AVERAGE(Documentation_South[[#This Row],[Jan]:[Dec]]),"") | Q47: Attitude, Learning, Collaboration & Client Impact
B48: Vincent | O48: =IFERROR(AVERAGE(Documentation_South[[#This Row],[Jan]:[Dec]]),"") | Q48: Focuses on attitude, growth, team-first mindset, idea-sharing, and collaboration with OTs.
B49: Kate | O49: =IFERROR(AVERAGE(Documentation_South[[#This Row],[Jan]:[Dec]]),"") | Q49: 5 | S49: Excellent | V49: Positive, engaged, always learning. Consistently team-first, contributes ideas, and collaborates proactively with OTs (e.g. internal referrals, joint planning), raving fans
B50: Shirley | O50: =IFERROR(AVERAGE(Documentation_South[[#This Row],[Jan]:[Dec]]),"") | Q50: 4 | S50: Very Good | V50: Reliable, team-focused, open to learning, shares ideas occasionally, collaborates with OTs when asked, positive feedback clients
Q51: 3 | S51: In Progress | V51: Generally positive with a team mindset. Contributes but may need prompting to share ideas or engage with OTs. Neutral feedback.
B52: Admin & Operational Efficiency | C52: Jan | D52: Feb | E52: Mar | F52: Apr | G52: May | H52: June | I52: July | J52: Aug | K52: Sept | L52: Oct | M52: Nov | N52: Dec | O52: Average | Q52: 2 | S52: Needs Improvement | V52: Inconsistent engagement. Limited learning, team contribution, idea-sharing, or collaboration. Some constructive feedback clients.
B53: Tom | O53: =IFERROR(AVERAGE(Admin_South[[#This Row],[Jan]:[Dec]]),"") | Q53: 1 | S53: Unsatisfactory | V53: Rarely team-focused. Minimal growth, idea-sharing, or collaboration with others. Consistent constructive feedback clients/referrers.
B54: Maddie | O54: =IFERROR(AVERAGE(Admin_South[[#This Row],[Jan]:[Dec]]),"")
B55: Andy | O55: =IFERROR(AVERAGE(Admin_South[[#This Row],[Jan]:[Dec]]),"")
B56: Beth | O56: =IFERROR(AVERAGE(Admin_South[[#This Row],[Jan]:[Dec]]),"")
B57: Felina | O57: =IFERROR(AVERAGE(Admin_South[[#This Row],[Jan]:[Dec]]),"")
B58: Janice | O58: =IFERROR(AVERAGE(Admin_South[[#This Row],[Jan]:[Dec]]),"")
B59: Raj | O59: =IFERROR(AVERAGE(Admin_South[[#This Row],[Jan]:[Dec]]),"")
B60: Steph | O60: =IFERROR(AVERAGE(Admin_South[[#This Row],[Jan]:[Dec]]),"")
B61: Vincent | O61: =IFERROR(AVERAGE(Admin_South[[#This Row],[Jan]:[Dec]]),"")
B62: Kate | O62: =IFERROR(AVERAGE(Admin_South[[#This Row],[Jan]:[Dec]]),"")
B63: Shirley | O63: =IFERROR(AVERAGE(Admin_South[[#This Row],[Jan]:[Dec]]),"")
B65: Attitude, Learning, Collaboration & Client Impact | C65: Jan | D65: Feb | E65: Mar | F65: Apr | G65: May | H65: June | I65: July | J65: Aug | K65: Sept | L65: Oct | M65: Nov | N65: Dec | O65: Average
B66: Tom | O66: =IFERROR(AVERAGE(Attitude_South[[#This Row],[Jan]:[Dec]]),"")
B67: Maddie | O67: =IFERROR(AVERAGE(Attitude_South[[#This Row],[Jan]:[Dec]]),"")
B68: Andy | O68: =IFERROR(AVERAGE(Attitude_South[[#This Row],[Jan]:[Dec]]),"")
B69: Beth | O69: =IFERROR(AVERAGE(Attitude_South[[#This Row],[Jan]:[Dec]]),"")
B70: Felina | O70: =IFERROR(AVERAGE(Attitude_South[[#This Row],[Jan]:[Dec]]),"")
B71: Janice | O71: =IFERROR(AVERAGE(Attitude_South[[#This Row],[Jan]:[Dec]]),"")
B72: Raj | O72: =IFERROR(AVERAGE(Attitude_South[[#This Row],[Jan]:[Dec]]),"")
B73: Steph | O73: =IFERROR(AVERAGE(Attitude_South[[#This Row],[Jan]:[Dec]]),"")
B74: Vincent | O74: =IFERROR(AVERAGE(Attitude_South[[#This Row],[Jan]:[Dec]]),"")
B75: Kate | O75: =IFERROR(AVERAGE(Attitude_South[[#This Row],[Jan]:[Dec]]),"")
B76: Shirley | O76: =IFERROR(AVERAGE(Attitude_South[[#This Row],[Jan]:[Dec]]),"")

Sheet KPI Dashboard North
B2: Team North | C2: Marco | Y2: 5
Y3: 4
Y4: 3
Y5: 2
B6: Team Average | C6: Jan | D6: Feb | E6: Mar | F6: Apr | G6: May | H6: June | I6: July | J6: Aug | K6: Sept | L6: Oct | M6: Nov | N6: Dec | O6: Average | Q6: TEAM KPI'S AND AVERAGES | Y6: 1 | AC6: 2 | AD6: 4
B7: Billings | C7: =IF(SUMIFS(FTETable[Jan], FTETable[Team], "Physio_North")=0, "", SUMIFS(FTETable[Jan], FTETable[Team], "Physio_North") / SUMIFS(FTETable[FTE], FTETable[Team], "Physio_North", FTETable[Jan], ">0")) | D7: =IF(SUMIFS(FTETable[Feb], FTETable[Team], "Physio_North")=0, "", SUMIFS(FTETable[Feb], FTETable[Team], "Physio_North") / SUMIFS(FTETable[FTE], FTETable[Team], "Physio_North", FTETable[Feb], ">0")) | E7: =IF(SUMIFS(FTETable[Mar], FTETable[Team], "Physio_North")=0, "", SUMIFS(FTETable[Mar], FTETable[Team], "Physio_North") / SUMIFS(FTETable[FTE], FTETable[Team], "Physio_North", FTETable[Mar], ">0")) | F7: =IF(SUMIFS(FTETable[Apr], FTETable[Team], "Physio_North")=0, "", SUMIFS(FTETable[Apr], FTETable[Team], "Physio_North") / SUMIFS(FTETable[FTE], FTETable[Team], "Physio_North", FTETable[Apr], ">0")) | G7: =IF(SUMIFS(FTETable[May], FTETable[Team], "Physio_North")=0, "", SUMIFS(FTETable[May], FTETable[Team], "Physio_North") / SUMIFS(FTETable[FTE], FTETable[Team], "Physio_North", FTETable[May], ">0")) | H7: =IF(SUMIFS(FTETable[June], FTETable[Team], "Physio_North")=0, "", SUMIFS(FTETable[June], FTETable[Team], "Physio_North") / SUMIFS(FTETable[FTE], FTETable[Team], "Physio_North", FTETable[June], ">0")) | I7: =IF(SUMIFS(FTETable[July], FTETable[Team], "Physio_North")=0, "", SUMIFS(FTETable[July], FTETable[Team], "Physio_North") / SUMIFS(FTETable[FTE], FTETable[Team], "Physio_North", FTETable[July], ">0")) | J7: =IF(SUMIFS(FTETable[Aug], FTETable[Team], "Physio_North")=0, "", SUMIFS(FTETable[Aug], FTETable[Team], "Physio_North") / SUMIFS(FTETable[FTE], FTETable[Team], "Physio_North", FTETable[Aug], ">0")) | K7: =IF(SUMIFS(FTETable[Sept], FTETable[Team], "Physio_North")=0, "", SUMIFS(FTETable[Sept], FTETable[Team], "Physio_North") / SUMIFS(FTETable[FTE], FTETable[Team], "Physio_North", FTETable[Sept], ">0")) | L7: =IF(SUMIFS(FTETable[Oct], FTETable[Team], "Physio_North")=0, "", SUMIFS(FTETable[Oct], FTETable[Team], "Physio_North") / SUMIFS(FTETable[FTE], FTETable[Team], "Physio_North", FTETable[Oct], ">0")) | M7: =IF(SUMIFS(FTETable[Nov], FTETable[Team], "Physio_North")=0, "", SUMIFS(FTETable[Nov], FTETable[Team], "Physio_North") / SUMIFS(FTETable[FTE], FTETable[Team], "Physio_North", FTETable[Nov], ">0")) | N7: =IF(SUMIFS(FTETable[Dec], FTETable[Team], "Physio_North")=0, "", SUMIFS(FTETable[Dec], FTETable[Team], "Physio_North") / SUMIFS(FTETable[FTE], FTETable[Team], "Physio_North", FTETable[Dec], ">0")) | O7: =IFERROR(AVERAGEIF(C7:N7, ">0"),"") | Q7: Team Billings Averages | S7: Below | T7: Good | U7: Excellent | V7: Month | AC7: 1 | AD7: 5
B8: Ceased Services | C8: =IFERROR(AVERAGE(Ceased_North[Jan]),"") | D8: =IFERROR(AVERAGE(Ceased_North[Feb]),"") | E8: =IFERROR(AVERAGE(Ceased_North[Mar]),"") | F8: =IFERROR(AVERAGE(Ceased_North[Apr]),"") | G8: =IFERROR(AVERAGE(Ceased_North[May]),"") | H8: =IFERROR(AVERAGE(Ceased_North[June]),"") | I8: =IFERROR(AVERAGE(Ceased_North[July]),"") | J8: =IFERROR(AVERAGE(Ceased_North[Aug]),"") | K8: =IFERROR(AVERAGE(Ceased_North[Sept]),"") | L8: =IFERROR(AVERAGE(Ceased_North[Oct]),"") | M8: =IFERROR(AVERAGE(Ceased_North[Nov]),"") | N8: =IFERROR(AVERAGE(Ceased_North[Dec]),"") | O8: =IFERROR(AVERAGEIF(C8:N8, ">0"),"") | S8: <5 | T8: 5-5.4 | U8: >5.4 | V8: 46023
B9: Documentation | C9: =IFERROR(AVERAGE(Documentation_North[Jan]),"") | D9: =IFERROR(AVERAGE(Documentation_North[Feb]),"") | E9: =IFERROR(AVERAGE(Documentation_North[Mar]),"") | F9: =IFERROR(AVERAGE(Documentation_North[Apr]),"") | G9: =IFERROR(AVERAGE(Documentation_North[May]),"") | H9: =IFERROR(AVERAGE(Documentation_North[June]),"") | I9: =IFERROR(AVERAGE(Documentation_North[July]),"") | J9: =IFERROR(AVERAGE(Documentation_North[Aug]),"") | K9: =IFERROR(AVERAGE(Documentation_North[Sept]),"") | L9: =IFERROR(AVERAGE(Documentation_North[Oct]),"") | M9: =IFERROR(AVERAGE(Documentation_North[Nov]),"") | N9: =IFERROR(AVERAGE(Documentation_North[Dec]),"") | O9: =IFERROR(AVERAGEIF(C9:N9, ">0"),"") | S9: <4.99 | T9: 4.99-5.39 | U9: >5.39 | V9: 46054
B10: Admin & Operational Efficiency | C10: =IFERROR(AVERAGE(Admin_North[Jan]),"") | D10: =IFERROR(AVERAGE(Admin_North[Feb]),"") | E10: =IFERROR(AVERAGE(Admin_North[Mar]),"") | F10: =IFERROR(AVERAGE(Admin_North[Apr]),"") | G10: =IFERROR(AVERAGE(Admin_North[May]),"") | H10: =IFERROR(AVERAGE(Admin_North[June]),"") | I10: =IFERROR(AVERAGE(Admin_North[July]),"") | J10: =IFERROR(AVERAGE(Admin_North[Aug]),"") | K10: =IFERROR(AVERAGE(Admin_North[Sept]),"") | L10: =IFERROR(AVERAGE(Admin_North[Oct]),"") | M10: =IFERROR(AVERAGE(Admin_North[Nov]),"") | N10: =IFERROR(AVERAGE(Admin_North[Dec]),"") | O10: =IFERROR(AVERAGEIF(C10:N10, ">0"),"")
B11: Attitude, Learning, Collaboration & Client Impact | C11: =IFERROR(AVERAGE(Attitude_North[Jan]),"") | D11: =IFERROR(AVERAGE(Attitude_North[Feb]),"") | E11: =IFERROR(AVERAGE(Attitude_North[Mar]),"") | F11: =IFERROR(AVERAGE(Attitude_North[Apr]),"") | G11: =IFERROR(AVERAGE(Attitude_North[May]),"") | H11: =IFERROR(AVERAGE(Attitude_North[June]),"") | I11: =IFERROR(AVERAGE(Attitude_North[July]),"") | J11: =IFERROR(AVERAGE(Attitude_North[Aug]),"") | K11: =IFERROR(AVERAGE(Attitude_North[Sept]),"") | L11: =IFERROR(AVERAGE(Attitude_North[Oct]),"") | M11: =IFERROR(AVERAGE(Attitude_North[Nov]),"") | N11: =IFERROR(AVERAGE(Attitude_North[Dec]),"") | O11: =IFERROR(AVERAGEIF(C11:N11, ">0"),"") | Q11: Other KPI Averages | S11: Unsatisfactory | T11: Needs improvement | U11: In progress | V11: Very Good | W11: Excellent
S12: <1.5 | T12: 1.5-2.5 | U12: 2.5-3.5 | V12: 3.5-4.5 | W12: 4.5-5
B13: Billings | C13: Jan | D13: Feb | E13: Mar | F13: Apr | G13: May | H13: June | I13: July | J13: Aug | K13: Sept | L13: Oct | M13: Nov | N13: Dec | O13: Average
B14: Marco | O14: =IFERROR(AVERAGE(Billings_North[[#This Row],[Jan]:[Dec]]),"")
B15: Danny | O15: =IFERROR(AVERAGE(Billings_North[[#This Row],[Jan]:[Dec]]),"") | Q15: Billings
B16: Alice | O16: =IFERROR(AVERAGE(Billings_North[[#This Row],[Jan]:[Dec]]),"")
B17: April | O17: =IFERROR(AVERAGE(Billings_North[[#This Row],[Jan]:[Dec]]),"") | S17: Below | T17: Good | U17: Excellent
B18: Chris | O18: =IFERROR(AVERAGE(Billings_North[[#This Row],[Jan]:[Dec]]),"") | Q18: Grad | S18: <4.5 | T18: 4.5-5 | U18: >5
B19: Emilie | O19: =IFERROR(AVERAGE(Billings_North[[#This Row],[May]:[Dec]]),"") | Q19: Clinical Associate | S19: <5 | T19: 5-5.4 | U19: >5.4
B20: Eva | O20: =IFERROR(AVERAGE(Billings_North[[#This Row],[May]:[Dec]]),"") | Q20: Senior | S20: <5.4 | T20: 5.4-5.7 | U20: >5.7
B21: Jackson | O21: =IFERROR(AVERAGE(Billings_North[[#This Row],[Jan]:[Dec]]),"")
B22: Jay | O22: =IFERROR(AVERAGE(Billings_North[[#This Row],[Jan]:[Dec]]),"")
B23: Jaymee | O23: =IFERROR(AVERAGE(Billings_North[[#This Row],[May]:[Dec]]),"") | Q23: Ceased Services
Q24: Ceased Clients ÷ Active Clients (excluding respite & deceased)
B25: Ceased Services | C25: Jan | D25: Feb | E25: Mar | F25: Apr | G25: May | H25: June | I25: July | J25: Aug | K25: Sept | L25: Oct | M25: Nov | N25: Dec | O25: Average
B26: Marco | O26: =IFERROR(AVERAGE(Ceased_North[[#This Row],[Jan]:[Dec]]),"") | Q26: <2.5 | S26: Excellent
B27: Danny | O27: =IFERROR(AVERAGE(Ceased_North[[#This Row],[Jan]:[Dec]]),"") | Q27: 2.5-4 | S27: Good
B28: Alice | O28: =IFERROR(AVERAGE(Ceased_North[[#This Row],[Jan]:[Dec]]),"") | Q28: >4 | S28: Below
B29: April | O29: =IFERROR(AVERAGE(Ceased_North[[#This Row],[Jan]:[Dec]]),"")
B30: Chris | O30: =IFERROR(AVERAGE(Ceased_North[[#This Row],[Jan]:[Dec]]),"")
B31: Emilie | O31: =IFERROR(AVERAGE(Ceased_North[[#This Row],[Jan]:[Dec]]),"") | Q31: Documentation
B32: Eva | O32: =IFERROR(AVERAGE(Ceased_North[[#This Row],[Jan]:[Dec]]),"") | Q32: Clinical notes, service agreements, and reports.
B33: Jackson | O33: =IFERROR(AVERAGE(Ceased_North[[#This Row],[Jan]:[Dec]]),"") | Q33: 5 | S33: Excellent | V33: Notes/reports completed on time, accurate, clinically sound, and advocate for client. Service agreements up to date.
B34: Jay | O34: =IFERROR(AVERAGE(Ceased_North[[#This Row],[Jan]:[Dec]]),"") | Q34: 4 | S34: Very Good | V34: Notes/reports generally completed on time and of good quality. Service agreements mostly up to date.
B35: Jaymee | O35: =IFERROR(AVERAGE(Ceased_North[[#This Row],[Jan]:[Dec]]),"") | Q35: 3 | S35: In Progress | V35: Notes/reports mostly on time. Clinical quality is developing, occasional revisions. Some service agreements need follow-up.
Q36: 2 | S36: Needs Improvement | V36: Frequent delays in documentation. Clinical quality inconsistent, most service agreements not up to date.
B37: Documentation | C37: Jan | D37: Feb | E37: Mar | F37: Apr | G37: May | H37: June | I37: July | J37: Aug | K37: Sept | L37: Oct | M37: Nov | N37: Dec | O37: Average | Q37: 1 | S37: Unsatisfactory | V37: Notes and reports regularly late or missing. Clinical quality below standard. Service agreements not maintained.
B38: Marco | O38: =IFERROR(AVERAGE(Documentation_North[[#This Row],[Jan]:[Dec]]),"")
B39: Danny | O39: =IFERROR(AVERAGE(Documentation_North[[#This Row],[Jan]:[Dec]]),"")
B40: Alice | O40: =IFERROR(AVERAGE(Documentation_North[[#This Row],[Jan]:[Dec]]),"") | Q40: Admin & Operational Efficiency
B41: April | O41: =IFERROR(AVERAGE(Documentation_North[[#This Row],[Jan]:[Dec]]),"") | Q41: Admin responsiveness, scheduling and bookings, service in Zanda, travel efficiency.
B42: Chris | O42: =IFERROR(AVERAGE(Documentation_North[[#This Row],[Jan]:[Dec]]),"") | Q42: 5 | S42: Excellent | V42: Responsive to admin. Appointments scheduled, confirmed & services in Zanda accurate/timely. Efficient travel.
B43: Emilie | O43: =IFERROR(AVERAGE(Documentation_North[[#This Row],[Jan]:[Dec]]),"") | Q43: 4 | S43: Very Good | V43: Generally responsive to admin. Most appointments scheduled and confirmed in a timely manner. Services entered in Zanda with occasional delays/minor errors. Travel mostly efficient.
B44: Eva | O44: =IFERROR(AVERAGE(Documentation_North[[#This Row],[Jan]:[Dec]]),"") | Q44: 3 | S44: In Progress | V44: Moderately responsive to admin. Some delays/inconsistencies in appointment scheduling or confirmation. Zanda services entry late or incomplete. Travel planning can be improved.
B45: Jackson | O45: =IFERROR(AVERAGE(Documentation_North[[#This Row],[Jan]:[Dec]]),"") | Q45: 2 | S45: Needs Improvement | V45: Slow response to admin. Appointments are frequently unconfirmed or poorly scheduled. Zanda service entry is inconsistent or late. Travel mostly inefficient.
B46: Jay | O46: =IFERROR(AVERAGE(Documentation_North[[#This Row],[Jan]:[Dec]]),"") | Q46: 1 | S46: Unsatisfactory | V46: Rarely responds to admin. Appointments often missed, unconfirmed, or disorganised. Services not entered in Zanda. Travel inefficient.
B47: Jaymee | O47: =IFERROR(AVERAGE(Documentation_North[[#This Row],[Jan]:[Dec]]),"")
B49: Admin & Operational Efficiency | C49: Jan | D49: Feb | E49: Mar | F49: Apr | G49: May | H49: June | I49: July | J49: Aug | K49: Sept | L49: Oct | M49: Nov | N49: Dec | O49: Average | Q49: Attitude, Learning, Collaboration & Client Impact
B50: Marco | O50: =IFERROR(AVERAGE(Admin_North[[#This Row],[Jan]:[Dec]]),"") | Q50: Focuses on attitude, growth, team-first mindset, idea-sharing, and collaboration with OTs.
B51: Danny | O51: =IFERROR(AVERAGE(Admin_North[[#This Row],[Jan]:[Dec]]),"") | Q51: 5 | S51: Excellent | V51: Positive, engaged, always learning. Consistently team-first, contributes ideas, and collaborates proactively with OTs (e.g. internal referrals, joint planning).
B52: Alice | O52: =IFERROR(AVERAGE(Admin_North[[#This Row],[Jan]:[Dec]]),"") | Q52: 4 | S52: Very Good | V52: Reliable, team-focused, open to learning, shares ideas occasionally, and collaborates with OTs when asked.
B53: April | O53: =IFERROR(AVERAGE(Admin_North[[#This Row],[Jan]:[Dec]]),"") | Q53: 3 | S53: In Progress | V53: Generally positive with a team mindset. Contributes but may need prompting to share ideas or engage with OTs.
B54: Chris | O54: =IFERROR(AVERAGE(Admin_North[[#This Row],[Jan]:[Dec]]),"") | Q54: 2 | S54: Needs Improvement | V54: Inconsistent engagement. Limited learning, team contribution, idea-sharing, or collaboration.
B55: Emilie | O55: =IFERROR(AVERAGE(Admin_North[[#This Row],[Jan]:[Dec]]),"") | Q55: 1 | S55: Unsatisfactory | V55: Rarely team-focused. Minimal growth, idea-sharing, or collaboration with others.
B56: Eva | O56: =IFERROR(AVERAGE(Admin_North[[#This Row],[Jan]:[Dec]]),"")
B57: Jackson | O57: =IFERROR(AVERAGE(Admin_North[[#This Row],[Jan]:[Dec]]),"")
B58: Jay | O58: =IFERROR(AVERAGE(Admin_North[[#This Row],[Jan]:[Dec]]),"")
B59: Jaymee | O59: =IFERROR(AVERAGE(Admin_North[[#This Row],[Jan]:[Dec]]),"")
B61: Attitude, Learning, Collaboration & Client Impact | C61: Jan | D61: Feb | E61: Mar | F61: Apr | G61: May | H61: June | I61: July | J61: Aug | K61: Sept | L61: Oct | M61: Nov | N61: Dec | O61: Average
B62: Marco | O62: =IFERROR(AVERAGE(Attitude_North[[#This Row],[Jan]:[Dec]]),"")
B63: Danny | O63: =IFERROR(AVERAGE(Attitude_North[[#This Row],[Jan]:[Dec]]),"")
B64: Alice | O64: =IFERROR(AVERAGE(Attitude_North[[#This Row],[Jan]:[Dec]]),"")
B65: April | O65: =IFERROR(AVERAGE(Attitude_North[[#This Row],[Jan]:[Dec]]),"")
B66: Chris | O66: =IFERROR(AVERAGE(Attitude_North[[#This Row],[Jan]:[Dec]]),"")
B67: Emilie | O67: =IFERROR(AVERAGE(Attitude_North[[#This Row],[Jan]:[Dec]]),"")
B68: Eva | O68: =IFERROR(AVERAGE(Attitude_North[[#This Row],[Jan]:[Dec]]),"")
B69: Jackson | O69: =IFERROR(AVERAGE(Attitude_North[[#This Row],[Jan]:[Dec]]),"")
B70: Jay | O70: =IFERROR(AVERAGE(Attitude_North[[#This Row],[Jan]:[Dec]]),"")
B71: Jaymee | O71: =IFERROR(AVERAGE(Attitude_North[[#This Row],[Jan]:[Dec]]),"")

Sheet KPI Dashboard OT
B2: Team Leader | C2: Josephine Lee | Y2: 5
Y3: 4
Y4: 3
Y5: 2
B6: Team Average | C6: Jan | D6: Feb | E6: Mar | F6: Apr | G6: May | H6: June | I6: July | J6: Aug | K6: Sept | L6: Oct | M6: Nov | N6: Dec | O6: Average | Q6: TEAM KPI'S | Y6: 1
B7: Billings | C7: =IF(SUMIFS(FTETable[Jan], FTETable[Team], "OT")=0, "", SUMIFS(FTETable[Jan], FTETable[Team], "OT") / SUMIFS(FTETable[FTE], FTETable[Team], "OT", FTETable[Jan], ">0")) | D7: =IF(SUMIFS(FTETable[Feb], FTETable[Team], "OT")=0, "", SUMIFS(FTETable[Feb], FTETable[Team], "OT") / SUMIFS(FTETable[FTE], FTETable[Team], "OT", FTETable[Feb], ">0")) | E7: =IF(SUMIFS(FTETable[Mar], FTETable[Team], "OT")=0, "", SUMIFS(FTETable[Mar], FTETable[Team], "OT") / SUMIFS(FTETable[FTE], FTETable[Team], "OT", FTETable[Mar], ">0")) | F7: =IF(SUMIFS(FTETable[Apr], FTETable[Team], "OT")=0, "", SUMIFS(FTETable[Apr], FTETable[Team], "OT") / SUMIFS(FTETable[FTE], FTETable[Team], "OT", FTETable[Apr], ">0")) | G7: =IF(SUMIFS(FTETable[May], FTETable[Team], "OT")=0, "", SUMIFS(FTETable[May], FTETable[Team], "OT") / SUMIFS(FTETable[FTE], FTETable[Team], "OT", FTETable[May], ">0")) | H7: =IF(SUMIFS(FTETable[June], FTETable[Team], "OT")=0, "", SUMIFS(FTETable[June], FTETable[Team], "OT") / SUMIFS(FTETable[FTE], FTETable[Team], "OT", FTETable[June], ">0")) | I7: =IF(SUMIFS(FTETable[July], FTETable[Team], "OT")=0, "", SUMIFS(FTETable[July], FTETable[Team], "OT") / SUMIFS(FTETable[FTE], FTETable[Team], "OT", FTETable[July], ">0")) | J7: =IF(SUMIFS(FTETable[Aug], FTETable[Team], "OT")=0, "", SUMIFS(FTETable[Aug], FTETable[Team], "OT") / SUMIFS(FTETable[FTE], FTETable[Team], "OT", FTETable[Aug], ">0")) | K7: =IF(SUMIFS(FTETable[Sept], FTETable[Team], "OT")=0, "", SUMIFS(FTETable[Sept], FTETable[Team], "OT") / SUMIFS(FTETable[FTE], FTETable[Team], "OT", FTETable[Sept], ">0")) | L7: =IF(SUMIFS(FTETable[Oct], FTETable[Team], "OT")=0, "", SUMIFS(FTETable[Oct], FTETable[Team], "OT") / SUMIFS(FTETable[FTE], FTETable[Team], "OT", FTETable[Oct], ">0")) | M7: =IF(SUMIFS(FTETable[Nov], FTETable[Team], "OT")=0, "", SUMIFS(FTETable[Nov], FTETable[Team], "OT") / SUMIFS(FTETable[FTE], FTETable[Team], "OT", FTETable[Nov], ">0")) | N7: =IF(SUMIFS(FTETable[Dec], FTETable[Team], "OT")=0, "", SUMIFS(FTETable[Dec], FTETable[Team], "OT") / SUMIFS(FTETable[FTE], FTETable[Team], "OT", FTETable[Dec], ">0")) | O7: =IFERROR(AVERAGEIF(C7:N7, ">0"),"") | Q7: Team Billings | S7: Below | T7: Good | U7: Excellent
B8: Operational Efficiency, Compliance & Admin Responsiveness | C8: =IFERROR(AVERAGE(Compliance_OT[Jan]),"") | D8: =IFERROR(AVERAGE(Compliance_OT[Feb]),"") | E8: =IFERROR(AVERAGE(Compliance_OT[Mar]),"") | F8: =IFERROR(AVERAGE(Compliance_OT[Apr]),"") | G8: =IFERROR(AVERAGE(Compliance_OT[May]),"") | H8: =IFERROR(AVERAGE(Compliance_OT[June]),"") | I8: =IFERROR(AVERAGE(Compliance_OT[July]),"") | J8: =IFERROR(AVERAGE(Compliance_OT[Aug]),"") | K8: =IFERROR(AVERAGE(Compliance_OT[Sept]),"") | L8: =IFERROR(AVERAGE(Compliance_OT[Oct]),"") | M8: =IFERROR(AVERAGE(Compliance_OT[Nov]),"") | N8: =IFERROR(AVERAGE(Compliance_OT[Dec]),"") | O8: =IFERROR(AVERAGEIF(C8:N8, ">0"),"") | S8: <4.3 | T8: 4.3-4.9 | U8: >4.9
B9: Client & Referrer Satisfaction | C9: =IFERROR(AVERAGE(ReferrerEng_OT[Jan]),"") | D9: =IFERROR(AVERAGE(ReferrerEng_OT[Feb]),"") | E9: =IFERROR(AVERAGE(ReferrerEng_OT[Mar]),"") | F9: =IFERROR(AVERAGE(ReferrerEng_OT[Apr]),"") | G9: =IFERROR(AVERAGE(ReferrerEng_OT[May]),"") | H9: =IFERROR(AVERAGE(ReferrerEng_OT[June]),"") | I9: =IFERROR(AVERAGE(ReferrerEng_OT[July]),"") | J9: =IFERROR(AVERAGE(ReferrerEng_OT[Aug]),"") | K9: =IFERROR(AVERAGE(ReferrerEng_OT[Sept]),"") | L9: =IFERROR(AVERAGE(ReferrerEng_OT[Oct]),"") | M9: =IFERROR(AVERAGE(ReferrerEng_OT[Nov]),"") | N9: =IFERROR(AVERAGE(ReferrerEng_OT[Dec]),"") | O9: =IFERROR(AVERAGEIF(C9:N9, ">0"),"") | Q9: Other KPI's | S9: Unsatisfactory | T9: Needs improvement | U9: In progress | V9: Very Good | W9: Excellent
B10: Capacity Building & Use of NDIS Funding | C10: =IFERROR(AVERAGE(Capacity_OT[Jan]),"") | D10: =IFERROR(AVERAGE(Capacity_OT[Feb]),"") | E10: =IFERROR(AVERAGE(Capacity_OT[Mar]),"") | F10: =IFERROR(AVERAGE(Capacity_OT[Apr]),"") | G10: =IFERROR(AVERAGE(Capacity_OT[May]),"") | H10: =IFERROR(AVERAGE(Capacity_OT[June]),"") | I10: =IFERROR(AVERAGE(Capacity_OT[July]),"") | J10: =IFERROR(AVERAGE(Capacity_OT[Aug]),"") | K10: =IFERROR(AVERAGE(Capacity_OT[Sept]),"") | L10: =IFERROR(AVERAGE(Capacity_OT[Oct]),"") | M10: =IFERROR(AVERAGE(Capacity_OT[Nov]),"") | N10: =IFERROR(AVERAGE(Capacity_OT[Dec]),"") | O10: =IFERROR(AVERAGEIF(C10:N10, ">0"),"") | S10: <1.5 | T10: 1.5-2.5 | U10: 2.5-3.5 | V10: 3.5-4.5 | W10: 4.5-5
B11: Team Contribution, Attitude & Clinical Growth | C11: =IFERROR(AVERAGE(Attitude_OT[Jan]),"") | D11: =IFERROR(AVERAGE(Attitude_OT[Feb]),"") | E11: =IFERROR(AVERAGE(Attitude_OT[Mar]),"") | F11: =IFERROR(AVERAGE(Attitude_OT[Apr]),"") | G11: =IFERROR(AVERAGE(Attitude_OT[May]),"") | H11: =IFERROR(AVERAGE(Attitude_OT[June]),"") | I11: =IFERROR(AVERAGE(Attitude_OT[July]),"") | J11: =IFERROR(AVERAGE(Attitude_OT[Aug]),"") | K11: =IFERROR(AVERAGE(Attitude_OT[Sept]),"") | L11: =IFERROR(AVERAGE(Attitude_OT[Oct]),"") | M11: =IFERROR(AVERAGE(Attitude_OT[Nov]),"") | N11: =IFERROR(AVERAGE(Attitude_OT[Dec]),"") | O11: =IFERROR(AVERAGEIF(C11:N11, ">0"),"")
B13: Billings | C13: Jan | D13: Feb | E13: Mar | F13: Apr | G13: May | H13: June | I13: July | J13: Aug | K13: Sept | L13: Oct | M13: Nov | N13: Dec | O13: Average | Q13: Billings
B14: Josephine | O14: =IFERROR(AVERAGE(Billings_OT[[#This Row],[Jan]:[Dec]]),"")
B15: Caitlin | O15: =IFERROR(AVERAGE(Billings_OT[[#This Row],[Jan]:[Dec]]),"") | S15: Below | T15: Good | U15: Excellent
B16: Charlotte | O16: =IFERROR(AVERAGE(Billings_OT[[#This Row],[Jan]:[Dec]]),"") | Q16: Grad | S16: <4 | T16: 4-4.8 | U16: >4.8
B17: Isabella | O17: =IFERROR(AVERAGE(Billings_OT[[#This Row],[Jan]:[Dec]]),"") | Q17: CA | S17: <4.5 | T17: 4.5-5 | U17: >5
B18: Lynn | O18: =IFERROR(AVERAGE(Billings_OT[[#This Row],[Jan]:[Dec]]),"") | Q18: Senior | S18: <4.8 | T18: 4.8-5.2 | U18: >5.2
B19: Portia | O19: =IFERROR(AVERAGE(Billings_OT[[#This Row],[Jan]:[Dec]]),"")
B20: Bao | O20: =IFERROR(AVERAGE(Billings_OT[[#This Row],[Jan]:[Dec]]),"")
B21: Jiayee | O21: =IFERROR(AVERAGE(Billings_OT[[#This Row],[Jan]:[Dec]]),"") | Q21: Operational Efficiency, Compliance & Admin Responsiveness
B22: Rainie | O22: =IFERROR(AVERAGE(Billings_OT[[#This Row],[Jan]:[Dec]]),"") | Q22: Clinical notes, service agreements, invoicing, travel efficiency, & admin communication.
B23: Sabrina | O23: =IFERROR(AVERAGE(Billings_OT[[#This Row],[Jan]:[Dec]]),"") | Q23: 5 | S23: Excellent | V23: Always submits accurate documentation on time, responds promptly to admin, and plans travel efficiently. Follows processes consistently.
Q24: 4 | S24: Very Good | V24: Mostly accurate and timely with documentation and admin replies. Travel is generally efficient.
B25: Operational Efficiency, Compliance & Admin Responsiveness | C25: Jan | D25: Feb | E25: Mar | F25: Apr | G25: May | H25: June | I25: July | J25: Aug | K25: Sept | L25: Oct | M25: Nov | N25: Dec | O25: Average | Q25: 3 | S25: In Progress | V25: Some delays or inconsistencies in documentation or admin responsiveness. Travel planning could improve.
B26: Josephine | O26: =IFERROR(AVERAGE(Compliance_OT[[#This Row],[Jan]:[Dec]]),"") | Q26: 2 | S26: Needs Improvement | V26: Frequent delays or inefficiencies. Often slow to respond to admin. Needs reminders.
B27: Caitlin | O27: =IFERROR(AVERAGE(Compliance_OT[[#This Row],[Jan]:[Dec]]),"") | Q27: 1 | S27: Unsatisfactory | V27: Often late or inaccurate. Poor planning, poor admin responsiveness, and non-compliance with systems.
B28: Charlotte | O28: =IFERROR(AVERAGE(Compliance_OT[[#This Row],[Jan]:[Dec]]),"")
B29: Isabella | O29: =IFERROR(AVERAGE(Compliance_OT[[#This Row],[Jan]:[Dec]]),"") | Q29: Client & Referrer Satisfaction
B30: Lynn | O30: =IFERROR(AVERAGE(Compliance_OT[[#This Row],[Jan]:[Dec]]),"") | Q30: Looks at how well we keep both clients and referrers in the loop and build rapport.
B31: Portia | O31: =IFERROR(AVERAGE(Compliance_OT[[#This Row],[Jan]:[Dec]]),"") | Q31: 5 | S31: Excellent | V31: Proactive and clear communication. Strong relationships. Regular positive feedback, great client results.
B32: Bao | O32: =IFERROR(AVERAGE(Compliance_OT[[#This Row],[Jan]:[Dec]]),"") | Q32: 4 | S32: Very Good | V32: Communicates well most of the time. Positive rapport.
B33: Jiayee | O33: =IFERROR(AVERAGE(Compliance_OT[[#This Row],[Jan]:[Dec]]),"") | Q33: 3 | S33: In Progress | V33: Generally responsive but a bit inconsistent.
B34: Rainie | O34: =IFERROR(AVERAGE(Compliance_OT[[#This Row],[Jan]:[Dec]]),"") | Q34: 2 | S34: Needs Improvement | V34: Delays or lack of clarity. Occasional negative feedback.
B35: Sabrina | O35: =IFERROR(AVERAGE(Compliance_OT[[#This Row],[Jan]:[Dec]]),"") | Q35: 1 | S35: Unsatisfactory | V35: Rarely communicates effectively. Ongoing issues.
B37: Client & Referrer Satisfaction | C37: Jan | D37: Feb | E37: Mar | F37: Apr | G37: May | H37: June | I37: July | J37: Aug | K37: Sept | L37: Oct | M37: Nov | N37: Dec | O37: Average | Q37: Capacity Building & Use of NDIS Funding
B38: Josephine | O38: =IFERROR(AVERAGE(ReferrerEng_OT[[#This Row],[Jan]:[Dec]]),"") | Q38: Focus on follow-through and using funding in a way that supports outcomes.
B39: Caitlin | O39: =IFERROR(AVERAGE(ReferrerEng_OT[[#This Row],[Jan]:[Dec]]),"") | Q39: 5 | S39: Excellent | V39: Delivers meaningful follow-up aligned with recommendations. NDIS funding well utilised.
B40: Charlotte | O40: =IFERROR(AVERAGE(ReferrerEng_OT[[#This Row],[Jan]:[Dec]]),"") | Q40: 4 | S40: Very Good | V40: Follows through on most recommendations. Good use of funds.
B41: Isabella | O41: =IFERROR(AVERAGE(ReferrerEng_OT[[#This Row],[Jan]:[Dec]]),"") | Q41: 3 | S41: In Progress | V41: Some follow-up, but some opportunities missed.
B42: Lynn | O42: =IFERROR(AVERAGE(ReferrerEng_OT[[#This Row],[Jan]:[Dec]]),"") | Q42: 2 | S42: Needs Improvement | V42: Often doesn’t complete follow-up. Funding underused.
B43: Portia | O43: =IFERROR(AVERAGE(ReferrerEng_OT[[#This Row],[Jan]:[Dec]]),"") | Q43: 1 | S43: Unsatisfactory | V43: Rarely follows through. Consistently underutilised funding.
B44: Bao | O44: =IFERROR(AVERAGE(ReferrerEng_OT[[#This Row],[Jan]:[Dec]]),"")
B45: Jiayee | O45: =IFERROR(AVERAGE(ReferrerEng_OT[[#This Row],[Jan]:[Dec]]),"") | Q45: Team Contribution, Attitude, Clinical Growth & Cross collab with physios
B46: Rainie | O46: =IFERROR(AVERAGE(ReferrerEng_OT[[#This Row],[Jan]:[Dec]]),"") | Q46: Looks at teamwork, attitude, and efforts to grow clinically.
B47: Sabrina | O47: =IFERROR(AVERAGE(ReferrerEng_OT[[#This Row],[Jan]:[Dec]]),"") | Q47: 5 | S47: Excellent | V47: Supports others, shows initiative, always looking to learn and grow. Proactively collaborates with physio team (internal referrals, MDT)
Q48: 4 | S48: Very Good | V48: Positive contributor, engaged in learning, willing to collaborates across MDT team, acts on feedback.
B49: Capacity Building & Use of NDIS Funding | C49: Jan | D49: Feb | E49: Mar | F49: Apr | G49: May | H49: June | I49: July | J49: Aug | K49: Sept | L49: Oct | M49: Nov | N49: Dec | O49: Average | Q49: 3 | S49: In Progress | V49: Participates when prompted. Development is steady but passive. Minimal collab with physios.
B50: Josephine | O50: =IFERROR(AVERAGE(Capacity_OT[[#This Row],[Jan]:[Dec]]),"") | Q50: 2 | S50: Needs Improvement | V50: Not very engaged. Limited engagement.
B51: Caitlin | O51: =IFERROR(AVERAGE(Capacity_OT[[#This Row],[Jan]:[Dec]]),"") | Q51: 1 | S51: Unsatisfactory | V51: Disengaged, avoids feedback, and collab opportunities.
B52: Charlotte | O52: =IFERROR(AVERAGE(Capacity_OT[[#This Row],[Jan]:[Dec]]),"")
B53: Isabella | O53: =IFERROR(AVERAGE(Capacity_OT[[#This Row],[Jan]:[Dec]]),"")
B54: Lynn | O54: =IFERROR(AVERAGE(Capacity_OT[[#This Row],[Jan]:[Dec]]),"")
B55: Portia | O55: =IFERROR(AVERAGE(Capacity_OT[[#This Row],[Jan]:[Dec]]),"")
B56: Bao | O56: =IFERROR(AVERAGE(Capacity_OT[[#This Row],[Jan]:[Dec]]),"")
B57: Jiayee | O57: =IFERROR(AVERAGE(Capacity_OT[[#This Row],[Jan]:[Dec]]),"")
B58: Rainie | O58: =IFERROR(AVERAGE(Capacity_OT[[#This Row],[Jan]:[Dec]]),"")
B59: Sabrina | O59: =IFERROR(AVERAGE(Capacity_OT[[#This Row],[Jan]:[Dec]]),"")
B61: Team Contribution, Attitude & Clinical Growth | C61: Jan | D61: Feb | E61: Mar | F61: Apr | G61: May | H61: June | I61: July | J61: Aug | K61: Sept | L61: Oct | M61: Nov | N61: Dec | O61: Average
B62: Josephine | O62: =IFERROR(AVERAGE(Attitude_OT[[#This Row],[Jan]:[Dec]]),"")
B63: Caitlin | O63: =IFERROR(AVERAGE(Attitude_OT[[#This Row],[Jan]:[Dec]]),"")
B64: Charlotte | O64: =IFERROR(AVERAGE(Attitude_OT[[#This Row],[Jan]:[Dec]]),"")
B65: Isabella | O65: =IFERROR(AVERAGE(Attitude_OT[[#This Row],[Jan]:[Dec]]),"")
B66: Lynn | O66: =IFERROR(AVERAGE(Attitude_OT[[#This Row],[Jan]:[Dec]]),"")
B67: Portia | O67: =IFERROR(AVERAGE(Attitude_OT[[#This Row],[Jan]:[Dec]]),"")
B68: Bao | O68: =IFERROR(AVERAGE(Attitude_OT[[#This Row],[Jan]:[Dec]]),"")
B69: Jiayee | O69: =IFERROR(AVERAGE(Attitude_OT[[#This Row],[Jan]:[Dec]]),"")
B70: Rainie | O70: =IFERROR(AVERAGE(Attitude_OT[[#This Row],[Jan]:[Dec]]),"")
B71: Sabrina | O71: =IFERROR(AVERAGE(Attitude_OT[[#This Row],[Jan]:[Dec]]),"")

Sheet Ceased services
C2: CEASED SERVICES LOG
E5: January 2026 | H5: February 2026 | K5: March 2026 | N5: April 2026 | Q5: May 2026 | T5: June 2026 | W5: July 2026 | Z5: August 2026 | AC5: September 2026 | AF5: October 2026 | AI5: November 2026 | AL5: December 2026
C6: Team | D6: Therapist | E6: Active | F6: Ceased | G6: % | H6: Active | I6: Ceased | J6: % | K6: Active | L6: Ceased | M6: % | N6: Active | O6: Ceased | P6: % | Q6: Active | R6: Ceased | S6: % | T6: Active | U6: Ceased | V6: % | W6: Active | X6: Ceased | Y6: % | Z6: Active | AA6: Ceased | AB6: % | AC6: Active | AD6: Ceased | AE6: % | AF6: Active | AG6: Ceased | AH6: % | AI6: Active | AJ6: Ceased | AK6: % | AL6: Active | AM6: Ceased | AN6: %
C7: North | D7: Marco | E7: 42 | F7: 0 | G7: =IF(OR(E7="", F7=""), "", F7/E7) | H7: 44 | I7: 0 | J7: =IF(OR(H7="", I7=""), "", I7/H7) | K7: 47 | L7: 1 | M7: =IF(OR(K7="", L7=""), "", L7/K7) | N7: 46 | O7: 3 | P7: =IF(OR(N7="", O7=""), "", O7/N7) | W7: 42 | X7: 0 | Y7: =IF(OR(W7="", X7=""), "", X7/W7) | Z7: 44 | AA7: 0 | AB7: =IF(OR(Z7="", AA7=""), "", AA7/Z7) | AC7: 47 | AD7: 1 | AE7: =IF(OR(AC7="", AD7=""), "", AD7/AC7) | AF7: 46 | AG7: 3 | AH7: =IF(OR(AF7="", AG7=""), "", AG7/AF7)
C8: North | D8: Simran | E8: 47 | F8: 2 | G8: =IF(OR(E8="", F8=""), "", F8/E8) | H8: 48 | I8: 1 | J8: =IF(OR(H8="", I8=""), "", I8/H8) | K8: 51 | L8: 3 | M8: =IF(OR(K8="", L8=""), "", L8/K8) | N8: 53 | O8: 0 | P8: =IF(OR(N8="", O8=""), "", O8/N8) | W8: 47 | X8: 2 | Y8: =IF(OR(W8="", X8=""), "", X8/W8) | Z8: 48 | AA8: 1 | AB8: =IF(OR(Z8="", AA8=""), "", AA8/Z8) | AC8: 51 | AD8: 3 | AE8: =IF(OR(AC8="", AD8=""), "", AD8/AC8) | AF8: 53 | AG8: 0 | AH8: =IF(OR(AF8="", AG8=""), "", AG8/AF8)
C9: North | D9: Jay | E9: 61 | F9: 5 | G9: =IF(OR(E9="", F9=""), "", F9/E9) | H9: 57 | I9: 6 | J9: =IF(OR(H9="", I9=""), "", I9/H9) | K9: 58 | L9: 2 | M9: =IF(OR(K9="", L9=""), "", L9/K9) | N9: 58 | O9: 4 | P9: =IF(OR(N9="", O9=""), "", O9/N9) | W9: 61 | X9: 5 | Y9: =IF(OR(W9="", X9=""), "", X9/W9) | Z9: 57 | AA9: 6 | AB9: =IF(OR(Z9="", AA9=""), "", AA9/Z9) | AC9: 58 | AD9: 2 | AE9: =IF(OR(AC9="", AD9=""), "", AD9/AC9) | AF9: 58 | AG9: 4 | AH9: =IF(OR(AF9="", AG9=""), "", AG9/AF9)
C10: North | D10: Danny | E10: 23 | F10: 0 | G10: =IF(OR(E10="", F10=""), "", F10/E10) | H10: 25 | I10: 1 | J10: =IF(OR(H10="", I10=""), "", I10/H10) | K10: 20 | L10: 0 | M10: =IF(OR(K10="", L10=""), "", L10/K10) | N10: 20 | O10: 0 | P10: =IF(OR(N10="", O10=""), "", O10/N10) | W10: 23 | X10: 0 | Y10: =IF(OR(W10="", X10=""), "", X10/W10) | Z10: 25 | AA10: 1 | AB10: =IF(OR(Z10="", AA10=""), "", AA10/Z10) | AC10: 20 | AD10: 0 | AE10: =IF(OR(AC10="", AD10=""), "", AD10/AC10) | AF10: 20 | AG10: 0 | AH10: =IF(OR(AF10="", AG10=""), "", AG10/AF10)
C11: North | D11: Chris | E11: 39 | F11: 0 | G11: =IF(OR(E11="", F11=""), "", F11/E11) | H11: 43 | I11: 2 | J11: =IF(OR(H11="", I11=""), "", I11/H11) | K11: 42 | L11: 1 | M11: =IF(OR(K11="", L11=""), "", L11/K11) | N11: 49 | O11: 3 | P11: =IF(OR(N11="", O11=""), "", O11/N11) | W11: 39 | X11: 0 | Y11: =IF(OR(W11="", X11=""), "", X11/W11) | Z11: 43 | AA11: 2 | AB11: =IF(OR(Z11="", AA11=""), "", AA11/Z11) | AC11: 42 | AD11: 1 | AE11: =IF(OR(AC11="", AD11=""), "", AD11/AC11) | AF11: 49 | AG11: 3 | AH11: =IF(OR(AF11="", AG11=""), "", AG11/AF11)
C12: North | D12: Alice | E12: 54 | F12: 4 | G12: =IF(OR(E12="", F12=""), "", F12/E12) | H12: 55 | I12: 6 | J12: =IF(OR(H12="", I12=""), "", I12/H12) | K12: 57 | L12: 1 | M12: =IF(OR(K12="", L12=""), "", L12/K12) | N12: 54 | O12: 4 | P12: =IF(OR(N12="", O12=""), "", O12/N12) | W12: 54 | X12: 4 | Y12: =IF(OR(W12="", X12=""), "", X12/W12) | Z12: 55 | AA12: 6 | AB12: =IF(OR(Z12="", AA12=""), "", AA12/Z12) | AC12: 57 | AD12: 1 | AE12: =IF(OR(AC12="", AD12=""), "", AD12/AC12) | AF12: 54 | AG12: 4 | AH12: =IF(OR(AF12="", AG12=""), "", AG12/AF12)
C13: North | D13: Elizabeth | G13: =IF(OR(E13="", F13=""), "", F13/E13) | H13: 11 | I13: 1 | J13: =IF(OR(H13="", I13=""), "", I13/H13) | K13: 14 | L13: 0 | M13: =IF(OR(K13="", L13=""), "", L13/K13) | N13: 15 | O13: 0 | P13: =IF(OR(N13="", O13=""), "", O13/N13) | Y13: =IF(OR(W13="", X13=""), "", X13/W13) | Z13: 11 | AA13: 1 | AB13: =IF(OR(Z13="", AA13=""), "", AA13/Z13) | AC13: 14 | AD13: 0 | AE13: =IF(OR(AC13="", AD13=""), "", AD13/AC13) | AF13: 15 | AG13: 0 | AH13: =IF(OR(AF13="", AG13=""), "", AG13/AF13)
C14: North | D14: Eva | E14: 41 | F14: 3 | G14: =IF(OR(E14="", F14=""), "", F14/E14) | H14: 43 | I14: 2 | J14: =IF(OR(H14="", I14=""), "", I14/H14) | K14: 40 | L14: 2 | M14: =IF(OR(K14="", L14=""), "", L14/K14) | N14: 49 | O14: 1 | P14: =IF(OR(N14="", O14=""), "", O14/N14) | W14: 41 | X14: 3 | Y14: =IF(OR(W14="", X14=""), "", X14/W14) | Z14: 43 | AA14: 2 | AB14: =IF(OR(Z14="", AA14=""), "", AA14/Z14) | AC14: 40 | AD14: 2 | AE14: =IF(OR(AC14="", AD14=""), "", AD14/AC14) | AF14: 49 | AG14: 1 | AH14: =IF(OR(AF14="", AG14=""), "", AG14/AF14)
C15: South | D15: Maddie | E15: 21 | F15: 2 | G15: =IF(OR(E15="", F15=""), "", F15/E15) | H15: 17 | I15: 0 | J15: =IF(OR(H15="", I15=""), "", I15/H15) | K15: 17 | L15: 0 | M15: =IF(OR(K15="", L15=""), "", L15/K15) | N15: 20 | O15: 0 | P15: =IF(OR(N15="", O15=""), "", O15/N15) | W15: 21 | X15: 2 | Y15: =IF(OR(W15="", X15=""), "", X15/W15) | Z15: 17 | AA15: 0 | AB15: =IF(OR(Z15="", AA15=""), "", AA15/Z15) | AC15: 17 | AD15: 0 | AE15: =IF(OR(AC15="", AD15=""), "", AD15/AC15) | AF15: 20 | AG15: 0 | AH15: =IF(OR(AF15="", AG15=""), "", AG15/AF15)
C16: South | D16: Stephen | E16: 25 | F16: 3 | G16: =IF(OR(E16="", F16=""), "", F16/E16) | H16: 20 | I16: 1 | J16: =IF(OR(H16="", I16=""), "", I16/H16) | K16: 20 | L16: 0 | M16: =IF(OR(K16="", L16=""), "", L16/K16) | N16: 20 | O16: 0 | P16: =IF(OR(N16="", O16=""), "", O16/N16) | W16: 25 | X16: 3 | Y16: =IF(OR(W16="", X16=""), "", X16/W16) | Z16: 20 | AA16: 1 | AB16: =IF(OR(Z16="", AA16=""), "", AA16/Z16) | AC16: 20 | AD16: 0 | AE16: =IF(OR(AC16="", AD16=""), "", AD16/AC16) | AF16: 20 | AG16: 0 | AH16: =IF(OR(AF16="", AG16=""), "", AG16/AF16)
C17: South | D17: Beth | E17: 45 | F17: 1 | G17: =IF(OR(E17="", F17=""), "", F17/E17) | H17: 35 | I17: 2 | J17: =IF(OR(H17="", I17=""), "", I17/H17) | K17: 32 | L17: 1 | M17: =IF(OR(K17="", L17=""), "", L17/K17) | N17: 28 | O17: 0 | P17: =IF(OR(N17="", O17=""), "", O17/N17) | W17: 45 | X17: 1 | Y17: =IF(OR(W17="", X17=""), "", X17/W17) | Z17: 35 | AA17: 2 | AB17: =IF(OR(Z17="", AA17=""), "", AA17/Z17) | AC17: 32 | AD17: 1 | AE17: =IF(OR(AC17="", AD17=""), "", AD17/AC17) | AF17: 28 | AG17: 0 | AH17: =IF(OR(AF17="", AG17=""), "", AG17/AF17)
C18: South | D18: April | E18: 42 | F18: 0 | G18: =IF(OR(E18="", F18=""), "", F18/E18) | H18: 31 | I18: 2 | J18: =IF(OR(H18="", I18=""), "", I18/H18) | K18: 33 | L18: 4 | M18: =IF(OR(K18="", L18=""), "", L18/K18) | N18: 32 | O18: 1 | P18: =IF(OR(N18="", O18=""), "", O18/N18) | W18: 42 | X18: 0 | Y18: =IF(OR(W18="", X18=""), "", X18/W18) | Z18: 31 | AA18: 2 | AB18: =IF(OR(Z18="", AA18=""), "", AA18/Z18) | AC18: 33 | AD18: 4 | AE18: =IF(OR(AC18="", AD18=""), "", AD18/AC18) | AF18: 32 | AG18: 1 | AH18: =IF(OR(AF18="", AG18=""), "", AG18/AF18)
C19: South | D19: Felina | E19: 45 | F19: 3 | G19: =IF(OR(E19="", F19=""), "", F19/E19) | H19: 48 | I19: 1 | J19: =IF(OR(H19="", I19=""), "", I19/H19) | K19: 46 | L19: 4 | M19: =IF(OR(K19="", L19=""), "", L19/K19) | N19: 47 | O19: 1 | P19: =IF(OR(N19="", O19=""), "", O19/N19) | W19: 45 | X19: 3 | Y19: =IF(OR(W19="", X19=""), "", X19/W19) | Z19: 48 | AA19: 1 | AB19: =IF(OR(Z19="", AA19=""), "", AA19/Z19) | AC19: 46 | AD19: 4 | AE19: =IF(OR(AC19="", AD19=""), "", AD19/AC19) | AF19: 47 | AG19: 1 | AH19: =IF(OR(AF19="", AG19=""), "", AG19/AF19)
C20: South | D20: Stephanie | E20: 47 | F20: 1 | G20: =IF(OR(E20="", F20=""), "", F20/E20) | H20: 53 | I20: 1 | J20: =IF(OR(H20="", I20=""), "", I20/H20) | K20: 48 | L20: 1 | M20: =IF(OR(K20="", L20=""), "", L20/K20) | N20: 51 | O20: 3 | P20: =IF(OR(N20="", O20=""), "", O20/N20) | W20: 47 | X20: 1 | Y20: =IF(OR(W20="", X20=""), "", X20/W20) | Z20: 53 | AA20: 1 | AB20: =IF(OR(Z20="", AA20=""), "", AA20/Z20) | AC20: 48 | AD20: 1 | AE20: =IF(OR(AC20="", AD20=""), "", AD20/AC20) | AF20: 51 | AG20: 3 | AH20: =IF(OR(AF20="", AG20=""), "", AG20/AF20)
C21: South | D21: Vincent | E21: 32 | F21: 3 | G21: =IF(OR(E21="", F21=""), "", F21/E21) | H21: 35 | I21: 3 | J21: =IF(OR(H21="", I21=""), "", I21/H21) | K21: 33 | L21: 1 | M21: =IF(OR(K21="", L21=""), "", L21/K21) | N21: 33 | O21: 0 | P21: =IF(OR(N21="", O21=""), "", O21/N21) | W21: 32 | X21: 3 | Y21: =IF(OR(W21="", X21=""), "", X21/W21) | Z21: 35 | AA21: 3 | AB21: =IF(OR(Z21="", AA21=""), "", AA21/Z21) | AC21: 33 | AD21: 1 | AE21: =IF(OR(AC21="", AD21=""), "", AD21/AC21) | AF21: 33 | AG21: 0 | AH21: =IF(OR(AF21="", AG21=""), "", AG21/AF21)
C22: South | D22: Janice | E22: 8 | F22: 2 | G22: =IF(OR(E22="", F22=""), "", F22/E22) | H22: 14 | I22: 0 | J22: =IF(OR(H22="", I22=""), "", I22/H22) | K22: 16 | L22: 0 | M22: =IF(OR(K22="", L22=""), "", L22/K22) | N22: 17 | O22: 0 | P22: =IF(OR(N22="", O22=""), "", O22/N22) | W22: 8 | X22: 2 | Y22: =IF(OR(W22="", X22=""), "", X22/W22) | Z22: 14 | AA22: 0 | AB22: =IF(OR(Z22="", AA22=""), "", AA22/Z22) | AC22: 16 | AD22: 0 | AE22: =IF(OR(AC22="", AD22=""), "", AD22/AC22) | AF22: 17 | AG22: 0 | AH22: =IF(OR(AF22="", AG22=""), "", AG22/AF22)
C23: South | D23: Raj | E23: 43 | F23: 1 | G23: =IF(OR(E23="", F23=""), "", F23/E23) | H23: 44 | I23: 1 | J23: =IF(OR(H23="", I23=""), "", I23/H23) | K23: 39 | L23: 2 | M23: =IF(OR(K23="", L23=""), "", L23/K23) | N23: 44 | O23: 1 | P23: =IF(OR(N23="", O23=""), "", O23/N23) | W23: 43 | X23: 1 | Y23: =IF(OR(W23="", X23=""), "", X23/W23) | Z23: 44 | AA23: 1 | AB23: =IF(OR(Z23="", AA23=""), "", AA23/Z23) | AC23: 39 | AD23: 2 | AE23: =IF(OR(AC23="", AD23=""), "", AD23/AC23) | AF23: 44 | AG23: 1 | AH23: =IF(OR(AF23="", AG23=""), "", AG23/AF23)
C24: South | D24: Shirley | G24: =IF(OR(E24="", F24=""), "", F24/E24) | H24: 23 | I24: 1 | J24: =IF(OR(H24="", I24=""), "", I24/H24) | K24: 36 | L24: 4 | M24: =IF(OR(K24="", L24=""), "", L24/K24) | N24: 46 | O24: 5 | P24: =IF(OR(N24="", O24=""), "", O24/N24) | S24: =IF(OR(Q24="", R24=""), "", R24/Q24) | V24: =IF(OR(T24="", U24=""), "", U24/T24) | Y24: =IF(OR(W24="", X24=""), "", X24/W24) | Z24: 23 | AA24: 1 | AB24: =IF(OR(Z24="", AA24=""), "", AA24/Z24) | AC24: 36 | AD24: 4 | AE24: =IF(OR(AC24="", AD24=""), "", AD24/AC24) | AF24: 46 | AG24: 5 | AH24: =IF(OR(AF24="", AG24=""), "", AG24/AF24) | AK24: =IF(OR(AI24="", AJ24=""), "", AJ24/AI24) | AN24: =IF(OR(AL24="", AM24=""), "", AM24/AL24)
J25: =IF(OR(H25="", I25=""), "", I25/H25) | M25: =IF(OR(K25="", L25=""), "", L25/K25) | P25: =IF(OR(N25="", O25=""), "", O25/N25) | S25: =IF(OR(Q25="", R25=""), "", R25/Q25) | V25: =IF(OR(T25="", U25=""), "", U25/T25)
J26: =IF(OR(H26="", I26=""), "", I26/H26) | M26: =IF(OR(K26="", L26=""), "", L26/K26) | P26: =IF(OR(N26="", O26=""), "", O26/N26) | S26: =IF(OR(Q26="", R26=""), "", R26/Q26) | V26: =IF(OR(T26="", U26=""), "", U26/T26)
J31: =IF(OR(H31="", I31=""), "", I31/H31) | M31: =IF(OR(K31="", L31=""), "", L31/K31) | P31: =IF(OR(N31="", O31=""), "", O31/N31) | S31: =IF(OR(Q31="", R31=""), "", R31/Q31) | V31: =IF(OR(T31="", U31=""), "", U31/T31)
J32: =IF(OR(H32="", I32=""), "", I32/H32) | M32: =IF(OR(K32="", L32=""), "", L32/K32) | P32: =IF(OR(N32="", O32=""), "", O32/N32) | S32: =IF(OR(Q32="", R32=""), "", R32/Q32) | V32: =IF(OR(T32="", U32=""), "", U32/T32)
J33: =IF(OR(H33="", I33=""), "", I33/H33) | M33: =IF(OR(K33="", L33=""), "", L33/K33) | P33: =IF(OR(N33="", O33=""), "", O33/N33) | S33: =IF(OR(Q33="", R33=""), "", R33/Q33) | V33: =IF(OR(T33="", U33=""), "", U33/T33)
J34: =IF(OR(H34="", I34=""), "", I34/H34) | M34: =IF(OR(K34="", L34=""), "", L34/K34) | P34: =IF(OR(N34="", O34=""), "", O34/N34) | S34: =IF(OR(Q34="", R34=""), "", R34/Q34) | V34: =IF(OR(T34="", U34=""), "", U34/T34)
J35: =IF(OR(H35="", I35=""), "", I35/H35) | M35: =IF(OR(K35="", L35=""), "", L35/K35) | P35: =IF(OR(N35="", O35=""), "", O35/N35) | S35: =IF(OR(Q35="", R35=""), "", R35/Q35) | V35: =IF(OR(T35="", U35=""), "", U35/T35)
J36: =IF(OR(H36="", I36=""), "", I36/H36) | M36: =IF(OR(K36="", L36=""), "", L36/K36) | P36: =IF(OR(N36="", O36=""), "", O36/N36) | S36: =IF(OR(Q36="", R36=""), "", R36/Q36) | V36: =IF(OR(T36="", U36=""), "", U36/T36)
J37: =IF(OR(H37="", I37=""), "", I37/H37) | M37: =IF(OR(K37="", L37=""), "", L37/K37) | P37: =IF(OR(N37="", O37=""), "", O37/N37) | S37: =IF(OR(Q37="", R37=""), "", R37/Q37) | V37: =IF(OR(T37="", U37=""), "", U37/T37)
J38: =IF(OR(H38="", I38=""), "", I38/H38) | M38: =IF(OR(K38="", L38=""), "", L38/K38) | P38: =IF(OR(N38="", O38=""), "", O38/N38) | S38: =IF(OR(Q38="", R38=""), "", R38/Q38) | V38: =IF(OR(T38="", U38=""), "", U38/T38)
J39: =IF(OR(H39="", I39=""), "", I39/H39) | M39: =IF(OR(K39="", L39=""), "", L39/K39) | P39: =IF(OR(N39="", O39=""), "", O39/N39) | S39: =IF(OR(Q39="", R39=""), "", R39/Q39) | V39: =IF(OR(T39="", U39=""), "", U39/T39)

Sheet Ceased reasons
A2: Therapist | B2: Month | C2: Client name | D2: Ceased Services/On Hold | E2: Client Type | F2: Reason for ceasing | I2: Therapists
A3: Alice | B3: 45839 | C3: Ursula Fredes-Ojeda | D3: Ceased Services | F3: Wants male physio in the area | I3: Alice
A4: Alice | B4: 45839 | C4: Olivia Baker | D4: Ceased Services | F4: On hold Feb 2025 - Remaining funds used for report instead of sessions - plan ending 5/6/25 Offboarded 16/7 - plan has ended and sc hasn’t gotten back to us. | I4: April
A5: Alice | B5: 45839 | C5: Stuart Bennier | D5: Ceased Services | F5: Working with a different physio - Physio services cancelled effective immediately - As previously advised, Stuart is currently working with a different physiotherapist. I had clearly outlined in my earlier correspondence that only Occupational Therapy services are required from Melbourne Physio, not Physiotherapy. | I5: Beth
A6: Alice | B6: 45839 | C6: Sotiria Niaros | D6: Ceased Services | F6: Family decided to discontinue services | I6: Chris
A7: Beth | B7: 45839 | C7: Uncle Lenny Evans | D7: Ceased Services | F7: feels physio is not working and he will be getting a massage chair instead | I7: Danny
A8: Eva | B8: 45839 | C8: Valerie Perry | D8: Ceased Services | F8: Referral was only for equipment, ongoing not required | I8: Elizabeth
A9: Eva | B9: 45839 | C9: Giancarlo Pera | D9: Ceased Services | F9: Neck feels better and has many appointments going on | I9: Eva
A10: Eva | B10: 45839 | C10: Corey Saffin | D10: Ceased Services | F10: No funds in new plan | I10: Felina
A11: Felina | B11: 45839 | C11: Dwayne Rushton | D11: Ceased Services | F11: Client request due to MMP cancellations | I11: Janice
A12: Felina | B12: 45839 | C12: Nha Fa Si | D12: Ceased Services | F12: son requested to cease the physio due to the cost unfortunately | I12: Jay
A13: Felina | B13: 45839 | C13: Lief Pangestu | D13: Ceased Services | F13: On hold since 7/5/25 - Ceased as he has been on hold and said when he msgd felina to resume he didnt hear back from her. Declined a free session | I13: Maddie
A14: Janice | B14: 45839 | C14: Charlie Welch | D14: Ceased Services | F14: From SC: Charlie has advised me she would no longer wants to proceed ahead with your services | I14: Marco
... A22: Maddie | B22: 45839 | C22: Peter Maple | D22: Ceased Services | F22: can’t afford to continue due to financials | I22: Dan H
A23: Raj | B23: 45839 | C23: Helmut Drobbe | D23: Ceased Services | F23: Doesn't need physio at this stage
A24: Simran | B24: 45839 | C24: Kanella Boussioutas | D24: Ceased Services | F24: CM emailed to cease services
A25: Simran | B25: 45839 | C25: Martine Hyde | D25: Ceased Services | F25: 14/7/25 Offboarded - Martine's NDIS plan has rolled over, but she has decided not to continue with physiotherapy services at this time.
A26: Stephanie | B26: 45839 | C26: Gael Lynas | D26: Ceased Services | F26: Transition to EP as part of new plan
A27: Stephen | B27: 45839 | C27: Jackie Cardente | D27: Ceased Services | F27: Don't have any physios that suit her needs
A28: Stephen | B28: 45839 | C28: Maria Metaxas | D28: Ceased Services | F28: Once off request, services no longer required
A29: Stephen | B29: 45839 | C29: David Plot | D29: Ceased Services | F29: Services no longer required
A30: Vincent | B30: 45839 | C30: Kathleen Stewart | D30: Ceased Services | F30: No longer requires physio
A31: Vincent | B31: 45839 | C31: Daniel Jamison | D31: Ceased Services | F31: Will be handed over to a Clinic Physio from aug
A32: Vincent | B32: 45839 | C32: Ruya Hashmi | D32: Ceased Services | F32: Ruya cant afford 45mins sessions and Insurance wont be paying.
A33: April | B33: 45839 | C33: Kerryn Wright | D33: On Hold | F33: she is currently having some health issues and is unable to push herself with Physiotherapy due to her lungs being inflamed. She must have tests for oxygen volumes etc and is finding any exertion is adding to the discomfort in her lungs and having to use her oxygen again
A34: Alice | B34: 45870 | C34: Faduma Hassan | D34: Ceased Services | E34: HC | F34: Went with another provider for hydro
A35: Felina | B35: 45870 | C35: Ralph Barthelot | D35: On Hold | F35: decided not to proceed with weekly physiotherapy sessions - no further feedback provided
A36: Raj | B36: 45870 | C36: Marie Francoise Gobbi | D36: On Hold | F36: CM: Please put this on hold for now as the client is very resistive to the Physio sessions.
A37: Alice | B37: 45870 | C37: Paul Omera | D37: Ceased Services | E37: TAC | F37: TAC approved for in clinic now
A38: Alice | B38: 45870 | C38: Vivien Omera | D38: Ceased Services | E38: TAC | F38: TAC approved for in clinic now
A39: Alice | B39: 45870 | C39: David King | D39: Ceased Services | E39: HC | F39: No future appts, hasn't had appt since December 2024
A40: April | B40: 45870 | C40: Deanne Leslie | D40: On Hold | F40: Low funding
A41: Alice | B41: 45870 | C41: Daniar Karimi | D41: Ceased Services | E41: NDIS | F41: Unhappy with service
A42: April | B42: 45870 | C42: John Mead | D42: Ceased Services | E42: HC | F42: I would like to cancel my client John Mead’s physiotherapy service moving forward due to his HCP being needed for other essential services. I would like to thank the physiotherapist for her support during this time and the positive impact that it has had for John. Should he wish to re-engage with MMP I will let you know.
A43: April | B43: 45870 | C43: Kevin Leacy | D43: Ceased Services | E43: HC | F43: I went out to see Kevin today and discussed physio however he feels that he doesn’t need to continue with services as he is doing well now however if he needs services in the future I will be in touch.
A44: Alice | B44: 45870 | C44: Peter King | D44: On Hold | F44: Cancelled initial appt - can’t do physio for 6 weeks
A45: Beth | B45: 45870 | C45: Rosa Ciccone | D45: Ceased Services | E45: HC | F45: unhappy with recent cancellations due to beth being unwell
A46: Marco | B46: 45870 | C46: Larry Carrigan | D46: On Hold | F46: Larry received a new plan but unfortunately it didn’t contain funding for Physio we’ve currently got a review being worked on by NDIS to fix the situation and we should be able to resume services when this is sorted.
A47: Beth | B47: 45870 | C47: Jenny Murphy | D47: Ceased Services | E47: HC | F47: Email from CM to cxl referral
A48: Chris | B48: 45870 | C48: Suad Edais | D48: Ceased Services | E48: TAC | F48: No longer approved
A49: Chris | B49: 45870 | C49: Dimitri Theodorou | D49: Ceased Services | E49: HC | F49: Too expensive for his HC budget
A50: Stephen | B50: 45870 | C50: Natalie Israel | D50: On Hold | F50: only 5 hrs allocated for physio in new plan SC Bec said to complete 1 session then put on hold until further notice
A51: Janice | B51: 45870 | C51: Penelope Kalos | D51: On Hold | F51: going away for a few months from 23 aug
A52: Eva | B52: 45870 | C52: Jeffry Babb | D52: On Hold | F52: Unfortunately, there has been a recent turn in Jeffry’s health. As a result, we kindly request that his physiotherapy sessions be cancelled until further notice.
A53: Stephanie | B53: 45870 | C53: Lucas Jackson | D53: On Hold | F53: Low funding
A54: Eva | B54: 45870 | C54: Maria Atsaves | D54: Ceased Services | E54: HC | F54: Maria is now having different treatment from a myotherapist which seems to be helping her significantly.
A55: Eva | B55: 45870 | C55: Donna Higham | D55: Ceased Services | E55: Private | F55: No physio sessions since Feb 2025 - she had originally booked a physio appt but when physio attended she declined and mentioned she made a mistake she doesn't want physio
A56: Eva | B56: 45870 | C56: Hari Singh | D56: Ceased Services | E56: HC | F56: doesnt wish to continue as he says he doesn’t need it
A57: Felina | B57: 45870 | C57: Valerie Wylie | D57: Ceased Services | E57: HC | F57: CM request to cancel services
A58: Felina | B58: 45870 | C58: Ioanna Tsadilas | D58: Ceased Services | E58: NDIS | F58: SC: I have just been instructed to cancel all Physio sessions for Ioanna moving forward. no feedback provided
A59: Felina | B59: 45870 | C59: Bruno De Machelis | D59: Ceased Services | E59: Private | F59: No longer required, goals met
A60: Felina | B60: 45870 | C60: June McCahill | D60: Ceased Services | E60: Private | F60: 23/4/25 SD - On hold - Going with My Aged Care provider, will resume with us if unhappy - want to book with Felina if rebooking 27/8/25 SD - Offboarded - No response when following up resuming
A61: Jay | B61: 45870 | C61: Trajan Talevski | D61: Ceased Services | E61: HC | F61: email from CM: Trajan no longer requires this service and is asking to cancel all of the upcoming appointments.
A62: Jay | B62: 45870 | C62: Margaret Sinclair | D62: Ceased Services | E62: HC | F62: canceled as she said the physio doesn’t attend, however we don’t attend as we’re not able to get a hold of her to confirm the appts
A63: Jay | B63: 45870 | C63: Annabell Johnson | D63: Ceased Services | E63: NDIS | F63: no appts booked, mum isn’t replying to our calls and emails
A64: Jay | B64: 45870 | C64: Sadie Johnson | D64: Ceased Services | E64: NDIS | F64: no appts booked, mum isn’t replying to our calls and emails
A65: Jay | B65: 45870 | C65: Amineh Neissi | D65: Ceased Services | E65: NDIS | F65: OOF
A66: Jay | B66: 45870 | C66: Efmorfia Katanos | D66: Ceased Services | E66: HC | F66: never received approval to book on going and this HCP have cancelled all clients with us
A67: Eva | B67: 45870 | C67: Marilyn Lorraine Cuttriss Mealy | D67: On Hold | F67: used up EPC, daughter happy with progress and said that she'll get back to us if she needs more support
A68: Eva | B68: 45870 | C68: Jason Giddings | D68: On Hold | F68: waiting for foot ucler to heal
A69: Eva | B69: 45870 | C69: Maria Wataszczuk | D69: On Hold | F69: doesn’t want to do hydro during colder months
A70: Simran | B70: 45870 | C70: Feriha Emirali | D70: On Hold | F70: In respite from 12/8/25
A71: Raj | B71: 45870 | C71: Cheryl Rodrigo | D71: Ceased Services | E71: NDIS | F71: I have spoken with Alston he has advised he is going to have Cheryl attend a physio clinic instead of home visits for Cheryl now
A72: Raj | B72: 45870 | C72: Alston Rodrigo | D72: Ceased Services | E72: Private | F72: Services no longer required
A73: Shirley | B73: 45870 | C73: Jill Jackson | D73: Ceased Services | E73: Private | F73: feeling confident to do daily exercises on her own. Very grateful for the team and thankful of the team
A74: Felina | B74: 45870 | C74: Christine Rubens | D74: On Hold | F74: Her T12 fracture I think needs repairing before she can proceed.. I have been in touch with a surgeon about doing a kyphoplasty, a procedure she had done very successfully in 2021 on her T6. Services on hold until after the procedure.
A75: Shirley | B75: 45870 | C75: Nicki Iliadis | D75: Ceased Services | E75: HC | F75: felt sore after her massage sessions and doesn’t want massage
A76: Simran | B76: 45870 | C76: Rohini Nath | D76: Ceased Services | E76: NDIS | F76: SC called to let us know they weren’t happy with the service and going with someone else
A77: Alice | B77: 45870 | C77: Robyn Baker | D77: On Hold | F77: asked to go on hold while she sorts out her funding. Said she will give us call when she is ready to resume
A78: April | B78: 45870 | C78: Assunta Tardio | D78: On Hold | F78: in hospital and needing to go on hold please. Her daughter will contact us when she's out and ready to resume
A79: Chris | B79: 45870 | C79: Colin Cook | D79: On Hold | F79: unwell at the moment to be considered for ongoing sessions
A80: Simran | B80: 45870 | C80: Karen Davenport | D80: Ceased Services | E80: NDIS | F80: no appts booked as not hearing about from SC. A while ago mentioned no hours remaining
A81: Stephanie | B81: 45870 | C81: Peter Groves | D81: Ceased Services | E81: Private | F81: one-time private client
A82: Stephen | B82: 45870 | C82: Edward Mogilevsky | D82: On Hold | F82: just wanted to remind that we stop physio for for some time. We let you know date when we're ready for physio Thank you very much for assistance Kind regards Alla
A83: Simran | B83: 45870 | C83: Elenora Mare | D83: On Hold | F83: Too much happening with mum and tues appts not working out. offered to move appts to other days, but still answered no
A84: Stephen | B84: 45870 | C84: Polly Kamberos | D84: Ceased Services | E84: HC | F84: CM emailed - Polly likely too unwell for physio
A85: Vincent | B85: 45870 | C85: Tony Greco | D85: Ceased Services | E85: HC | F85: walker recommendation completed - no further services required
A86: Vincent | B86: 45870 | C86: Jennifer Hartney | D86: Ceased Services | E86: Private | F86: private client was in alot of pain. Called the next day to say how amazing Vincent is and to let us know that he has magically healed her. no further services required
A87: Simran | B87: 45870 | C87: Maria Pietrobuono | D87: On Hold | F87: She is over the budget and cannot afford until we get the upgrade of the package.
A88: Vincent | B88: 45870 | C88: Gary Webber | D88: Ceased Services | E88: HC | F88: OOF
A89: Shirley | B89: 45870 | C89: Wendy Bee | D89: On Hold | F89: going into hospital with unknown discharge at this stage.
A90: Stephanie | B90: 45870 | C90: Helen Flanigan | D90: On Hold | F90: Helen's family still really want Helen to do physio however Helen is very resistant. Johanna mentioned that Helen's decline in cognition is making her very resistive to alot of things and not just Stephanie and physio and Helens memory for appointments and other things are declining. She would really appreciate if we contacted Helens daughter in a few weeks time to see if she is ready to resume and discuss if they would like to keep with Steph or try another therapist when she is ready to return.
A91: Janice | B91: 45870 | C91: Van Yen Nguyen | D91: On Hold | F91: He’s just wanting to go away and visit family for a few weeks since he’s feeling so well again.
A92: Vincent | B92: 45870 | C92: Laurence Muscat | D92: Ceased Services | E92: HC | F92: CM: Please be advised that my above client will be cancelling all future appointments until further notice. TP requested feedback
A93: Raj | B93: 45870 | C93: Wilvamalar Rasaratnam | D93: On Hold | F93: family visiting from overseas and asked us to check in with her in October
A94: Danny | B94: 45870 | C94: Effat Namazi | D94: On Hold | F94: Trying a new Persian speaking physio and will call us later to book with Danny if needed
A95: Alice | B95: 45901 | C95: Patricia Zougaib | D95: On Hold | E95: NDIS | F95: using remaining hours for end of plan report
A96: Alice | B96: 45901 | C96: Michael Grech | D96: Ceased Services | E96: NDIS | F96: 8/1 In hospital and no funds until new plan (12/9/25) 17/9 change to cease now as he doesnt want to reengage
A97: Alice | B97: 45901 | C97: Tesfay Seyoum | D97: On Hold | E97: NDIS | F97: Unwell
A98: Amanda | B98: 45901 | C98: Mia Denton | D98: Ceased Services | E98: NDIS | F98: unfortunately Mia won’t require any further services at the moment.
A99: April | B99: 45901 | C99: Annie Mitchell | D99: Ceased Services | E99: HC | F99: her son Errol has requested to cancel the Physiotherapy for the time being.,
A100: April | B100: 45901 | C100: Margaret Cairns | D100: Ceased Services | E100: HC | F100: CM request: would like to cancel her physio services ongoing.
A101: April | B101: 45901 | C101: Janet Johns | D101: Ceased Services | E101: HC | F101: 4/6/25 SD - On hold - CM: We just feel at the moment that it is not doing anything for her, she really likes Felina but she whinges and asks for it to be cancelled every fortnight, she is just not in the right space. Thanks to Felina for her effort. 22/9/25 SD - Offboarded - Physio no longer required
A102: April | B102: 45901 | C102: Judith Brooks | D102: Ceased Services | E102: HC | F102: Judi has decided to not go ahead with the OT and would also like to cancel ongoing physio session please.
A103: April | B103: 45901 | C103: Elisa Cretella | D103: On Hold | E103: HC | F103: 23/9 From CM: Elisa Cretella's DTR yesterday to cancel the physio for her ongoing. No issues at all, but she wants to have a break. I don't think at this stage she will take it up again for a while, she is also prioritising family so is busy with family coming and going.
A104: April | B104: 45901 | C104: Jeff Shaw | D104: Ceased Services | E104: HC | F104: text to cease services - From CM: He is going away for a few weeks so, I think it could be cancelled just until he gets back. I will chase up when he returns.
A105: April | B105: 45901 | C105: Shirley Leach | D105: Ceased Services | E105: HC | F105: From CM: I would like to request on her behalf that the monthly physiotherapy visit be cancelled please but she said she will call you directly when she needs to be seen if possible
A106: Beth | B106: 45901 | C106: Nancy Venville | D106: Ceased Services | E106: HC | F106: 16/05 email from CM: Due to current budget constraints can we please suspend Nancy Venvilles physiotherapy with Beth until further notice. 15/9 TP emailed CM to check in - CM response: I did speak with her last week about the possibility of returning to physio, or even just a one off check in? She mentioned that she feels it is not currently necessary, but she will keep it in mind and we will continue to check with her also.
... A109: Danny | B109: 45901 | C109: Helen Aivaliotis | D109: On Hold | E109: HC | F109: CM emailed to go on hold due to low funding
A110: Elizabeth | B110: 45901 | C110: Tina Ng | D110: On Hold | F110: Called to advise would like to go on hold as she has had her baby.
...

Sheet FTE
A1: Team Member | B1: FTE | C1: Team | D1: Jan | E1: Feb | F1: Mar | G1: Apr | H1: May | I1: June | J1: July | K1: Aug | L1: Sept | M1: Oct | N1: Nov | O1: Dec
A2: Marco | B2: 1 | C2: Physio_North | D2: =IFERROR(IF($C2="Physio_North",INDEX('KPI Dashboard North'!$C:$C,MATCH($A2,'KPI Dashboard North'!$B:$B,0)),IF($C2="Physio_South",INDEX('KPI Dashboard South'!$C:$C,MATCH($A2,'KPI Dashboard South'!$B:$B,0)),INDEX('KPI Dashboard OT'!$C:$C,MATCH($A2,'KPI Dashboard OT'!$B:$B,0))))*B2,"") | E2: =IFERROR(IF($C2="Physio_North",INDEX('KPI Dashboard North'!$D:$D,MATCH($A2,'KPI Dashboard North'!$B:$B,0)),IF($C2="Physio_South",INDEX('KPI Dashboard South'!$D:$D,MATCH($A2,'KPI Dashboard South'!$B:$B,0)),INDEX('KPI Dashboard OT'!$D:$D,MATCH($A2,'KPI Dashboard OT'!$B:$B,0))))*$B2,"") | F2: =IFERROR(IF($C2="Physio_North",INDEX('KPI Dashboard North'!$E:$E,MATCH($A2,'KPI Dashboard North'!$B:$B,0)),IF($C2="Physio_South",INDEX('KPI Dashboard South'!$E:$E,MATCH($A2,'KPI Dashboard South'!$B:$B,0)),INDEX('KPI Dashboard OT'!$E:$E,MATCH($A2,'KPI Dashboard OT'!$B:$B,0))))*$B2,"") | G2: =IFERROR(IF($C2="Physio_North",INDEX('KPI Dashboard North'!$F:$F,MATCH($A2,'KPI Dashboard North'!$B:$B,0)),IF($C2="Physio_South",INDEX('KPI Dashboard South'!$F:$F,MATCH($A2,'KPI Dashboard South'!$B:$B,0)),INDEX('KPI Dashboard OT'!$F:$F,MATCH($A2,'KPI Dashboard OT'!$B:$B,0))))*$B2,"") | H2: =IFERROR(IF($C2="Physio_North",INDEX('KPI Dashboard North'!$G:$G,MATCH($A2,'KPI Dashboard North'!$B:$B,0)),IF($C2="Physio_South",INDEX('KPI Dashboard South'!$G:$G,MATCH($A2,'KPI Dashboard South'!$B:$B,0)),INDEX('KPI Dashboard OT'!$G:$G,MATCH($A2,'KPI Dashboard OT'!$B:$B,0))))*$B2,"") | I2: =IFERROR(IF($C2="Physio_North",INDEX('KPI Dashboard North'!$H:$H,MATCH($A2,'KPI Dashboard North'!$B:$B,0)),IF($C2="Physio_South",INDEX('KPI Dashboard South'!$H:$H,MATCH($A2,'KPI Dashboard South'!$B:$B,0)),INDEX('KPI Dashboard OT'!$H:$H,MATCH($A2,'KPI Dashboard OT'!$B:$B,0))))*$B2,"") | J2: =IFERROR(IF($C2="Physio_North",INDEX('KPI Dashboard North'!$I:$I,MATCH($A2,'KPI Dashboard North'!$B:$B,0)),IF($C2="Physio_South",INDEX('KPI Dashboard South'!$I:$I,MATCH($A2,'KPI Dashboard South'!$B:$B,0)),INDEX('KPI Dashboard OT'!$I:$I,MATCH($A2,'KPI Dashboard OT'!$B:$B,0))))*$B2,"") | K2: =IFERROR(IF($C2="Physio_North",INDEX('KPI Dashboard North'!$J:$J,MATCH($A2,'KPI Dashboard North'!$B:$B,0)),IF($C2="Physio_South",INDEX('KPI Dashboard South'!$J:$J,MATCH($A2,'KPI Dashboard South'!$B:$B,0)),INDEX('KPI Dashboard OT'!$J:$J,MATCH($A2,'KPI Dashboard OT'!$B:$B,0))))*$B2,"") | L2: =IFERROR(IF($C2="Physio_North",INDEX('KPI Dashboard North'!$K:$K,MATCH($A2,'KPI Dashboard North'!$B:$B,0)),IF($C2="Physio_South",INDEX('KPI Dashboard South'!$K:$K,MATCH($A2,'KPI Dashboard South'!$B:$B,0)),INDEX('KPI Dashboard OT'!$K:$K,MATCH($A2,'KPI Dashboard OT'!$B:$B,0))))*$B2,"") | M2: =IFERROR(IF($C2="Physio_North",INDEX('KPI Dashboard North'!$L:$L,MATCH($A2,'KPI Dashboard North'!$B:$B,0)),IF($C2="Physio_South",INDEX('KPI Dashboard South'!$L:$L,MATCH($A2,'KPI Dashboard South'!$B:$B,0)),INDEX('KPI Dashboard OT'!$L:$L,MATCH($A2,'KPI Dashboard OT'!$B:$B,0))))*$B2,"") | N2: =IFERROR(IF($C2="Physio_North",INDEX('KPI Dashboard North'!$M:$M,MATCH($A2,'KPI Dashboard North'!$B:$B,0)),IF($C2="Physio_South",INDEX('KPI Dashboard South'!$M:$M,MATCH($A2,'KPI Dashboard South'!$B:$B,0)),INDEX('KPI Dashboard OT'!$M:$M,MATCH($A2,'KPI Dashboard OT'!$B:$B,0))))*$B2,"") | O2: =IFERROR(IF($C2="Physio_North",INDEX('KPI Dashboard North'!$N:$N,MATCH($A2,'KPI Dashboard North'!$B:$B,0)),IF($C2="Physio_South",INDEX('KPI Dashboard South'!$N:$N,MATCH($A2,'KPI Dashboard South'!$B:$B,0)),INDEX('KPI Dashboard OT'!$N:$N,MATCH($A2,'KPI Dashboard OT'!$B:$B,0))))*$B2,"")
A3: Danny | B3: 0.4 | C3: Physio_North | D3: =IFERROR(IF($C3="Physio_North",INDEX('KPI Dashboard North'!$C:$C,MATCH($A3,'KPI Dashboard North'!$B:$B,0)),IF($C3="Physio_South",INDEX('KPI Dashboard South'!$C:$C,MATCH($A3,'KPI Dashboard South'!$B:$B,0)),INDEX('KPI Dashboard OT'!$C:$C,MATCH($A3,'KPI Dashboard OT'!$B:$B,0))))*B3,"") | E3: =IFERROR(IF($C3="Physio_North",INDEX('KPI Dashboard North'!$D:$D,MATCH($A3,'KPI Dashboard North'!$B:$B,0)),IF($C3="Physio_South",INDEX('KPI Dashboard South'!$D:$D,MATCH($A3,'KPI Dashboard South'!$B:$B,0)),INDEX('KPI Dashboard OT'!$D:$D,MATCH($A3,'KPI Dashboard OT'!$B:$B,0))))*$B3,"") | F3: =IFERROR(IF($C3="Physio_North",INDEX('KPI Dashboard North'!$E:$E,MATCH($A3,'KPI Dashboard North'!$B:$B,0)),IF($C3="Physio_South",INDEX('KPI Dashboard South'!$E:$E,MATCH($A3,'KPI Dashboard South'!$B:$B,0)),INDEX('KPI Dashboard OT'!$E:$E,MATCH($A3,'KPI Dashboard OT'!$B:$B,0))))*$B3,"") | G3: =IFERROR(IF($C3="Physio_North",INDEX('KPI Dashboard North'!$F:$F,MATCH($A3,'KPI Dashboard North'!$B:$B,0)),IF($C3="Physio_South",INDEX('KPI Dashboard South'!$F:$F,MATCH($A3,'KPI Dashboard South'!$B:$B,0)),INDEX('KPI Dashboard OT'!$F:$F,MATCH($A3,'KPI Dashboard OT'!$B:$B,0))))*$B3,"") | H3: =IFERROR(IF($C3="Physio_North",INDEX('KPI Dashboard North'!$G:$G,MATCH($A3,'KPI Dashboard North'!$B:$B,0)),IF($C3="Physio_South",INDEX('KPI Dashboard South'!$G:$G,MATCH($A3,'KPI Dashboard South'!$B:$B,0)),INDEX('KPI Dashboard OT'!$G:$G,MATCH($A3,'KPI Dashboard OT'!$B:$B,0))))*$B3,"") | I3: =IFERROR(IF($C3="Physio_North",INDEX('KPI Dashboard North'!$H:$H,MATCH($A3,'KPI Dashboard North'!$B:$B,0)),IF($C3="Physio_South",INDEX('KPI Dashboard South'!$H:$H,MATCH($A3,'KPI Dashboard South'!$B:$B,0)),INDEX('KPI Dashboard OT'!$H:$H,MATCH($A3,'KPI Dashboard OT'!$B:$B,0))))*$B3,"") | J3: =IFERROR(IF($C3="Physio_North",INDEX('KPI Dashboard North'!$I:$I,MATCH($A3,'KPI Dashboard North'!$B:$B,0)),IF($C3="Physio_South",INDEX('KPI Dashboard South'!$I:$I,MATCH($A3,'KPI Dashboard South'!$B:$B,0)),INDEX('KPI Dashboard OT'!$I:$I,MATCH($A3,'KPI Dashboard OT'!$B:$B,0))))*$B3,"") | K3: =IFERROR(IF($C3="Physio_North",INDEX('KPI Dashboard North'!$J:$J,MATCH($A3,'KPI Dashboard North'!$B:$B,0)),IF($C3="Physio_South",INDEX('KPI Dashboard South'!$J:$J,MATCH($A3,'KPI Dashboard South'!$B:$B,0)),INDEX('KPI Dashboard OT'!$J:$J,MATCH($A3,'KPI Dashboard OT'!$B:$B,0))))*$B3,"") | L3: =IFERROR(IF($C3="Physio_North",INDEX('KPI Dashboard North'!$K:$K,MATCH($A3,'KPI Dashboard North'!$B:$B,0)),IF($C3="Physio_South",INDEX('KPI Dashboard South'!$K:$K,MATCH($A3,'KPI Dashboard South'!$B:$B,0)),INDEX('KPI Dashboard OT'!$K:$K,MATCH($A3,'KPI Dashboard OT'!$B:$B,0))))*$B3,"") | M3: =IFERROR(IF($C3="Physio_North",INDEX('KPI Dashboard North'!$L:$L,MATCH($A3,'KPI Dashboard North'!$B:$B,0)),IF($C3="Physio_South",INDEX('KPI Dashboard South'!$L:$L,MATCH($A3,'KPI Dashboard South'!$B:$B,0)),INDEX('KPI Dashboard OT'!$L:$L,MATCH($A3,'KPI Dashboard OT'!$B:$B,0))))*$B3,"") | N3: =IFERROR(IF($C3="Physio_North",INDEX('KPI Dashboard North'!$M:$M,MATCH($A3,'KPI Dashboard North'!$B:$B,0)),IF($C3="Physio_South",INDEX('KPI Dashboard South'!$M:$M,MATCH($A3,'KPI Dashboard South'!$B:$B,0)),INDEX('KPI Dashboard OT'!$M:$M,MATCH($A3,'KPI Dashboard OT'!$B:$B,0))))*$B3,"") | O3: =IFERROR(IF($C3="Physio_North",INDEX('KPI Dashboard North'!$N:$N,MATCH($A3,'KPI Dashboard North'!$B:$B,0)),IF($C3="Physio_South",INDEX('KPI Dashboard South'!$N:$N,MATCH($A3,'KPI Dashboard South'!$B:$B,0)),INDEX('KPI Dashboard OT'!$N:$N,MATCH($A3,'KPI Dashboard OT'!$B:$B,0))))*$B3,"")
A4: Alice | B4: 1 | C4: Physio_North | D4: =IFERROR(IF($C4="Physio_North",INDEX('KPI Dashboard North'!$C:$C,MATCH($A4,'KPI Dashboard North'!$B:$B,0)),IF($C4="Physio_South",INDEX('KPI Dashboard South'!$C:$C,MATCH($A4,'KPI Dashboard South'!$B:$B,0)),INDEX('KPI Dashboard OT'!$C:$C,MATCH($A4,'KPI Dashboard OT'!$B:$B,0))))*B4,"") | E4: =IFERROR(IF($C4="Physio_North",INDEX('KPI Dashboard North'!$D:$D,MATCH($A4,'KPI Dashboard North'!$B:$B,0)),IF($C4="Physio_South",INDEX('KPI Dashboard South'!$D:$D,MATCH($A4,'KPI Dashboard South'!$B:$B,0)),INDEX('KPI Dashboard OT'!$D:$D,MATCH($A4,'KPI Dashboard OT'!$B:$B,0))))*$B4,"") | F4: =IFERROR(IF($C4="Physio_North",INDEX('KPI Dashboard North'!$E:$E,MATCH($A4,'KPI Dashboard North'!$B:$B,0)),IF($C4="Physio_South",INDEX('KPI Dashboard South'!$E:$E,MATCH($A4,'KPI Dashboard South'!$B:$B,0)),INDEX('KPI Dashboard OT'!$E:$E,MATCH($A4,'KPI Dashboard OT'!$B:$B,0))))*$B4,"") | G4: =IFERROR(IF($C4="Physio_North",INDEX('KPI Dashboard North'!$F:$F,MATCH($A4,'KPI Dashboard North'!$B:$B,0)),IF($C4="Physio_South",INDEX('KPI Dashboard South'!$F:$F,MATCH($A4,'KPI Dashboard South'!$B:$B,0)),INDEX('KPI Dashboard OT'!$F:$F,MATCH($A4,'KPI Dashboard OT'!$B:$B,0))))*$B4,"") | H4: =IFERROR(IF($C4="Physio_North",INDEX('KPI Dashboard North'!$G:$G,MATCH($A4,'KPI Dashboard North'!$B:$B,0)),IF($C4="Physio_South",INDEX('KPI Dashboard South'!$G:$G,MATCH($A4,'KPI Dashboard South'!$B:$B,0)),INDEX('KPI Dashboard OT'!$G:$G,MATCH($A4,'KPI Dashboard OT'!$B:$B,0))))*$B4,"") | I4: =IFERROR(IF($C4="Physio_North",INDEX('KPI Dashboard North'!$H:$H,MATCH($A4,'KPI Dashboard North'!$B:$B,0)),IF($C4="Physio_South",INDEX('KPI Dashboard South'!$H:$H,MATCH($A4,'KPI Dashboard South'!$B:$B,0)),INDEX('KPI Dashboard OT'!$H:$H,MATCH($A4,'KPI Dashboard OT'!$B:$B,0))))*$B4,"") | J4: =IFERROR(IF($C4="Physio_North",INDEX('KPI Dashboard North'!$I:$I,MATCH($A4,'KPI Dashboard North'!$B:$B,0)),IF($C4="Physio_South",INDEX('KPI Dashboard South'!$I:$I,MATCH($A4,'KPI Dashboard South'!$B:$B,0)),INDEX('KPI Dashboard OT'!$I:$I,MATCH($A4,'KPI Dashboard OT'!$B:$B,0))))*$B4,"") | K4: =IFERROR(IF($C4="Physio_North",INDEX('KPI Dashboard North'!$J:$J,MATCH($A4,'KPI Dashboard North'!$B:$B,0)),IF($C4="Physio_South",INDEX('KPI Dashboard South'!$J:$J,MATCH($A4,'KPI Dashboard South'!$B:$B,0)),INDEX('KPI Dashboard OT'!$J:$J,MATCH($A4,'KPI Dashboard OT'!$B:$B,0))))*$B4,"") | L4: =IFERROR(IF($C4="Physio_North",INDEX('KPI Dashboard North'!$K:$K,MATCH($A4,'KPI Dashboard North'!$B:$B,0)),IF($C4="Physio_South",INDEX('KPI Dashboard South'!$K:$K,MATCH($A4,'KPI Dashboard South'!$B:$B,0)),INDEX('KPI Dashboard OT'!$K:$K,MATCH($A4,'KPI Dashboard OT'!$B:$B,0))))*$B4,"") | M4: =IFERROR(IF($C4="Physio_North",INDEX('KPI Dashboard North'!$L:$L,MATCH($A4,'KPI Dashboard North'!$B:$B,0)),IF($C4="Physio_South",INDEX('KPI Dashboard South'!$L:$L,MATCH($A4,'KPI Dashboard South'!$B:$B,0)),INDEX('KPI Dashboard OT'!$L:$L,MATCH($A4,'KPI Dashboard OT'!$B:$B,0))))*$B4,"") | N4: =IFERROR(IF($C4="Physio_North",INDEX('KPI Dashboard North'!$M:$M,MATCH($A4,'KPI Dashboard North'!$B:$B,0)),IF($C4="Physio_South",INDEX('KPI Dashboard South'!$M:$M,MATCH($A4,'KPI Dashboard South'!$B:$B,0)),INDEX('KPI Dashboard OT'!$M:$M,MATCH($A4,'KPI Dashboard OT'!$B:$B,0))))*$B4,"") | O4: =IFERROR(IF($C4="Physio_North",INDEX('KPI Dashboard North'!$N:$N,MATCH($A4,'KPI Dashboard North'!$B:$B,0)),IF($C4="Physio_South",INDEX('KPI Dashboard South'!$N:$N,MATCH($A4,'KPI Dashboard South'!$B:$B,0)),INDEX('KPI Dashboard OT'!$N:$N,MATCH($A4,'KPI Dashboard OT'!$B:$B,0))))*$B4,"")
A5: April | B5: 0.8 | C5: Physio_North | D5: =IFERROR(IF($C5="Physio_North",INDEX('KPI Dashboard North'!$C:$C,MATCH($A5,'KPI Dashboard North'!$B:$B,0)),IF($C5="Physio_South",INDEX('KPI Dashboard South'!$C:$C,MATCH($A5,'KPI Dashboard South'!$B:$B,0)),INDEX('KPI Dashboard OT'!$C:$C,MATCH($A5,'KPI Dashboard OT'!$B:$B,0))))*B5,"") | E5: =IFERROR(IF($C5="Physio_North",INDEX('KPI Dashboard North'!$D:$D,MATCH($A5,'KPI Dashboard North'!$B:$B,0)),IF($C5="Physio_South",INDEX('KPI Dashboard South'!$D:$D,MATCH($A5,'KPI Dashboard South'!$B:$B,0)),INDEX('KPI Dashboard OT'!$D:$D,MATCH($A5,'KPI Dashboard OT'!$B:$B,0))))*$B5,"") | F5: =IFERROR(IF($C5="Physio_North",INDEX('KPI Dashboard North'!$E:$E,MATCH($A5,'KPI Dashboard North'!$B:$B,0)),IF($C5="Physio_South",INDEX('KPI Dashboard South'!$E:$E,MATCH($A5,'KPI Dashboard South'!$B:$B,0)),INDEX('KPI Dashboard OT'!$E:$E,MATCH($A5,'KPI Dashboard OT'!$B:$B,0))))*$B5,"") | G5: =IFERROR(IF($C5="Physio_North",INDEX('KPI Dashboard North'!$F:$F,MATCH($A5,'KPI Dashboard North'!$B:$B,0)),IF($C5="Physio_South",INDEX('KPI Dashboard South'!$F:$F,MATCH($A5,'KPI Dashboard South'!$B:$B,0)),INDEX('KPI Dashboard OT'!$F:$F,MATCH($A5,'KPI Dashboard OT'!$B:$B,0))))*$B5,"") | H5: =IFERROR(IF($C5="Physio_North",INDEX('KPI Dashboard North'!$G:$G,MATCH($A5,'KPI Dashboard North'!$B:$B,0)),IF($C5="Physio_South",INDEX('KPI Dashboard South'!$G:$G,MATCH($A5,'KPI Dashboard South'!$B:$B,0)),INDEX('KPI Dashboard OT'!$G:$G,MATCH($A5,'KPI Dashboard OT'!$B:$B,0))))*$B5,"") | I5: =IFERROR(IF($C5="Physio_North",INDEX('KPI Dashboard North'!$H:$H,MATCH($A5,'KPI Dashboard North'!$B:$B,0)),IF($C5="Physio_South",INDEX('KPI Dashboard South'!$H:$H,MATCH($A5,'KPI Dashboard South'!$B:$B,0)),INDEX('KPI Dashboard OT'!$H:$H,MATCH($A5,'KPI Dashboard OT'!$B:$B,0))))*$B5,"") | J5: =IFERROR(IF($C5="Physio_North",INDEX('KPI Dashboard North'!$I:$I,MATCH($A5,'KPI Dashboard North'!$B:$B,0)),IF($C5="Physio_South",INDEX('KPI Dashboard South'!$I:$I,MATCH($A5,'KPI Dashboard South'!$B:$B,0)),INDEX('KPI Dashboard OT'!$I:$I,MATCH($A5,'KPI Dashboard OT'!$B:$B,0))))*$B5,"") | K5: =IFERROR(IF($C5="Physio_North",INDEX('KPI Dashboard North'!$J:$J,MATCH($A5,'KPI Dashboard North'!$B:$B,0)),IF($C5="Physio_South",INDEX('KPI Dashboard South'!$J:$J,MATCH($A5,'KPI Dashboard South'!$B:$B,0)),INDEX('KPI Dashboard OT'!$J:$J,MATCH($A5,'KPI Dashboard OT'!$B:$B,0))))*$B5,"") | L5: =IFERROR(IF($C5="Physio_North",INDEX('KPI Dashboard North'!$K:$K,MATCH($A5,'KPI Dashboard North'!$B:$B,0)),IF($C5="Physio_South",INDEX('KPI Dashboard South'!$K:$K,MATCH($A5,'KPI Dashboard South'!$B:$B,0)),INDEX('KPI Dashboard OT'!$K:$K,MATCH($A5,'KPI Dashboard OT'!$B:$B,0))))*$B5,"") | M5: =IFERROR(IF($C5="Physio_North",INDEX('KPI Dashboard North'!$L:$L,MATCH($A5,'KPI Dashboard North'!$B:$B,0)),IF($C5="Physio_South",INDEX('KPI Dashboard South'!$L:$L,MATCH($A5,'KPI Dashboard South'!$B:$B,0)),INDEX('KPI Dashboard OT'!$L:$L,MATCH($A5,'KPI Dashboard OT'!$B:$B,0))))*$B5,"") | N5: =IFERROR(IF($C5="Physio_North",INDEX('KPI Dashboard North'!$M:$M,MATCH($A5,'KPI Dashboard North'!$B:$B,0)),IF($C5="Physio_South",INDEX('KPI Dashboard South'!$M:$M,MATCH($A5,'KPI Dashboard South'!$B:$B,0)),INDEX('KPI Dashboard OT'!$M:$M,MATCH($A5,'KPI Dashboard OT'!$B:$B,0))))*$B5,"") | O5: =IFERROR(IF($C5="Physio_North",INDEX('KPI Dashboard North'!$N:$N,MATCH($A5,'KPI Dashboard North'!$B:$B,0)),IF($C5="Physio_South",INDEX('KPI Dashboard South'!$N:$N,MATCH($A5,'KPI Dashboard South'!$B:$B,0)),INDEX('KPI Dashboard OT'!$N:$N,MATCH($A5,'KPI Dashboard OT'!$B:$B,0))))*$B5,"")
A6: Chris | B6: 1 | C6: Physio_North | D6: =IFERROR(IF($C6="Physio_North",INDEX('KPI Dashboard North'!$C:$C,MATCH($A6,'KPI Dashboard North'!$B:$B,0)),IF($C6="Physio_South",INDEX('KPI Dashboard South'!$C:$C,MATCH($A6,'KPI Dashboard South'!$B:$B,0)),INDEX('KPI Dashboard OT'!$C:$C,MATCH($A6,'KPI Dashboard OT'!$B:$B,0))))*B6,"") | E6: =IFERROR(IF($C6="Physio_North",INDEX('KPI Dashboard North'!$D:$D,MATCH($A6,'KPI Dashboard North'!$B:$B,0)),IF($C6="Physio_South",INDEX('KPI Dashboard South'!$D:$D,MATCH($A6,'KPI Dashboard South'!$B:$B,0)),INDEX('KPI Dashboard OT'!$D:$D,MATCH($A6,'KPI Dashboard OT'!$B:$B,0))))*$B6,"") | F6: =IFERROR(IF($C6="Physio_North",INDEX('KPI Dashboard North'!$E:$E,MATCH($A6,'KPI Dashboard North'!$B:$B,0)),IF($C6="Physio_South",INDEX('KPI Dashboard South'!$E:$E,MATCH($A6,'KPI Dashboard South'!$B:$B,0)),INDEX('KPI Dashboard OT'!$E:$E,MATCH($A6,'KPI Dashboard OT'!$B:$B,0))))*$B6,"") | G6: =IFERROR(IF($C6="Physio_North",INDEX('KPI Dashboard North'!$F:$F,MATCH($A6,'KPI Dashboard North'!$B:$B,0)),IF($C6="Physio_South",INDEX('KPI Dashboard South'!$F:$F,MATCH($A6,'KPI Dashboard South'!$B:$B,0)),INDEX('KPI Dashboard OT'!$F:$F,MATCH($A6,'KPI Dashboard OT'!$B:$B,0))))*$B6,"") | H6: =IFERROR(IF($C6="Physio_North",INDEX('KPI Dashboard North'!$G:$G,MATCH($A6,'KPI Dashboard North'!$B:$B,0)),IF($C6="Physio_South",INDEX('KPI Dashboard South'!$G:$G,MATCH($A6,'KPI Dashboard South'!$B:$B,0)),INDEX('KPI Dashboard OT'!$G:$G,MATCH($A6,'KPI Dashboard OT'!$B:$B,0))))*$B6,"") | I6: =IFERROR(IF($C6="Physio_North",INDEX('KPI Dashboard North'!$H:$H,MATCH($A6,'KPI Dashboard North'!$B:$B,0)),IF($C6="Physio_South",INDEX('KPI Dashboard South'!$H:$H,MATCH($A6,'KPI Dashboard South'!$B:$B,0)),INDEX('KPI Dashboard OT'!$H:$H,MATCH($A6,'KPI Dashboard OT'!$B:$B,0))))*$B6,"") | J6: =IFERROR(IF($C6="Physio_North",INDEX('KPI Dashboard North'!$I:$I,MATCH($A6,'KPI Dashboard North'!$B:$B,0)),IF($C6="Physio_South",INDEX('KPI Dashboard South'!$I:$I,MATCH($A6,'KPI Dashboard South'!$B:$B,0)),INDEX('KPI Dashboard OT'!$I:$I,MATCH($A6,'KPI Dashboard OT'!$B:$B,0))))*$B6,"") | K6: =IFERROR(IF($C6="Physio_North",INDEX('KPI Dashboard North'!$J:$J,MATCH($A6,'KPI Dashboard North'!$B:$B,0)),IF($C6="Physio_South",INDEX('KPI Dashboard South'!$J:$J,MATCH($A6,'KPI Dashboard South'!$B:$B,0)),INDEX('KPI Dashboard OT'!$J:$J,MATCH($A6,'KPI Dashboard OT'!$B:$B,0))))*$B6,"") | L6: =IFERROR(IF($C6="Physio_North",INDEX('KPI Dashboard North'!$K:$K,MATCH($A6,'KPI Dashboard North'!$B:$B,0)),IF($C6="Physio_South",INDEX('KPI Dashboard South'!$K:$K,MATCH($A6,'KPI Dashboard South'!$B:$B,0)),INDEX('KPI Dashboard OT'!$K:$K,MATCH($A6,'KPI Dashboard OT'!$B:$B,0))))*$B6,"") | M6: =IFERROR(IF($C6="Physio_North",INDEX('KPI Dashboard North'!$L:$L,MATCH($A6,'KPI Dashboard North'!$B:$B,0)),IF($C6="Physio_South",INDEX('KPI Dashboard South'!$L:$L,MATCH($A6,'KPI Dashboard South'!$B:$B,0)),INDEX('KPI Dashboard OT'!$L:$L,MATCH($A6,'KPI Dashboard OT'!$B:$B,0))))*$B6,"") | N6: =IFERROR(IF($C6="Physio_North",INDEX('KPI Dashboard North'!$M:$M,MATCH($A6,'KPI Dashboard North'!$B:$B,0)),IF($C6="Physio_South",INDEX('KPI Dashboard South'!$M:$M,MATCH($A6,'KPI Dashboard South'!$B:$B,0)),INDEX('KPI Dashboard OT'!$M:$M,MATCH($A6,'KPI Dashboard OT'!$B:$B,0))))*$B6,"") | O6: =IFERROR(IF($C6="Physio_North",INDEX('KPI Dashboard North'!$N:$N,MATCH($A6,'KPI Dashboard North'!$B:$B,0)),IF($C6="Physio_South",INDEX('KPI Dashboard South'!$N:$N,MATCH($A6,'KPI Dashboard South'!$B:$B,0)),INDEX('KPI Dashboard OT'!$N:$N,MATCH($A6,'KPI Dashboard OT'!$B:$B,0))))*$B6,"")
A7: Emilie | B7: 1 | C7: Physio_North | D7: =IFERROR(IF($C7="Physio_North",INDEX('KPI Dashboard North'!$C:$C,MATCH($A7,'KPI Dashboard North'!$B:$B,0)),IF($C7="Physio_South",INDEX('KPI Dashboard South'!$C:$C,MATCH($A7,'KPI Dashboard South'!$B:$B,0)),INDEX('KPI Dashboard OT'!$C:$C,MATCH($A7,'KPI Dashboard OT'!$B:$B,0))))*B7,"") | E7: =IFERROR(IF($C7="Physio_North",INDEX('KPI Dashboard North'!$D:$D,MATCH($A7,'KPI Dashboard North'!$B:$B,0)),IF($C7="Physio_South",INDEX('KPI Dashboard South'!$D:$D,MATCH($A7,'KPI Dashboard South'!$B:$B,0)),INDEX('KPI Dashboard OT'!$D:$D,MATCH($A7,'KPI Dashboard OT'!$B:$B,0))))*$B7,"") | F7: =IFERROR(IF($C7="Physio_North",INDEX('KPI Dashboard North'!$E:$E,MATCH($A7,'KPI Dashboard North'!$B:$B,0)),IF($C7="Physio_South",INDEX('KPI Dashboard South'!$E:$E,MATCH($A7,'KPI Dashboard South'!$B:$B,0)),INDEX('KPI Dashboard OT'!$E:$E,MATCH($A7,'KPI Dashboard OT'!$B:$B,0))))*$B7,"") | G7: =IFERROR(IF($C7="Physio_North",INDEX('KPI Dashboard North'!$F:$F,MATCH($A7,'KPI Dashboard North'!$B:$B,0)),IF($C7="Physio_South",INDEX('KPI Dashboard South'!$F:$F,MATCH($A7,'KPI Dashboard South'!$B:$B,0)),INDEX('KPI Dashboard OT'!$F:$F,MATCH($A7,'KPI Dashboard OT'!$B:$B,0))))*$B7,"") | H7: =IFERROR(IF($C7="Physio_North",INDEX('KPI Dashboard North'!$G:$G,MATCH($A7,'KPI Dashboard North'!$B:$B,0)),IF($C7="Physio_South",INDEX('KPI Dashboard South'!$G:$G,MATCH($A7,'KPI Dashboard South'!$B:$B,0)),INDEX('KPI Dashboard OT'!$G:$G,MATCH($A7,'KPI Dashboard OT'!$B:$B,0))))*$B7,"") | I7: =IFERROR(IF($C7="Physio_North",INDEX('KPI Dashboard North'!$H:$H,MATCH($A7,'KPI Dashboard North'!$B:$B,0)),IF($C7="Physio_South",INDEX('KPI Dashboard South'!$H:$H,MATCH($A7,'KPI Dashboard South'!$B:$B,0)),INDEX('KPI Dashboard OT'!$H:$H,MATCH($A7,'KPI Dashboard OT'!$B:$B,0))))*$B7,"") | J7: =IFERROR(IF($C7="Physio_North",INDEX('KPI Dashboard North'!$I:$I,MATCH($A7,'KPI Dashboard North'!$B:$B,0)),IF($C7="Physio_South",INDEX('KPI Dashboard South'!$I:$I,MATCH($A7,'KPI Dashboard South'!$B:$B,0)),INDEX('KPI Dashboard OT'!$I:$I,MATCH($A7,'KPI Dashboard OT'!$B:$B,0))))*$B7,"") | K7: =IFERROR(IF($C7="Physio_North",INDEX('KPI Dashboard North'!$J:$J,MATCH($A7,'KPI Dashboard North'!$B:$B,0)),IF($C7="Physio_South",INDEX('KPI Dashboard South'!$J:$J,MATCH($A7,'KPI Dashboard South'!$B:$B,0)),INDEX('KPI Dashboard OT'!$J:$J,MATCH($A7,'KPI Dashboard OT'!$B:$B,0))))*$B7,"") | L7: =IFERROR(IF($C7="Physio_North",INDEX('KPI Dashboard North'!$K:$K,MATCH($A7,'KPI Dashboard North'!$B:$B,0)),IF($C7="Physio_South",INDEX('KPI Dashboard South'!$K:$K,MATCH($A7,'KPI Dashboard South'!$B:$B,0)),INDEX('KPI Dashboard OT'!$K:$K,MATCH($A7,'KPI Dashboard OT'!$B:$B,0))))*$B7,"") | M7: =IFERROR(IF($C7="Physio_North",INDEX('KPI Dashboard North'!$L:$L,MATCH($A7,'KPI Dashboard North'!$B:$B,0)),IF($C7="Physio_South",INDEX('KPI Dashboard South'!$L:$L,MATCH($A7,'KPI Dashboard South'!$B:$B,0)),INDEX('KPI Dashboard OT'!$L:$L,MATCH($A7,'KPI Dashboard OT'!$B:$B,0))))*$B7,"") | N7: =IFERROR(IF($C7="Physio_North",INDEX('KPI Dashboard North'!$M:$M,MATCH($A7,'KPI Dashboard North'!$B:$B,0)),IF($C7="Physio_South",INDEX('KPI Dashboard South'!$M:$M,MATCH($A7,'KPI Dashboard South'!$B:$B,0)),INDEX('KPI Dashboard OT'!$M:$M,MATCH($A7,'KPI Dashboard OT'!$B:$B,0))))*$B7,"") | O7: =IFERROR(IF($C7="Physio_North",INDEX('KPI Dashboard North'!$N:$N,MATCH($A7,'KPI Dashboard North'!$B:$B,0)),IF($C7="Physio_South",INDEX('KPI Dashboard South'!$N:$N,MATCH($A7,'KPI Dashboard South'!$B:$B,0)),INDEX('KPI Dashboard OT'!$N:$N,MATCH($A7,'KPI Dashboard OT'!$B:$B,0))))*$B7,"")
A8: Eva | B8: 1 | C8: Physio_North | D8: =IFERROR(IF($C8="Physio_North",INDEX('KPI Dashboard North'!$C:$C,MATCH($A8,'KPI Dashboard North'!$B:$B,0)),IF($C8="Physio_South",INDEX('KPI Dashboard South'!$C:$C,MATCH($A8,'KPI Dashboard South'!$B:$B,0)),INDEX('KPI Dashboard OT'!$C:$C,MATCH($A8,'KPI Dashboard OT'!$B:$B,0))))*B8,"") | E8: =IFERROR(IF($C8="Physio_North",INDEX('KPI Dashboard North'!$D:$D,MATCH($A8,'KPI Dashboard North'!$B:$B,0)),IF($C8="Physio_South",INDEX('KPI Dashboard South'!$D:$D,MATCH($A8,'KPI Dashboard South'!$B:$B,0)),INDEX('KPI Dashboard OT'!$D:$D,MATCH($A8,'KPI Dashboard OT'!$B:$B,0))))*$B8,"") | F8: =IFERROR(IF($C8="Physio_North",INDEX('KPI Dashboard North'!$E:$E,MATCH($A8,'KPI Dashboard North'!$B:$B,0)),IF($C8="Physio_South",INDEX('KPI Dashboard South'!$E:$E,MATCH($A8,'KPI Dashboard South'!$B:$B,0)),INDEX('KPI Dashboard OT'!$E:$E,MATCH($A8,'KPI Dashboard OT'!$B:$B,0))))*$B8,"") | G8: =IFERROR(IF($C8="Physio_North",INDEX('KPI Dashboard North'!$F:$F,MATCH($A8,'KPI Dashboard North'!$B:$B,0)),IF($C8="Physio_South",INDEX('KPI Dashboard South'!$F:$F,MATCH($A8,'KPI Dashboard South'!$B:$B,0)),INDEX('KPI Dashboard OT'!$F:$F,MATCH($A8,'KPI Dashboard OT'!$B:$B,0))))*$B8,"") | H8: =IFERROR(IF($C8="Physio_North",INDEX('KPI Dashboard North'!$G:$G,MATCH($A8,'KPI Dashboard North'!$B:$B,0)),IF($C8="Physio_South",INDEX('KPI Dashboard South'!$G:$G,MATCH($A8,'KPI Dashboard South'!$B:$B,0)),INDEX('KPI Dashboard OT'!$G:$G,MATCH($A8,'KPI Dashboard OT'!$B:$B,0))))*$B8,"") | I8: =IFERROR(IF($C8="Physio_North",INDEX('KPI Dashboard North'!$H:$H,MATCH($A8,'KPI Dashboard North'!$B:$B,0)),IF($C8="Physio_South",INDEX('KPI Dashboard South'!$H:$H,MATCH($A8,'KPI Dashboard South'!$B:$B,0)),INDEX('KPI Dashboard OT'!$H:$H,MATCH($A8,'KPI Dashboard OT'!$B:$B,0))))*$B8,"") | J8: =IFERROR(IF($C8="Physio_North",INDEX('KPI Dashboard North'!$I:$I,MATCH($A8,'KPI Dashboard North'!$B:$B,0)),IF($C8="Physio_South",INDEX('KPI Dashboard South'!$I:$I,MATCH($A8,'KPI Dashboard South'!$B:$B,0)),INDEX('KPI Dashboard OT'!$I:$I,MATCH($A8,'KPI Dashboard OT'!$B:$B,0))))*$B8,"") | K8: =IFERROR(IF($C8="Physio_North",INDEX('KPI Dashboard North'!$J:$J,MATCH($A8,'KPI Dashboard North'!$B:$B,0)),IF($C8="Physio_South",INDEX('KPI Dashboard South'!$J:$J,MATCH($A8,'KPI Dashboard South'!$B:$B,0)),INDEX('KPI Dashboard OT'!$J:$J,MATCH($A8,'KPI Dashboard OT'!$B:$B,0))))*$B8,"") | L8: =IFERROR(IF($C8="Physio_North",INDEX('KPI Dashboard North'!$K:$K,MATCH($A8,'KPI Dashboard North'!$B:$B,0)),IF($C8="Physio_South",INDEX('KPI Dashboard South'!$K:$K,MATCH($A8,'KPI Dashboard South'!$B:$B,0)),INDEX('KPI Dashboard OT'!$K:$K,MATCH($A8,'KPI Dashboard OT'!$B:$B,0))))*$B8,"") | M8: =IFERROR(IF($C8="Physio_North",INDEX('KPI Dashboard North'!$L:$L,MATCH($A8,'KPI Dashboard North'!$B:$B,0)),IF($C8="Physio_South",INDEX('KPI Dashboard South'!$L:$L,MATCH($A8,'KPI Dashboard South'!$B:$B,0)),INDEX('KPI Dashboard OT'!$L:$L,MATCH($A8,'KPI Dashboard OT'!$B:$B,0))))*$B8,"") | N8: =IFERROR(IF($C8="Physio_North",INDEX('KPI Dashboard North'!$M:$M,MATCH($A8,'KPI Dashboard North'!$B:$B,0)),IF($C8="Physio_South",INDEX('KPI Dashboard South'!$M:$M,MATCH($A8,'KPI Dashboard South'!$B:$B,0)),INDEX('KPI Dashboard OT'!$M:$M,MATCH($A8,'KPI Dashboard OT'!$B:$B,0))))*$B8,"") | O8: =IFERROR(IF($C8="Physio_North",INDEX('KPI Dashboard North'!$N:$N,MATCH($A8,'KPI Dashboard North'!$B:$B,0)),IF($C8="Physio_South",INDEX('KPI Dashboard South'!$N:$N,MATCH($A8,'KPI Dashboard South'!$B:$B,0)),INDEX('KPI Dashboard OT'!$N:$N,MATCH($A8,'KPI Dashboard OT'!$B:$B,0))))*$B8,"")
A9: Jackson | B9: 0.6 | C9: Physio_North | D9: =IFERROR(IF($C9="Physio_North",INDEX('KPI Dashboard North'!$C:$C,MATCH($A9,'KPI Dashboard North'!$B:$B,0)),IF($C9="Physio_South",INDEX('KPI Dashboard South'!$C:$C,MATCH($A9,'KPI Dashboard South'!$B:$B,0)),INDEX('KPI Dashboard OT'!$C:$C,MATCH($A9,'KPI Dashboard OT'!$B:$B,0))))*B9,"") | E9: =IFERROR(IF($C9="Physio_North",INDEX('KPI Dashboard North'!$D:$D,MATCH($A9,'KPI Dashboard North'!$B:$B,0)),IF($C9="Physio_South",INDEX('KPI Dashboard South'!$D:$D,MATCH($A9,'KPI Dashboard South'!$B:$B,0)),INDEX('KPI Dashboard OT'!$D:$D,MATCH($A9,'KPI Dashboard OT'!$B:$B,0))))*$B9,"") | F9: =IFERROR(IF($C9="Physio_North",INDEX('KPI Dashboard North'!$E:$E,MATCH($A9,'KPI Dashboard North'!$B:$B,0)),IF($C9="Physio_South",INDEX('KPI Dashboard South'!$E:$E,MATCH($A9,'KPI Dashboard South'!$B:$B,0)),INDEX('KPI Dashboard OT'!$E:$E,MATCH($A9,'KPI Dashboard OT'!$B:$B,0))))*$B9,"") | G9: =IFERROR(IF($C9="Physio_North",INDEX('KPI Dashboard North'!$F:$F,MATCH($A9,'KPI Dashboard North'!$B:$B,0)),IF($C9="Physio_South",INDEX('KPI Dashboard South'!$F:$F,MATCH($A9,'KPI Dashboard South'!$B:$B,0)),INDEX('KPI Dashboard OT'!$F:$F,MATCH($A9,'KPI Dashboard OT'!$B:$B,0))))*$B9,"") | H9: =IFERROR(IF($C9="Physio_North",INDEX('KPI Dashboard North'!$G:$G,MATCH($A9,'KPI Dashboard North'!$B:$B,0)),IF($C9="Physio_South",INDEX('KPI Dashboard South'!$G:$G,MATCH($A9,'KPI Dashboard South'!$B:$B,0)),INDEX('KPI Dashboard OT'!$G:$G,MATCH($A9,'KPI Dashboard OT'!$B:$B,0))))*$B9,"") | I9: =IFERROR(IF($C9="Physio_North",INDEX('KPI Dashboard North'!$H:$H,MATCH($A9,'KPI Dashboard North'!$B:$B,0)),IF($C9="Physio_South",INDEX('KPI Dashboard South'!$H:$H,MATCH($A9,'KPI Dashboard South'!$B:$B,0)),INDEX('KPI Dashboard OT'!$H:$H,MATCH($A9,'KPI Dashboard OT'!$B:$B,0))))*$B9,"") | J9: =IFERROR(IF($C9="Physio_North",INDEX('KPI Dashboard North'!$I:$I,MATCH($A9,'KPI Dashboard North'!$B:$B,0)),IF($C9="Physio_South",INDEX('KPI Dashboard South'!$I:$I,MATCH($A9,'KPI Dashboard South'!$B:$B,0)),INDEX('KPI Dashboard OT'!$I:$I,MATCH($A9,'KPI Dashboard OT'!$B:$B,0))))*$B9,"") | K9: =IFERROR(IF($C9="Physio_North",INDEX('KPI Dashboard North'!$J:$J,MATCH($A9,'KPI Dashboard North'!$B:$B,0)),IF($C9="Physio_South",INDEX('KPI Dashboard South'!$J:$J,MATCH($A9,'KPI Dashboard South'!$B:$B,0)),INDEX('KPI Dashboard OT'!$J:$J,MATCH($A9,'KPI Dashboard OT'!$B:$B,0))))*$B9,"") | L9: =IFERROR(IF($C9="Physio_North",INDEX('KPI Dashboard North'!$K:$K,MATCH($A9,'KPI Dashboard North'!$B:$B,0)),IF($C9="Physio_South",INDEX('KPI Dashboard South'!$K:$K,MATCH($A9,'KPI Dashboard South'!$B:$B,0)),INDEX('KPI Dashboard OT'!$K:$K,MATCH($A9,'KPI Dashboard OT'!$B:$B,0))))*$B9,"") | M9: =IFERROR(IF($C9="Physio_North",INDEX('KPI Dashboard North'!$L:$L,MATCH($A9,'KPI Dashboard North'!$B:$B,0)),IF($C9="Physio_South",INDEX('KPI Dashboard South'!$L:$L,MATCH($A9,'KPI Dashboard South'!$B:$B,0)),INDEX('KPI Dashboard OT'!$L:$L,MATCH($A9,'KPI Dashboard OT'!$B:$B,0))))*$B9,"") | N9: =IFERROR(IF($C9="Physio_North",INDEX('KPI Dashboard North'!$M:$M,MATCH($A9,'KPI Dashboard North'!$B:$B,0)),IF($C9="Physio_South",INDEX('KPI Dashboard South'!$M:$M,MATCH($A9,'KPI Dashboard South'!$B:$B,0)),INDEX('KPI Dashboard OT'!$M:$M,MATCH($A9,'KPI Dashboard OT'!$B:$B,0))))*$B9,"") | O9: =IFERROR(IF($C9="Physio_North",INDEX('KPI Dashboard North'!$N:$N,MATCH($A9,'KPI Dashboard North'!$B:$B,0)),IF($C9="Physio_South",INDEX('KPI Dashboard South'!$N:$N,MATCH($A9,'KPI Dashboard South'!$B:$B,0)),INDEX('KPI Dashboard OT'!$N:$N,MATCH($A9,'KPI Dashboard OT'!$B:$B,0))))*$B9,"")
A10: Jay | B10: 1 | C10: Physio_North | D10: =IFERROR(IF($C10="Physio_North",INDEX('KPI Dashboard North'!$C:$C,MATCH($A10,'KPI Dashboard North'!$B:$B,0)),IF($C10="Physio_South",INDEX('KPI Dashboard South'!$C:$C,MATCH($A10,'KPI Dashboard South'!$B:$B,0)),INDEX('KPI Dashboard OT'!$C:$C,MATCH($A10,'KPI Dashboard OT'!$B:$B,0))))*B10,"") | E10: =IFERROR(IF($C10="Physio_North",INDEX('KPI Dashboard North'!$D:$D,MATCH($A10,'KPI Dashboard North'!$B:$B,0)),IF($C10="Physio_South",INDEX('KPI Dashboard South'!$D:$D,MATCH($A10,'KPI Dashboard South'!$B:$B,0)),INDEX('KPI Dashboard OT'!$D:$D,MATCH($A10,'KPI Dashboard OT'!$B:$B,0))))*$B10,"") | F10: =IFERROR(IF($C10="Physio_North",INDEX('KPI Dashboard North'!$E:$E,MATCH($A10,'KPI Dashboard North'!$B:$B,0)),IF($C10="Physio_South",INDEX('KPI Dashboard South'!$E:$E,MATCH($A10,'KPI Dashboard South'!$B:$B,0)),INDEX('KPI Dashboard OT'!$E:$E,MATCH($A10,'KPI Dashboard OT'!$B:$B,0))))*$B10,"") | G10: =IFERROR(IF($C10="Physio_North",INDEX('KPI Dashboard North'!$F:$F,MATCH($A10,'KPI Dashboard North'!$B:$B,0)),IF($C10="Physio_South",INDEX('KPI Dashboard South'!$F:$F,MATCH($A10,'KPI Dashboard South'!$B:$B,0)),INDEX('KPI Dashboard OT'!$F:$F,MATCH($A10,'KPI Dashboard OT'!$B:$B,0))))*$B10,"") | H10: =IFERROR(IF($C10="Physio_North",INDEX('KPI Dashboard North'!$G:$G,MATCH($A10,'KPI Dashboard North'!$B:$B,0)),IF($C10="Physio_South",INDEX('KPI Dashboard South'!$G:$G,MATCH($A10,'KPI Dashboard South'!$B:$B,0)),INDEX('KPI Dashboard OT'!$G:$G,MATCH($A10,'KPI Dashboard OT'!$B:$B,0))))*$B10,"") | I10: =IFERROR(IF($C10="Physio_North",INDEX('KPI Dashboard North'!$H:$H,MATCH($A10,'KPI Dashboard North'!$B:$B,0)),IF($C10="Physio_South",INDEX('KPI Dashboard South'!$H:$H,MATCH($A10,'KPI Dashboard South'!$B:$B,0)),INDEX('KPI Dashboard OT'!$H:$H,MATCH($A10,'KPI Dashboard OT'!$B:$B,0))))*$B10,"") | J10: =IFERROR(IF($C10="Physio_North",INDEX('KPI Dashboard North'!$I:$I,MATCH($A10,'KPI Dashboard North'!$B:$B,0)),IF($C10="Physio_South",INDEX('KPI Dashboard South'!$I:$I,MATCH($A10,'KPI Dashboard South'!$B:$B,0)),INDEX('KPI Dashboard OT'!$I:$I,MATCH($A10,'KPI Dashboard OT'!$B:$B,0))))*$B10,"") | K10: =IFERROR(IF($C10="Physio_North",INDEX('KPI Dashboard North'!$J:$J,MATCH($A10,'KPI Dashboard North'!$B:$B,0)),IF($C10="Physio_South",INDEX('KPI Dashboard South'!$J:$J,MATCH($A10,'KPI Dashboard South'!$B:$B,0)),INDEX('KPI Dashboard OT'!$J:$J,MATCH($A10,'KPI Dashboard OT'!$B:$B,0))))*$B10,"") | L10: =IFERROR(IF($C10="Physio_North",INDEX('KPI Dashboard North'!$K:$K,MATCH($A10,'KPI Dashboard North'!$B:$B,0)),IF($C10="Physio_South",INDEX('KPI Dashboard South'!$K:$K,MATCH($A10,'KPI Dashboard South'!$B:$B,0)),INDEX('KPI Dashboard OT'!$K:$K,MATCH($A10,'KPI Dashboard OT'!$B:$B,0))))*$B10,"") | M10: =IFERROR(IF($C10="Physio_North",INDEX('KPI Dashboard North'!$L:$L,MATCH($A10,'KPI Dashboard North'!$B:$B,0)),IF($C10="Physio_South",INDEX('KPI Dashboard South'!$L:$L,MATCH($A10,'KPI Dashboard South'!$B:$B,0)),INDEX('KPI Dashboard OT'!$L:$L,MATCH($A10,'KPI Dashboard OT'!$B:$B,0))))*$B10,"") | N10: =IFERROR(IF($C10="Physio_North",INDEX('KPI Dashboard North'!$M:$M,MATCH($A10,'KPI Dashboard North'!$B:$B,0)),IF($C10="Physio_South",INDEX('KPI Dashboard South'!$M:$M,MATCH($A10,'KPI Dashboard South'!$B:$B,0)),INDEX('KPI Dashboard OT'!$M:$M,MATCH($A10,'KPI Dashboard OT'!$B:$B,0))))*$B10,"") | O10: =IFERROR(IF($C10="Physio_North",INDEX('KPI Dashboard North'!$N:$N,MATCH($A10,'KPI Dashboard North'!$B:$B,0)),IF($C10="Physio_South",INDEX('KPI Dashboard South'!$N:$N,MATCH($A10,'KPI Dashboard South'!$B:$B,0)),INDEX('KPI Dashboard OT'!$N:$N,MATCH($A10,'KPI Dashboard OT'!$B:$B,0))))*$B10,"")
A11: Jaymee | B11: 1 | C11: Physio_North | D11: =IFERROR(IF($C11="Physio_North",INDEX('KPI Dashboard North'!$C:$C,MATCH($A11,'KPI Dashboard North'!$B:$B,0)),IF($C11="Physio_South",INDEX('KPI Dashboard South'!$C:$C,MATCH($A11,'KPI Dashboard South'!$B:$B,0)),INDEX('KPI Dashboard OT'!$C:$C,MATCH($A11,'KPI Dashboard OT'!$B:$B,0))))*B11,"") | E11: =IFERROR(IF($C11="Physio_North",INDEX('KPI Dashboard North'!$D:$D,MATCH($A11,'KPI Dashboard North'!$B:$B,0)),IF($C11="Physio_South",INDEX('KPI Dashboard South'!$D:$D,MATCH($A11,'KPI Dashboard South'!$B:$B,0)),INDEX('KPI Dashboard OT'!$D:$D,MATCH($A11,'KPI Dashboard OT'!$B:$B,0))))*$B11,"") | F11: =IFERROR(IF($C11="Physio_North",INDEX('KPI Dashboard North'!$E:$E,MATCH($A11,'KPI Dashboard North'!$B:$B,0)),IF($C11="Physio_South",INDEX('KPI Dashboard South'!$E:$E,MATCH($A11,'KPI Dashboard South'!$B:$B,0)),INDEX('KPI Dashboard OT'!$E:$E,MATCH($A11,'KPI Dashboard OT'!$B:$B,0))))*$B11,"") | G11: =IFERROR(IF($C11="Physio_North",INDEX('KPI Dashboard North'!$F:$F,MATCH($A11,'KPI Dashboard North'!$B:$B,0)),IF($C11="Physio_South",INDEX('KPI Dashboard South'!$F:$F,MATCH($A11,'KPI Dashboard South'!$B:$B,0)),INDEX('KPI Dashboard OT'!$F:$F,MATCH($A11,'KPI Dashboard OT'!$B:$B,0))))*$B11,"") | H11: =IFERROR(IF($C11="Physio_North",INDEX('KPI Dashboard North'!$G:$G,MATCH($A11,'KPI Dashboard North'!$B:$B,0)),IF($C11="Physio_South",INDEX('KPI Dashboard South'!$G:$G,MATCH($A11,'KPI Dashboard South'!$B:$B,0)),INDEX('KPI Dashboard OT'!$G:$G,MATCH($A11,'KPI Dashboard OT'!$B:$B,0))))*$B11,"") | I11: =IFERROR(IF($C11="Physio_North",INDEX('KPI Dashboard North'!$H:$H,MATCH($A11,'KPI Dashboard North'!$B:$B,0)),IF($C11="Physio_South",INDEX('KPI Dashboard South'!$H:$H,MATCH($A11,'KPI Dashboard South'!$B:$B,0)),INDEX('KPI Dashboard OT'!$H:$H,MATCH($A11,'KPI Dashboard OT'!$B:$B,0))))*$B11,"") | J11: =IFERROR(IF($C11="Physio_North",INDEX('KPI Dashboard North'!$I:$I,MATCH($A11,'KPI Dashboard North'!$B:$B,0)),IF($C11="Physio_South",INDEX('KPI Dashboard South'!$I:$I,MATCH($A11,'KPI Dashboard South'!$B:$B,0)),INDEX('KPI Dashboard OT'!$I:$I,MATCH($A11,'KPI Dashboard OT'!$B:$B,0))))*$B11,"") | K11: =IFERROR(IF($C11="Physio_North",INDEX('KPI Dashboard North'!$J:$J,MATCH($A11,'KPI Dashboard North'!$B:$B,0)),IF($C11="Physio_South",INDEX('KPI Dashboard South'!$J:$J,MATCH($A11,'KPI Dashboard South'!$B:$B,0)),INDEX('KPI Dashboard OT'!$J:$J,MATCH($A11,'KPI Dashboard OT'!$B:$B,0))))*$B11,"") | L11: =IFERROR(IF($C11="Physio_North",INDEX('KPI Dashboard North'!$K:$K,MATCH($A11,'KPI Dashboard North'!$B:$B,0)),IF($C11="Physio_South",INDEX('KPI Dashboard South'!$K:$K,MATCH($A11,'KPI Dashboard South'!$B:$B,0)),INDEX('KPI Dashboard OT'!$K:$K,MATCH($A11,'KPI Dashboard OT'!$B:$B,0))))*$B11,"") | M11: =IFERROR(IF($C11="Physio_North",INDEX('KPI Dashboard North'!$L:$L,MATCH($A11,'KPI Dashboard North'!$B:$B,0)),IF($C11="Physio_South",INDEX('KPI Dashboard South'!$L:$L,MATCH($A11,'KPI Dashboard South'!$B:$B,0)),INDEX('KPI Dashboard OT'!$L:$L,MATCH($A11,'KPI Dashboard OT'!$B:$B,0))))*$B11,"") | N11: =IFERROR(IF($C11="Physio_North",INDEX('KPI Dashboard North'!$M:$M,MATCH($A11,'KPI Dashboard North'!$B:$B,0)),IF($C11="Physio_South",INDEX('KPI Dashboard South'!$M:$M,MATCH($A11,'KPI Dashboard South'!$B:$B,0)),INDEX('KPI Dashboard OT'!$M:$M,MATCH($A11,'KPI Dashboard OT'!$B:$B,0))))*$B11,"") | O11: =IFERROR(IF($C11="Physio_North",INDEX('KPI Dashboard North'!$N:$N,MATCH($A11,'KPI Dashboard North'!$B:$B,0)),IF($C11="Physio_South",INDEX('KPI Dashboard South'!$N:$N,MATCH($A11,'KPI Dashboard South'!$B:$B,0)),INDEX('KPI Dashboard OT'!$N:$N,MATCH($A11,'KPI Dashboard OT'!$B:$B,0))))*$B11,"")
A12: Tom | B12: 0.4 | C12: Physio_South | D12: =IFERROR(IF($C12="Physio_North",INDEX('KPI Dashboard North'!$C:$C,MATCH($A12,'KPI Dashboard North'!$B:$B,0)),IF($C12="Physio_South",INDEX('KPI Dashboard South'!$C:$C,MATCH($A12,'KPI Dashboard South'!$B:$B,0)),INDEX('KPI Dashboard OT'!$C:$C,MATCH($A12,'KPI Dashboard OT'!$B:$B,0))))*B12,"") | E12: =IFERROR(IF($C12="Physio_North",INDEX('KPI Dashboard North'!$D:$D,MATCH($A12,'KPI Dashboard North'!$B:$B,0)),IF($C12="Physio_South",INDEX('KPI Dashboard South'!$D:$D,MATCH($A12,'KPI Dashboard South'!$B:$B,0)),INDEX('KPI Dashboard OT'!$D:$D,MATCH($A12,'KPI Dashboard OT'!$B:$B,0))))*$B12,"") | F12: =IFERROR(IF($C12="Physio_North",INDEX('KPI Dashboard North'!$E:$E,MATCH($A12,'KPI Dashboard North'!$B:$B,0)),IF($C12="Physio_South",INDEX('KPI Dashboard South'!$E:$E,MATCH($A12,'KPI Dashboard South'!$B:$B,0)),INDEX('KPI Dashboard OT'!$E:$E,MATCH($A12,'KPI Dashboard OT'!$B:$B,0))))*$B12,"") | G12: =IFERROR(IF($C12="Physio_North",INDEX('KPI Dashboard North'!$F:$F,MATCH($A12,'KPI Dashboard North'!$B:$B,0)),IF($C12="Physio_South",INDEX('KPI Dashboard South'!$F:$F,MATCH($A12,'KPI Dashboard South'!$B:$B,0)),INDEX('KPI Dashboard OT'!$F:$F,MATCH($A12,'KPI Dashboard OT'!$B:$B,0))))*$B12,"") | H12: =IFERROR(IF($C12="Physio_North",INDEX('KPI Dashboard North'!$G:$G,MATCH($A12,'KPI Dashboard North'!$B:$B,0)),IF($C12="Physio_South",INDEX('KPI Dashboard South'!$G:$G,MATCH($A12,'KPI Dashboard South'!$B:$B,0)),INDEX('KPI Dashboard OT'!$G:$G,MATCH($A12,'KPI Dashboard OT'!$B:$B,0))))*$B12,"") | I12: =IFERROR(IF($C12="Physio_North",INDEX('KPI Dashboard North'!$H:$H,MATCH($A12,'KPI Dashboard North'!$B:$B,0)),IF($C12="Physio_South",INDEX('KPI Dashboard South'!$H:$H,MATCH($A12,'KPI Dashboard South'!$B:$B,0)),INDEX('KPI Dashboard OT'!$H:$H,MATCH($A12,'KPI Dashboard OT'!$B:$B,0))))*$B12,"") | J12: =IFERROR(IF($C12="Physio_North",INDEX('KPI Dashboard North'!$I:$I,MATCH($A12,'KPI Dashboard North'!$B:$B,0)),IF($C12="Physio_South",INDEX('KPI Dashboard South'!$I:$I,MATCH($A12,'KPI Dashboard South'!$B:$B,0)),INDEX('KPI Dashboard OT'!$I:$I,MATCH($A12,'KPI Dashboard OT'!$B:$B,0))))*$B12,"") | K12: =IFERROR(IF($C12="Physio_North",INDEX('KPI Dashboard North'!$J:$J,MATCH($A12,'KPI Dashboard North'!$B:$B,0)),IF($C12="Physio_South",INDEX('KPI Dashboard South'!$J:$J,MATCH($A12,'KPI Dashboard South'!$B:$B,0)),INDEX('KPI Dashboard OT'!$J:$J,MATCH($A12,'KPI Dashboard OT'!$B:$B,0))))*$B12,"") | L12: =IFERROR(IF($C12="Physio_North",INDEX('KPI Dashboard North'!$K:$K,MATCH($A12,'KPI Dashboard North'!$B:$B,0)),IF($C12="Physio_South",INDEX('KPI Dashboard South'!$K:$K,MATCH($A12,'KPI Dashboard South'!$B:$B,0)),INDEX('KPI Dashboard OT'!$K:$K,MATCH($A12,'KPI Dashboard OT'!$B:$B,0))))*$B12,"") | M12: =IFERROR(IF($C12="Physio_North",INDEX('KPI Dashboard North'!$L:$L,MATCH($A12,'KPI Dashboard North'!$B:$B,0)),IF($C12="Physio_South",INDEX('KPI Dashboard South'!$L:$L,MATCH($A12,'KPI Dashboard South'!$B:$B,0)),INDEX('KPI Dashboard OT'!$L:$L,MATCH($A12,'KPI Dashboard OT'!$B:$B,0))))*$B12,"") | N12: =IFERROR(IF($C12="Physio_North",INDEX('KPI Dashboard North'!$M:$M,MATCH($A12,'KPI Dashboard North'!$B:$B,0)),IF($C12="Physio_South",INDEX('KPI Dashboard South'!$M:$M,MATCH($A12,'KPI Dashboard South'!$B:$B,0)),INDEX('KPI Dashboard OT'!$M:$M,MATCH($A12,'KPI Dashboard OT'!$B:$B,0))))*$B12,"") | O12: =IFERROR(IF($C12="Physio_North",INDEX('KPI Dashboard North'!$N:$N,MATCH($A12,'KPI Dashboard North'!$B:$B,0)),IF($C12="Physio_South",INDEX('KPI Dashboard South'!$N:$N,MATCH($A12,'KPI Dashboard South'!$B:$B,0)),INDEX('KPI Dashboard OT'!$N:$N,MATCH($A12,'KPI Dashboard OT'!$B:$B,0))))*$B12,"")
A13: Maddie | B13: 0.2 | C13: Physio_South | D13: =IFERROR(IF($C13="Physio_North",INDEX('KPI Dashboard North'!$C:$C,MATCH($A13,'KPI Dashboard North'!$B:$B,0)),IF($C13="Physio_South",INDEX('KPI Dashboard South'!$C:$C,MATCH($A13,'KPI Dashboard South'!$B:$B,0)),INDEX('KPI Dashboard OT'!$C:$C,MATCH($A13,'KPI Dashboard OT'!$B:$B,0))))*B13,"") | E13: =IFERROR(IF($C13="Physio_North",INDEX('KPI Dashboard North'!$D:$D,MATCH($A13,'KPI Dashboard North'!$B:$B,0)),IF($C13="Physio_South",INDEX('KPI Dashboard South'!$D:$D,MATCH($A13,'KPI Dashboard South'!$B:$B,0)),INDEX('KPI Dashboard OT'!$D:$D,MATCH($A13,'KPI Dashboard OT'!$B:$B,0))))*$B13,"") | F13: =IFERROR(IF($C13="Physio_North",INDEX('KPI Dashboard North'!$E:$E,MATCH($A13,'KPI Dashboard North'!$B:$B,0)),IF($C13="Physio_South",INDEX('KPI Dashboard South'!$E:$E,MATCH($A13,'KPI Dashboard South'!$B:$B,0)),INDEX('KPI Dashboard OT'!$E:$E,MATCH($A13,'KPI Dashboard OT'!$B:$B,0))))*$B13,"") | G13: =IFERROR(IF($C13="Physio_North",INDEX('KPI Dashboard North'!$F:$F,MATCH($A13,'KPI Dashboard North'!$B:$B,0)),IF($C13="Physio_South",INDEX('KPI Dashboard South'!$F:$F,MATCH($A13,'KPI Dashboard South'!$B:$B,0)),INDEX('KPI Dashboard OT'!$F:$F,MATCH($A13,'KPI Dashboard OT'!$B:$B,0))))*$B13,"") | H13: =IFERROR(IF($C13="Physio_North",INDEX('KPI Dashboard North'!$G:$G,MATCH($A13,'KPI Dashboard North'!$B:$B,0)),IF($C13="Physio_South",INDEX('KPI Dashboard South'!$G:$G,MATCH($A13,'KPI Dashboard South'!$B:$B,0)),INDEX('KPI Dashboard OT'!$G:$G,MATCH($A13,'KPI Dashboard OT'!$B:$B,0))))*$B13,"") | I13: =IFERROR(IF($C13="Physio_North",INDEX('KPI Dashboard North'!$H:$H,MATCH($A13,'KPI Dashboard North'!$B:$B,0)),IF($C13="Physio_South",INDEX('KPI Dashboard South'!$H:$H,MATCH($A13,'KPI Dashboard South'!$B:$B,0)),INDEX('KPI Dashboard OT'!$H:$H,MATCH($A13,'KPI Dashboard OT'!$B:$B,0))))*$B13,"") | J13: =IFERROR(IF($C13="Physio_North",INDEX('KPI Dashboard North'!$I:$I,MATCH($A13,'KPI Dashboard North'!$B:$B,0)),IF($C13="Physio_South",INDEX('KPI Dashboard South'!$I:$I,MATCH($A13,'KPI Dashboard South'!$B:$B,0)),INDEX('KPI Dashboard OT'!$I:$I,MATCH($A13,'KPI Dashboard OT'!$B:$B,0))))*$B13,"") | K13: =IFERROR(IF($C13="Physio_North",INDEX('KPI Dashboard North'!$J:$J,MATCH($A13,'KPI Dashboard North'!$B:$B,0)),IF($C13="Physio_South",INDEX('KPI Dashboard South'!$J:$J,MATCH($A13,'KPI Dashboard South'!$B:$B,0)),INDEX('KPI Dashboard OT'!$J:$J,MATCH($A13,'KPI Dashboard OT'!$B:$B,0))))*$B13,"") | L13: =IFERROR(IF($C13="Physio_North",INDEX('KPI Dashboard North'!$K:$K,MATCH($A13,'KPI Dashboard North'!$B:$B,0)),IF($C13="Physio_South",INDEX('KPI Dashboard South'!$K:$K,MATCH($A13,'KPI Dashboard South'!$B:$B,0)),INDEX('KPI Dashboard OT'!$K:$K,MATCH($A13,'KPI Dashboard OT'!$B:$B,0))))*$B13,"") | M13: =IFERROR(IF($C13="Physio_North",INDEX('KPI Dashboard North'!$L:$L,MATCH($A13,'KPI Dashboard North'!$B:$B,0)),IF($C13="Physio_South",INDEX('KPI Dashboard South'!$L:$L,MATCH($A13,'KPI Dashboard South'!$B:$B,0)),INDEX('KPI Dashboard OT'!$L:$L,MATCH($A13,'KPI Dashboard OT'!$B:$B,0))))*$B13,"") | N13: =IFERROR(IF($C13="Physio_North",INDEX('KPI Dashboard North'!$M:$M,MATCH($A13,'KPI Dashboard North'!$B:$B,0)),IF($C13="Physio_South",INDEX('KPI Dashboard South'!$M:$M,MATCH($A13,'KPI Dashboard South'!$B:$B,0)),INDEX('KPI Dashboard OT'!$M:$M,MATCH($A13,'KPI Dashboard OT'!$B:$B,0))))*$B13,"") | O13: =IFERROR(IF($C13="Physio_North",INDEX('KPI Dashboard North'!$N:$N,MATCH($A13,'KPI Dashboard North'!$B:$B,0)),IF($C13="Physio_South",INDEX('KPI Dashboard South'!$N:$N,MATCH($A13,'KPI Dashboard South'!$B:$B,0)),INDEX('KPI Dashboard OT'!$N:$N,MATCH($A13,'KPI Dashboard OT'!$B:$B,0))))*$B13,"")
... A29: Bao | B29: 1 | C29: OT | D29: =IFERROR(IF($C29="Physio_North",INDEX('KPI Dashboard North'!$C:$C,MATCH($A29,'KPI Dashboard North'!$B:$B,0)),IF($C29="Physio_South",INDEX('KPI Dashboard South'!$C:$C,MATCH($A29,'KPI Dashboard South'!$B:$B,0)),INDEX('KPI Dashboard OT'!$C:$C,MATCH($A29,'KPI Dashboard OT'!$B:$B,0))))*B29,"") | E29: =IFERROR(IF($C29="Physio_North",INDEX('KPI Dashboard North'!$D:$D,MATCH($A29,'KPI Dashboard North'!$B:$B,0)),IF($C29="Physio_South",INDEX('KPI Dashboard South'!$D:$D,MATCH($A29,'KPI Dashboard South'!$B:$B,0)),INDEX('KPI Dashboard OT'!$D:$D,MATCH($A29,'KPI Dashboard OT'!$B:$B,0))))*$B29,"") | F29: =IFERROR(IF($C29="Physio_North",INDEX('KPI Dashboard North'!$E:$E,MATCH($A29,'KPI Dashboard North'!$B:$B,0)),IF($C29="Physio_South",INDEX('KPI Dashboard South'!$E:$E,MATCH($A29,'KPI Dashboard South'!$B:$B,0)),INDEX('KPI Dashboard OT'!$E:$E,MATCH($A29,'KPI Dashboard OT'!$B:$B,0))))*$B29,"") | G29: =IFERROR(IF($C29="Physio_North",INDEX('KPI Dashboard North'!$F:$F,MATCH($A29,'KPI Dashboard North'!$B:$B,0)),IF($C29="Physio_South",INDEX('KPI Dashboard South'!$F:$F,MATCH($A29,'KPI Dashboard South'!$B:$B,0)),INDEX('KPI Dashboard OT'!$F:$F,MATCH($A29,'KPI Dashboard OT'!$B:$B,0))))*$B29,"") | H29: =IFERROR(IF($C29="Physio_North",INDEX('KPI Dashboard North'!$G:$G,MATCH($A29,'KPI Dashboard North'!$B:$B,0)),IF($C29="Physio_South",INDEX('KPI Dashboard South'!$G:$G,MATCH($A29,'KPI Dashboard South'!$B:$B,0)),INDEX('KPI Dashboard OT'!$G:$G,MATCH($A29,'KPI Dashboard OT'!$B:$B,0))))*$B29,"") | I29: =IFERROR(IF($C29="Physio_North",INDEX('KPI Dashboard North'!$H:$H,MATCH($A29,'KPI Dashboard North'!$B:$B,0)),IF($C29="Physio_South",INDEX('KPI Dashboard South'!$H:$H,MATCH($A29,'KPI Dashboard South'!$B:$B,0)),INDEX('KPI Dashboard OT'!$H:$H,MATCH($A29,'KPI Dashboard OT'!$B:$B,0))))*$B29,"") | J29: =IFERROR(IF($C29="Physio_North",INDEX('KPI Dashboard North'!$I:$I,MATCH($A29,'KPI Dashboard North'!$B:$B,0)),IF($C29="Physio_South",INDEX('KPI Dashboard South'!$I:$I,MATCH($A29,'KPI Dashboard South'!$B:$B,0)),INDEX('KPI Dashboard OT'!$I:$I,MATCH($A29,'KPI Dashboard OT'!$B:$B,0))))*$B29,"") | K29: =IFERROR(IF($C29="Physio_North",INDEX('KPI Dashboard North'!$J:$J,MATCH($A29,'KPI Dashboard North'!$B:$B,0)),IF($C29="Physio_South",INDEX('KPI Dashboard South'!$J:$J,MATCH($A29,'KPI Dashboard South'!$B:$B,0)),INDEX('KPI Dashboard OT'!$J:$J,MATCH($A29,'KPI Dashboard OT'!$B:$B,0))))*$B29,"") | L29: =IFERROR(IF($C29="Physio_North",INDEX('KPI Dashboard North'!$K:$K,MATCH($A29,'KPI Dashboard North'!$B:$B,0)),IF($C29="Physio_South",INDEX('KPI Dashboard South'!$K:$K,MATCH($A29,'KPI Dashboard South'!$B:$B,0)),INDEX('KPI Dashboard OT'!$K:$K,MATCH($A29,'KPI Dashboard OT'!$B:$B,0))))*$B29,"") | M29: =IFERROR(IF($C29="Physio_North",INDEX('KPI Dashboard North'!$L:$L,MATCH($A29,'KPI Dashboard North'!$B:$B,0)),IF($C29="Physio_South",INDEX('KPI Dashboard South'!$L:$L,MATCH($A29,'KPI Dashboard South'!$B:$B,0)),INDEX('KPI Dashboard OT'!$L:$L,MATCH($A29,'KPI Dashboard OT'!$B:$B,0))))*$B29,"") | N29: =IFERROR(IF($C29="Physio_North",INDEX('KPI Dashboard North'!$M:$M,MATCH($A29,'KPI Dashboard North'!$B:$B,0)),IF($C29="Physio_South",INDEX('KPI Dashboard South'!$M:$M,MATCH($A29,'KPI Dashboard South'!$B:$B,0)),INDEX('KPI Dashboard OT'!$M:$M,MATCH($A29,'KPI Dashboard OT'!$B:$B,0))))*$B29,"") | O29: =IFERROR(IF($C29="Physio_North",INDEX('KPI Dashboard North'!$N:$N,MATCH($A29,'KPI Dashboard North'!$B:$B,0)),IF($C29="Physio_South",INDEX('KPI Dashboard South'!$N:$N,MATCH($A29,'KPI Dashboard South'!$B:$B,0)),INDEX('KPI Dashboard OT'!$N:$N,MATCH($A29,'KPI Dashboard OT'!$B:$B,0))))*$B29,"")
D30: =IFERROR(IF($C30="Physio_North",INDEX('KPI Dashboard North'!$C:$C,MATCH($A30,'KPI Dashboard North'!$B:$B,0)),IF($C30="Physio_South",INDEX('KPI Dashboard South'!$C:$C,MATCH($A30,'KPI Dashboard South'!$B:$B,0)),INDEX('KPI Dashboard OT'!$C:$C,MATCH($A30,'KPI Dashboard OT'!$B:$B,0))))*B30,"") | E30: =IFERROR(IF($C30="Physio_North",INDEX('KPI Dashboard North'!$D:$D,MATCH($A30,'KPI Dashboard North'!$B:$B,0)),IF($C30="Physio_South",INDEX('KPI Dashboard South'!$D:$D,MATCH($A30,'KPI Dashboard South'!$B:$B,0)),INDEX('KPI Dashboard OT'!$D:$D,MATCH($A30,'KPI Dashboard OT'!$B:$B,0))))*$B30,"") | F30: =IFERROR(IF($C30="Physio_North",INDEX('KPI Dashboard North'!$E:$E,MATCH($A30,'KPI Dashboard North'!$B:$B,0)),IF($C30="Physio_South",INDEX('KPI Dashboard South'!$E:$E,MATCH($A30,'KPI Dashboard South'!$B:$B,0)),INDEX('KPI Dashboard OT'!$E:$E,MATCH($A30,'KPI Dashboard OT'!$B:$B,0))))*$B30,"") | G30: =IFERROR(IF($C30="Physio_North",INDEX('KPI Dashboard North'!$F:$F,MATCH($A30,'KPI Dashboard North'!$B:$B,0)),IF($C30="Physio_South",INDEX('KPI Dashboard South'!$F:$F,MATCH($A30,'KPI Dashboard South'!$B:$B,0)),INDEX('KPI Dashboard OT'!$F:$F,MATCH($A30,'KPI Dashboard OT'!$B:$B,0))))*$B30,"") | H30: =IFERROR(IF($C30="Physio_North",INDEX('KPI Dashboard North'!$G:$G,MATCH($A30,'KPI Dashboard North'!$B:$B,0)),IF($C30="Physio_South",INDEX('KPI Dashboard South'!$G:$G,MATCH($A30,'KPI Dashboard South'!$B:$B,0)),INDEX('KPI Dashboard OT'!$G:$G,MATCH($A30,'KPI Dashboard OT'!$B:$B,0))))*$B30,"") | I30: =IFERROR(IF($C30="Physio_North",INDEX('KPI Dashboard North'!$H:$H,MATCH($A30,'KPI Dashboard North'!$B:$B,0)),IF($C30="Physio_South",INDEX('KPI Dashboard South'!$H:$H,MATCH($A30,'KPI Dashboard South'!$B:$B,0)),INDEX('KPI Dashboard OT'!$H:$H,MATCH($A30,'KPI Dashboard OT'!$B:$B,0))))*$B30,"") | J30: =IFERROR(IF($C30="Physio_North",INDEX('KPI Dashboard North'!$I:$I,MATCH($A30,'KPI Dashboard North'!$B:$B,0)),IF($C30="Physio_South",INDEX('KPI Dashboard South'!$I:$I,MATCH($A30,'KPI Dashboard South'!$B:$B,0)),INDEX('KPI Dashboard OT'!$I:$I,MATCH($A30,'KPI Dashboard OT'!$B:$B,0))))*$B30,"") | K30: =IFERROR(IF($C30="Physio_North",INDEX('KPI Dashboard North'!$J:$J,MATCH($A30,'KPI Dashboard North'!$B:$B,0)),IF($C30="Physio_South",INDEX('KPI Dashboard South'!$J:$J,MATCH($A30,'KPI Dashboard South'!$B:$B,0)),INDEX('KPI Dashboard OT'!$J:$J,MATCH($A30,'KPI Dashboard OT'!$B:$B,0))))*$B30,"") | L30: =IFERROR(IF($C30="Physio_North",INDEX('KPI Dashboard North'!$K:$K,MATCH($A30,'KPI Dashboard North'!$B:$B,0)),IF($C30="Physio_South",INDEX('KPI Dashboard South'!$K:$K,MATCH($A30,'KPI Dashboard South'!$B:$B,0)),INDEX('KPI Dashboard OT'!$K:$K,MATCH($A30,'KPI Dashboard OT'!$B:$B,0))))*$B30,"") | M30: =IFERROR(IF($C30="Physio_North",INDEX('KPI Dashboard North'!$L:$L,MATCH($A30,'KPI Dashboard North'!$B:$B,0)),IF($C30="Physio_South",INDEX('KPI Dashboard South'!$L:$L,MATCH($A30,'KPI Dashboard South'!$B:$B,0)),INDEX('KPI Dashboard OT'!$L:$L,MATCH($A30,'KPI Dashboard OT'!$B:$B,0))))*$B30,"") | N30: =IFERROR(IF($C30="Physio_North",INDEX('KPI Dashboard North'!$M:$M,MATCH($A30,'KPI Dashboard North'!$B:$B,0)),IF($C30="Physio_South",INDEX('KPI Dashboard South'!$M:$M,MATCH($A30,'KPI Dashboard South'!$B:$B,0)),INDEX('KPI Dashboard OT'!$M:$M,MATCH($A30,'KPI Dashboard OT'!$B:$B,0))))*$B30,"") | O30: =IFERROR(IF($C30="Physio_North",INDEX('KPI Dashboard North'!$N:$N,MATCH($A30,'KPI Dashboard North'!$B:$B,0)),IF($C30="Physio_South",INDEX('KPI Dashboard South'!$N:$N,MATCH($A30,'KPI Dashboard South'!$B:$B,0)),INDEX('KPI Dashboard OT'!$N:$N,MATCH($A30,'KPI Dashboard OT'!$B:$B,0))))*$B30,"")
D31: =IFERROR(IF($C31="Physio_North",INDEX('KPI Dashboard North'!$C:$C,MATCH($A31,'KPI Dashboard North'!$B:$B,0)),IF($C31="Physio_South",INDEX('KPI Dashboard South'!$C:$C,MATCH($A31,'KPI Dashboard South'!$B:$B,0)),INDEX('KPI Dashboard OT'!$C:$C,MATCH($A31,'KPI Dashboard OT'!$B:$B,0))))*B31,"") | E31: =IFERROR(IF($C31="Physio_North",INDEX('KPI Dashboard North'!$D:$D,MATCH($A31,'KPI Dashboard North'!$B:$B,0)),IF($C31="Physio_South",INDEX('KPI Dashboard South'!$D:$D,MATCH($A31,'KPI Dashboard South'!$B:$B,0)),INDEX('KPI Dashboard OT'!$D:$D,MATCH($A31,'KPI Dashboard OT'!$B:$B,0))))*$B31,"") | F31: =IFERROR(IF($C31="Physio_North",INDEX('KPI Dashboard North'!$E:$E,MATCH($A31,'KPI Dashboard North'!$B:$B,0)),IF($C31="Physio_South",INDEX('KPI Dashboard South'!$E:$E,MATCH($A31,'KPI Dashboard South'!$B:$B,0)),INDEX('KPI Dashboard OT'!$E:$E,MATCH($A31,'KPI Dashboard OT'!$B:$B,0))))*$B31,"") | G31: =IFERROR(IF($C31="Physio_North",INDEX('KPI Dashboard North'!$F:$F,MATCH($A31,'KPI Dashboard North'!$B:$B,0)),IF($C31="Physio_South",INDEX('KPI Dashboard South'!$F:$F,MATCH($A31,'KPI Dashboard South'!$B:$B,0)),INDEX('KPI Dashboard OT'!$F:$F,MATCH($A31,'KPI Dashboard OT'!$B:$B,0))))*$B31,"") | H31: =IFERROR(IF($C31="Physio_North",INDEX('KPI Dashboard North'!$G:$G,MATCH($A31,'KPI Dashboard North'!$B:$B,0)),IF($C31="Physio_South",INDEX('KPI Dashboard South'!$G:$G,MATCH($A31,'KPI Dashboard South'!$B:$B,0)),INDEX('KPI Dashboard OT'!$G:$G,MATCH($A31,'KPI Dashboard OT'!$B:$B,0))))*$B31,"") | I31: =IFERROR(IF($C31="Physio_North",INDEX('KPI Dashboard North'!$H:$H,MATCH($A31,'KPI Dashboard North'!$B:$B,0)),IF($C31="Physio_South",INDEX('KPI Dashboard South'!$H:$H,MATCH($A31,'KPI Dashboard South'!$B:$B,0)),INDEX('KPI Dashboard OT'!$H:$H,MATCH($A31,'KPI Dashboard OT'!$B:$B,0))))*$B31,"") | J31: =IFERROR(IF($C31="Physio_North",INDEX('KPI Dashboard North'!$I:$I,MATCH($A31,'KPI Dashboard North'!$B:$B,0)),IF($C31="Physio_South",INDEX('KPI Dashboard South'!$I:$I,MATCH($A31,'KPI Dashboard South'!$B:$B,0)),INDEX('KPI Dashboard OT'!$I:$I,MATCH($A31,'KPI Dashboard OT'!$B:$B,0))))*$B31,"") | K31: =IFERROR(IF($C31="Physio_North",INDEX('KPI Dashboard North'!$J:$J,MATCH($A31,'KPI Dashboard North'!$B:$B,0)),IF($C31="Physio_South",INDEX('KPI Dashboard South'!$J:$J,MATCH($A31,'KPI Dashboard South'!$B:$B,0)),INDEX('KPI Dashboard OT'!$J:$J,MATCH($A31,'KPI Dashboard OT'!$B:$B,0))))*$B31,"") | L31: =IFERROR(IF($C31="Physio_North",INDEX('KPI Dashboard North'!$K:$K,MATCH($A31,'KPI Dashboard North'!$B:$B,0)),IF($C31="Physio_South",INDEX('KPI Dashboard South'!$K:$K,MATCH($A31,'KPI Dashboard South'!$B:$B,0)),INDEX('KPI Dashboard OT'!$K:$K,MATCH($A31,'KPI Dashboard OT'!$B:$B,0))))*$B31,"") | M31: =IFERROR(IF($C31="Physio_North",INDEX('KPI Dashboard North'!$L:$L,MATCH($A31,'KPI Dashboard North'!$B:$B,0)),IF($C31="Physio_South",INDEX('KPI Dashboard South'!$L:$L,MATCH($A31,'KPI Dashboard South'!$B:$B,0)),INDEX('KPI Dashboard OT'!$L:$L,MATCH($A31,'KPI Dashboard OT'!$B:$B,0))))*$B31,"") | N31: =IFERROR(IF($C31="Physio_North",INDEX('KPI Dashboard North'!$M:$M,MATCH($A31,'KPI Dashboard North'!$B:$B,0)),IF($C31="Physio_South",INDEX('KPI Dashboard South'!$M:$M,MATCH($A31,'KPI Dashboard South'!$B:$B,0)),INDEX('KPI Dashboard OT'!$M:$M,MATCH($A31,'KPI Dashboard OT'!$B:$B,0))))*$B31,"") | O31: =IFERROR(IF($C31="Physio_North",INDEX('KPI Dashboard North'!$N:$N,MATCH($A31,'KPI Dashboard North'!$B:$B,0)),IF($C31="Physio_South",INDEX('KPI Dashboard South'!$N:$N,MATCH($A31,'KPI Dashboard South'!$B:$B,0)),INDEX('KPI Dashboard OT'!$N:$N,MATCH($A31,'KPI Dashboard OT'!$B:$B,0))))*$B31,"")
D32: =IFERROR(IF($C32="Physio_North",INDEX('KPI Dashboard North'!$C:$C,MATCH($A32,'KPI Dashboard North'!$B:$B,0)),IF($C32="Physio_South",INDEX('KPI Dashboard South'!$C:$C,MATCH($A32,'KPI Dashboard South'!$B:$B,0)),INDEX('KPI Dashboard OT'!$C:$C,MATCH($A32,'KPI Dashboard OT'!$B:$B,0))))*B32,"") | E32: =IFERROR(IF($C32="Physio_North",INDEX('KPI Dashboard North'!$D:$D,MATCH($A32,'KPI Dashboard North'!$B:$B,0)),IF($C32="Physio_South",INDEX('KPI Dashboard South'!$D:$D,MATCH($A32,'KPI Dashboard South'!$B:$B,0)),INDEX('KPI Dashboard OT'!$D:$D,MATCH($A32,'KPI Dashboard OT'!$B:$B,0))))*$B32,"") | F32: =IFERROR(IF($C32="Physio_North",INDEX('KPI Dashboard North'!$E:$E,MATCH($A32,'KPI Dashboard North'!$B:$B,0)),IF($C32="Physio_South",INDEX('KPI Dashboard South'!$E:$E,MATCH($A32,'KPI Dashboard South'!$B:$B,0)),INDEX('KPI Dashboard OT'!$E:$E,MATCH($A32,'KPI Dashboard OT'!$B:$B,0))))*$B32,"") | G32: =IFERROR(IF($C32="Physio_North",INDEX('KPI Dashboard North'!$F:$F,MATCH($A32,'KPI Dashboard North'!$B:$B,0)),IF($C32="Physio_South",INDEX('KPI Dashboard South'!$F:$F,MATCH($A32,'KPI Dashboard South'!$B:$B,0)),INDEX('KPI Dashboard OT'!$F:$F,MATCH($A32,'KPI Dashboard OT'!$B:$B,0))))*$B32,"") | H32: =IFERROR(IF($C32="Physio_North",INDEX('KPI Dashboard North'!$G:$G,MATCH($A32,'KPI Dashboard North'!$B:$B,0)),IF($C32="Physio_South",INDEX('KPI Dashboard South'!$G:$G,MATCH($A32,'KPI Dashboard South'!$B:$B,0)),INDEX('KPI Dashboard OT'!$G:$G,MATCH($A32,'KPI Dashboard OT'!$B:$B,0))))*$B32,"") | I32: =IFERROR(IF($C32="Physio_North",INDEX('KPI Dashboard North'!$H:$H,MATCH($A32,'KPI Dashboard North'!$B:$B,0)),IF($C32="Physio_South",INDEX('KPI Dashboard South'!$H:$H,MATCH($A32,'KPI Dashboard South'!$B:$B,0)),INDEX('KPI Dashboard OT'!$H:$H,MATCH($A32,'KPI Dashboard OT'!$B:$B,0))))*$B32,"") | J32: =IFERROR(IF($C32="Physio_North",INDEX('KPI Dashboard North'!$I:$I,MATCH($A32,'KPI Dashboard North'!$B:$B,0)),IF($C32="Physio_South",INDEX('KPI Dashboard South'!$I:$I,MATCH($A32,'KPI Dashboard South'!$B:$B,0)),INDEX('KPI Dashboard OT'!$I:$I,MATCH($A32,'KPI Dashboard OT'!$B:$B,0))))*$B32,"") | K32: =IFERROR(IF($C32="Physio_North",INDEX('KPI Dashboard North'!$J:$J,MATCH($A32,'KPI Dashboard North'!$B:$B,0)),IF($C32="Physio_South",INDEX('KPI Dashboard South'!$J:$J,MATCH($A32,'KPI Dashboard South'!$B:$B,0)),INDEX('KPI Dashboard OT'!$J:$J,MATCH($A32,'KPI Dashboard OT'!$B:$B,0))))*$B32,"") | L32: =IFERROR(IF($C32="Physio_North",INDEX('KPI Dashboard North'!$K:$K,MATCH($A32,'KPI Dashboard North'!$B:$B,0)),IF($C32="Physio_South",INDEX('KPI Dashboard South'!$K:$K,MATCH($A32,'KPI Dashboard South'!$B:$B,0)),INDEX('KPI Dashboard OT'!$K:$K,MATCH($A32,'KPI Dashboard OT'!$B:$B,0))))*$B32,"") | M32: =IFERROR(IF($C32="Physio_North",INDEX('KPI Dashboard North'!$L:$L,MATCH($A32,'KPI Dashboard North'!$B:$B,0)),IF($C32="Physio_South",INDEX('KPI Dashboard South'!$L:$L,MATCH($A32,'KPI Dashboard South'!$B:$B,0)),INDEX('KPI Dashboard OT'!$L:$L,MATCH($A32,'KPI Dashboard OT'!$B:$B,0))))*$B32,"") | N32: =IFERROR(IF($C32="Physio_North",INDEX('KPI Dashboard North'!$M:$M,MATCH($A32,'KPI Dashboard North'!$B:$B,0)),IF($C32="Physio_South",INDEX('KPI Dashboard South'!$M:$M,MATCH($A32,'KPI Dashboard South'!$B:$B,0)),INDEX('KPI Dashboard OT'!$M:$M,MATCH($A32,'KPI Dashboard OT'!$B:$B,0))))*$B32,"") | O32: =IFERROR(IF($C32="Physio_North",INDEX('KPI Dashboard North'!$N:$N,MATCH($A32,'KPI Dashboard North'!$B:$B,0)),IF($C32="Physio_South",INDEX('KPI Dashboard South'!$N:$N,MATCH($A32,'KPI Dashboard South'!$B:$B,0)),INDEX('KPI Dashboard OT'!$N:$N,MATCH($A32,'KPI Dashboard OT'!$B:$B,0))))*$B32,"")
